Workbook
Name IQ_CH: 110000
Name IQ_CQ: 5000
Name IQ_CY: 10000
Name IQ_DAILY: 500000
Name IQ_FH: 100000
Name IQ_FQ: 500
Name IQ_FY: 1000
Name IQ_LTM: 2000
Name IQ_MONTH: 15000
Name IQ_NTM: 6000
Name IQ_WEEK: 50000
Name IQ_YTD: 3000
Name UPDATE: '[1]Data Sheet'!$E$1
Name UPDATE: 'Data Sheet'!$E$1

Sheet Financials>

Sheet HistoricalFS
B2: ='Data Sheet'!B1 -> GODREJ CONSUMER PRODUCTS LTD
B3: (GODREJCP | BSE Code: 532424)
B5: ="Historical Financial Statement - "&'Data Sheet'!B1 -> Historical Financial Statement - GODREJ CONSUMER PRODUCTS LTD
B6: Years | C6: ='Data Sheet'!B16 -> 42094 | D6: ='Data Sheet'!C16 -> 42460 | E6: ='Data Sheet'!D16 -> 42825 | F6: ='Data Sheet'!E16 -> 43190 | G6: ='Data Sheet'!F16 -> 43555 | H6: ='Data Sheet'!G16 -> 43921 | I6: ='Data Sheet'!H16 -> 44286 | J6: ='Data Sheet'!I16 -> 44651 | ... L6: ='Data Sheet'!K16 -> 45382
A8: # | B8: Income Statement
B9: Sales | C9: =IFERROR('Data Sheet'!B17,0) -> 8273.15 | D9: =IFERROR('Data Sheet'!C17,0) -> 8423.88 | E9: =IFERROR('Data Sheet'!D17,0) -> 9267.91 | F9: =IFERROR('Data Sheet'!E17,0) -> 9847.43 | G9: =IFERROR('Data Sheet'!F17,0) -> 10314.34 | H9: =IFERROR('Data Sheet'!G17,0) -> 9910.8 | I9: =IFERROR('Data Sheet'!H17,0) -> 11028.62 | J9: =IFERROR('Data Sheet'!I17,0) -> 12276.5 | ... L9: =IFERROR('Data Sheet'!K17,0) -> 14096.11
B10: Sales Growth | C10: - | D10: =D9/C9-1 -> 0.018219179 | E10: =E9/D9-1 -> 0.10019492 | F10: =F9/E9-1 -> 0.06252974 | G10: =G9/F9-1 -> 0.047414402 | H10: =H9/G9-1 -> -0.039124171 | I10: =I9/H9-1 -> 0.11278807 | J10: =J9/I9-1 -> 0.11314924 | K10: =K9/J9-1 -> 0.084671527 | L10: =L9/K9-1 -> 0.058586795
B12: COGS | C12: =IFERROR(SUM('Data Sheet'!B18,'Data Sheet'!B20:B22)-1*'Data Sheet'!B19,0) -> 4952.36 | D12: =IFERROR(SUM('Data Sheet'!C18,'Data Sheet'!C20:C22)-1*'Data Sheet'!C19,0) -> 5157.59 | E12: =IFERROR(SUM('Data Sheet'!D18,'Data Sheet'!D20:D22)-1*'Data Sheet'!D19,0) -> 5512.85 | F12: =IFERROR(SUM('Data Sheet'!E18,'Data Sheet'!E20:E22)-1*'Data Sheet'!E19,0) -> 5751.63 | G12: =IFERROR(SUM('Data Sheet'!F18,'Data Sheet'!F20:F22)-1*'Data Sheet'!F19,0) -> 6071.83 | H12: =IFERROR(SUM('Data Sheet'!G18,'Data Sheet'!G20:G22)-1*'Data Sheet'!G19,0) -> 5777.48 | I12: =IFERROR(SUM('Data Sheet'!H18,'Data Sheet'!H20:H22)-1*'Data Sheet'!H19,0) -> 6556.24 | J12: =IFERROR(SUM('Data Sheet'!I18,'Data Sheet'!I20:I22)-1*'Data Sheet'!I19,0) -> 7743.02 | ... L12: =IFERROR(SUM('Data Sheet'!K18,'Data Sheet'!K20:K22)-1*'Data Sheet'!K19,0) -> 8140.92
B13: COGS % Sales | C13: =C12/C9 -> 0.59860633 | D13: =D12/D9 -> 0.61225825 | E13: =E12/E9 -> 0.59483206 | F13: =F12/F9 -> 0.58407422 | G13: =G12/G9 -> 0.58867848 | H13: =H12/H9 -> 0.5829479 | I13: =I12/I9 -> 0.5944751 | J13: =J12/J9 -> 0.63071885 | ... L13: =L12/L9 -> 0.57752955
B15: Gross Profit | C15: =C9-C12 -> 3320.79 | D15: =D9-D12 -> 3266.29 | E15: =E9-E12 -> 3755.06 | F15: =F9-F12 -> 4095.8 | G15: =G9-G12 -> 4242.51 | H15: =H9-H12 -> 4133.32 | I15: =I9-I12 -> 4472.38 | J15: =J9-J12 -> 4533.48 | ... L15: =L9-L12 -> 5955.19
B16: Gross Margins | C16: =C15/C9 -> 0.40139367 | D16: =D15/D9 -> 0.38774175 | E16: =E15/E9 -> 0.40516794 | F16: =F15/F9 -> 0.41592578 | G16: =G15/G9 -> 0.41132152 | H16: =H15/H9 -> 0.4170521 | I16: =I15/I9 -> 0.4055249 | J16: =J15/J9 -> 0.36928115 | ... L16: =L15/L9 -> 0.42247045
B18: Selling & General Expenses | C18: =IFERROR(SUM('Data Sheet'!B23:B24),0) -> 1941.84 | D18: =IFERROR(SUM('Data Sheet'!C23:C24),0) -> 1608.91 | E18: =IFERROR(SUM('Data Sheet'!D23:D24),0) -> 1848.35 | F18: =IFERROR(SUM('Data Sheet'!E23:E24),0) -> 2011.4 | G18: =IFERROR(SUM('Data Sheet'!F23:F24),0) -> 2110.94 | H18: =IFERROR(SUM('Data Sheet'!G23:G24),0) -> 1979.57 | I18: =IFERROR(SUM('Data Sheet'!H23:H24),0) -> 2073.12 | J18: =IFERROR(SUM('Data Sheet'!I23:I24),0) -> 2124.3 | ... L18: =IFERROR(SUM('Data Sheet'!K23:K24),0) -> 2997.87
B19: S&G Exp % Sales | C19: =C18/C9 -> 0.23471592 | D19: =D18/D9 -> 0.19099394 | E19: =E18/E9 -> 0.19943547 | F19: =F18/F9 -> 0.20425634 | G19: =G18/G9 -> 0.2046607 | H19: =H18/H9 -> 0.19973867 | I19: =I18/I9 -> 0.18797637 | J19: =J18/J9 -> 0.17303792 | ... L19: =L18/L9 -> 0.21267357
B21: EBITDA | C21: =C15-C18 -> 1378.95 | D21: =D15-D18 -> 1657.38 | E21: =E15-E18 -> 1906.71 | F21: =F15-F18 -> 2084.4 | G21: =G15-G18 -> 2131.57 | H21: =H15-H18 -> 2153.75 | I21: =I15-I18 -> 2399.26 | J21: =J15-J18 -> 2409.18 | ... L21: =L15-L18 -> 2957.32
B22: EBITDA Margins | C22: =C21/C9 -> 0.16667775 | D22: =D21/D9 -> 0.19674782 | E22: =E21/E9 -> 0.20573247 | F22: =F21/F9 -> 0.21166944 | G22: =G21/G9 -> 0.20666082 | H22: =H21/H9 -> 0.21731344 | I22: =I21/I9 -> 0.21754852 | J22: =J21/J9 -> 0.19624323 | ... L22: =L21/L9 -> 0.20979689
B24: Interest | C24: =IFERROR('Data Sheet'!B27,0) -> 112.46 | D24: =IFERROR('Data Sheet'!C27,0) -> 128.04 | E24: =IFERROR('Data Sheet'!D27,0) -> 154.19 | F24: =IFERROR('Data Sheet'!E27,0) -> 173.12 | G24: =IFERROR('Data Sheet'!F27,0) -> 238.21 | H24: =IFERROR('Data Sheet'!G27,0) -> 228.13 | I24: =IFERROR('Data Sheet'!H27,0) -> 137.65 | J24: =IFERROR('Data Sheet'!I27,0) -> 122.26 | ... L24: =IFERROR('Data Sheet'!K27,0) -> 309.57
B25: Interest % Sales | C25: =C24/C9 -> 0.013593371 | D25: =D24/D9 -> 0.015199647 | E25: =E24/E9 -> 0.016636976 | F25: =F24/F9 -> 0.017580221 | G25: =G24/G9 -> 0.023095031 | H25: =H24/H9 -> 0.023018323 | I25: =I24/I9 -> 0.012481163 | J25: =J24/J9 -> 0.0099588645 | ... L25: =L24/L9 -> 0.021961378
B27: Depreciation | C27: =IFERROR('Data Sheet'!B26,0) -> 90.78 | D27: =IFERROR('Data Sheet'!C26,0) -> 100.63 | E27: =IFERROR('Data Sheet'!D26,0) -> 141.57 | F27: =IFERROR('Data Sheet'!E26,0) -> 155.68 | G27: =IFERROR('Data Sheet'!F26,0) -> 169.98 | H27: =IFERROR('Data Sheet'!G26,0) -> 197.28 | I27: =IFERROR('Data Sheet'!H26,0) -> 203.85 | J27: =IFERROR('Data Sheet'!I26,0) -> 209.93 | ... L27: =IFERROR('Data Sheet'!K26,0) -> 240.96
B28: Depreciation%Sales | C28: =C27/C9 -> 0.010972846 | D28: =D27/D9 -> 0.011945802 | E28: =E27/E9 -> 0.015275289 | F28: =F27/F9 -> 0.015809201 | G28: =G27/G9 -> 0.016479969 | H28: =H27/H9 -> 0.019905558 | I28: =I27/I9 -> 0.018483727 | J28: =J27/J9 -> 0.017100151 | ... L28: =L27/L9 -> 0.017094078
B30: Earnings Before Tax | C30: =IFERROR(C21-SUM(C27,C24),0) -> 1175.71 | D30: =IFERROR(D21-SUM(D27,D24),0) -> 1428.71 | E30: =IFERROR(E21-SUM(E27,E24),0) -> 1610.95 | F30: =IFERROR(F21-SUM(F27,F24),0) -> 1755.6 | G30: =IFERROR(G21-SUM(G27,G24),0) -> 1723.38 | H30: =IFERROR(H21-SUM(H27,H24),0) -> 1728.34 | I30: =IFERROR(I21-SUM(I27,I24),0) -> 2057.76 | J30: =IFERROR(J21-SUM(J27,J24),0) -> 2076.99 | ... L30: =IFERROR(L21-SUM(L27,L24),0) -> 2406.79
B31: EBT % Sales | C31: =C30/C9 -> 0.14211153 | D31: =D30/D9 -> 0.16960237 | E31: =E30/E9 -> 0.1738202 | F31: =F30/F9 -> 0.17828002 | G31: =G30/G9 -> 0.16708582 | H31: =H30/H9 -> 0.17438955 | I31: =I30/I9 -> 0.18658363 | J31: =J30/J9 -> 0.16918421 | ... L31: =L30/L9 -> 0.17074143
B33: Tax | C33: =IFERROR('Data Sheet'!B29,0) -> 272.29 | D33: =IFERROR('Data Sheet'!C29,0) -> 336.05 | E33: =IFERROR('Data Sheet'!D29,0) -> 379.16 | F33: =IFERROR('Data Sheet'!E29,0) -> 404.7 | G33: =IFERROR('Data Sheet'!F29,0) -> -256.2 | H33: =IFERROR('Data Sheet'!G29,0) -> 263.82 | I33: =IFERROR('Data Sheet'!H29,0) -> 359.54 | J33: =IFERROR('Data Sheet'!I29,0) -> 371.87 | ... L33: =IFERROR('Data Sheet'!K29,0) -> 758.78
B34: Effective Tax Rate | C34: =C33/C30 -> 0.23159623 | D34: =D33/D30 -> 0.23521218 | E34: =E33/E30 -> 0.23536423 | F34: =F33/F30 -> 0.23051948 | G34: =G33/G30 -> -0.14866135 | H34: =H33/H30 -> 0.15264358 | I34: =I33/I30 -> 0.17472397 | J34: =J33/J30 -> 0.17904275 | ... L34: =L33/L30 -> 0.31526639
B36: Net Profit | C36: =IFERROR(C30-C33,0) -> 903.42 | D36: =IFERROR(D30-D33,0) -> 1092.66 | E36: =IFERROR(E30-E33,0) -> 1231.79 | F36: =IFERROR(F30-F33,0) -> 1350.9 | G36: =IFERROR(G30-G33,0) -> 1979.58 | H36: =IFERROR(H30-H33,0) -> 1464.52 | I36: =IFERROR(I30-I33,0) -> 1698.22 | J36: =IFERROR(J30-J33,0) -> 1705.12 | ... L36: =IFERROR(L30-L33,0) -> 1648.01
B37: Net Margins | C37: =C36/C9 -> 0.10919904 | D37: =D36/D9 -> 0.12970982 | E37: =E36/E9 -> 0.13290915 | F37: =F36/F9 -> 0.137183 | G37: =G36/G9 -> 0.19192503 | H37: =H36/H9 -> 0.14777011 | I37: =I36/I9 -> 0.153983 | J37: =J36/J9 -> 0.13889301 | ... L37: =L36/L9 -> 0.1169124
B39: No of Equity Shares | C39: =IFERROR('Data Sheet'!B93,0) -> 102.14 | D39: =IFERROR('Data Sheet'!C93,0) -> 102.16 | E39: =IFERROR('Data Sheet'!D93,0) -> 102.18 | F39: =IFERROR('Data Sheet'!E93,0) -> 102.2 | G39: =IFERROR('Data Sheet'!F93,0) -> 102.22 | H39: =IFERROR('Data Sheet'!G93,0) -> 102.23 | I39: =IFERROR('Data Sheet'!H93,0) -> 102.25 | J39: =IFERROR('Data Sheet'!I93,0) -> 102.26 | ... L39: =IFERROR('Data Sheet'!K93,0) -> 102.28
B41: Earnings per Share | C41: =IFERROR(C36/C39,0) -> 8.8449187 | D41: =IFERROR(D36/D39,0) -> 10.695576 | E41: =IFERROR(E36/E39,0) -> 12.055099 | F41: =IFERROR(F36/F39,0) -> 13.2182 | G41: =IFERROR(G36/G39,0) -> 19.365878 | H41: =IFERROR(H36/H39,0) -> 14.325736 | I41: =IFERROR(I36/I39,0) -> 16.608509 | J41: =IFERROR(J36/J39,0) -> 16.674359 | ... L41: =IFERROR(L36/L39,0) -> 16.11273
B42: EPS Growth % | D42: =IFERROR(D41/C41-1,0) -> 0.2092339 | E42: =IFERROR(E41/D41-1,0) -> 0.12711081 | F42: =IFERROR(F41/E41-1,0) -> 0.096482059 | G42: =IFERROR(G41/F41-1,0) -> 0.46509193 | H42: =IFERROR(H41/G41-1,0) -> -0.26025887 | I42: =IFERROR(I41/H41-1,0) -> 0.15934766 | J42: =IFERROR(J41/I41-1,0) -> 0.0039648905 | K42: =IFERROR(K41/J41-1,0) -> -0.068684486 | L42: =IFERROR(L41/K41-1,0) -> 0.037583665
B44: Dividend per Share | C44: =IFERROR('Data Sheet'!B31/HistoricalFS!C39,0) -> 1.8329743 | D44: =IFERROR('Data Sheet'!C31/HistoricalFS!D39,0) -> 1.9165035 | E44: =IFERROR('Data Sheet'!D31/HistoricalFS!E39,0) -> 5 | F44: =IFERROR('Data Sheet'!E31/HistoricalFS!F39,0) -> 6.6663405 | G44: =IFERROR('Data Sheet'!F31/HistoricalFS!G39,0) -> 10 | H44: =IFERROR('Data Sheet'!G31/HistoricalFS!H39,0) -> 8 | I44: =IFERROR('Data Sheet'!H31/HistoricalFS!I39,0) -> 0 | J44: =IFERROR('Data Sheet'!I31/HistoricalFS!J39,0) -> 0 | ... L44: =IFERROR('Data Sheet'!K31/HistoricalFS!L39,0) -> 0
B45: Dividend payout ratio | C45: =IFERROR(C44/C41,0) -> 0.20723473 | D45: =IFERROR(D44/D41,0) -> 0.17918657 | E45: =IFERROR(E44/E41,0) -> 0.41476226 | F45: =IFERROR(F44/F41,0) -> 0.50433045 | G45: =IFERROR(G44/G41,0) -> 0.51637216 | H45: =IFERROR(H44/H41,0) -> 0.55843553 | I45: =IFERROR(I44/I41,0) -> 0 | J45: =IFERROR(J44/J41,0) -> 0 | ... L45: =IFERROR(L44/L41,0) -> 0
B47: Retained Earnings | C47: =IFERROR(IF(C41>C44,1-C45,0),0) -> 0.79276527 | D47: =IFERROR(IF(D41>D44,1-D45,0),0) -> 0.82081343 | E47: =IFERROR(IF(E41>E44,1-E45,0),0) -> 0.58523774 | F47: =IFERROR(IF(F41>F44,1-F45,0),0) -> 0.49566955 | G47: =IFERROR(IF(G41>G44,1-G45,0),0) -> 0.48362784 | H47: =IFERROR(IF(H41>H44,1-H45,0),0) -> 0.44156447 | I47: =IFERROR(IF(I41>I44,1-I45,0),0) -> 1 | J47: =IFERROR(IF(J41>J44,1-J45,0),0) -> 1 | ... L47: =IFERROR(IF(L41>L44,1-L45,0),0) -> 1
A49: # | B49: Balance Sheet
B51: Equity Share Capital | C51: =IFERROR('Data Sheet'!B57,0) -> 34.04 | D51: =IFERROR('Data Sheet'!C57,0) -> 34.05 | E51: =IFERROR('Data Sheet'!D57,0) -> 34.06 | F51: =IFERROR('Data Sheet'!E57,0) -> 68.13 | G51: =IFERROR('Data Sheet'!F57,0) -> 102.22 | H51: =IFERROR('Data Sheet'!G57,0) -> 102.23 | I51: =IFERROR('Data Sheet'!H57,0) -> 102.25 | J51: =IFERROR('Data Sheet'!I57,0) -> 102.26 | ... L51: =IFERROR('Data Sheet'!K57,0) -> 102.28
B52: Reserves | C52: =IFERROR('Data Sheet'!B58,0) -> 4276.65 | D52: =IFERROR('Data Sheet'!C58,0) -> 4232.91 | E52: =IFERROR('Data Sheet'!D58,0) -> 5267.89 | F52: =IFERROR('Data Sheet'!E58,0) -> 6190.18 | G52: =IFERROR('Data Sheet'!F58,0) -> 7164.7 | H52: =IFERROR('Data Sheet'!G58,0) -> 7796.13 | I52: =IFERROR('Data Sheet'!H58,0) -> 9336.65 | J52: =IFERROR('Data Sheet'!I58,0) -> 11453.67 | ... L52: =IFERROR('Data Sheet'!K58,0) -> 12496.29
B53: Borrowings | C53: =IFERROR('Data Sheet'!B59,0) -> 2717.15 | D53: =IFERROR('Data Sheet'!C59,0) -> 2891.12 | E53: =IFERROR('Data Sheet'!D59,0) -> 4000.93 | F53: =IFERROR('Data Sheet'!E59,0) -> 3507.57 | G53: =IFERROR('Data Sheet'!F59,0) -> 3382.05 | H53: =IFERROR('Data Sheet'!G59,0) -> 3574.97 | I53: =IFERROR('Data Sheet'!H59,0) -> 1863.97 | J53: =IFERROR('Data Sheet'!I59,0) -> 1704.34 | ... L53: =IFERROR('Data Sheet'!K59,0) -> 3222.2
B54: Other Liabilities | C54: =IFERROR('Data Sheet'!B60,0) -> 2097.18 | D54: =IFERROR('Data Sheet'!C60,0) -> 2520.66 | E54: =IFERROR('Data Sheet'!D60,0) -> 3637.37 | F54: =IFERROR('Data Sheet'!E60,0) -> 4097.89 | G54: =IFERROR('Data Sheet'!F60,0) -> 3444.58 | H54: =IFERROR('Data Sheet'!G60,0) -> 3406.95 | I54: =IFERROR('Data Sheet'!H60,0) -> 2940.92 | J54: =IFERROR('Data Sheet'!I60,0) -> 2821.85 | ... L54: =IFERROR('Data Sheet'!K60,0) -> 2571.31
B55: Total Liabilities | C55: =IFERROR('Data Sheet'!B61,0) -> 9125.02 | D55: =IFERROR('Data Sheet'!C61,0) -> 9678.74 | E55: =IFERROR('Data Sheet'!D61,0) -> 12940.25 | F55: =IFERROR('Data Sheet'!E61,0) -> 13863.77 | G55: =IFERROR('Data Sheet'!F61,0) -> 14093.55 | H55: =IFERROR('Data Sheet'!G61,0) -> 14880.28 | I55: =IFERROR('Data Sheet'!H61,0) -> 14243.79 | J55: =IFERROR('Data Sheet'!I61,0) -> 16082.12 | ... L55: =IFERROR('Data Sheet'!K61,0) -> 18392.08
B57: Fixed Assets Net Block | C57: =IFERROR('Data Sheet'!B62,0) -> 5550.95 | D57: =IFERROR('Data Sheet'!C62,0) -> 5931.41 | E57: =IFERROR('Data Sheet'!D62,0) -> 8082.89 | F57: =IFERROR('Data Sheet'!E62,0) -> 8315 | G57: =IFERROR('Data Sheet'!F62,0) -> 8670.26 | H57: =IFERROR('Data Sheet'!G62,0) -> 9231.4 | I57: =IFERROR('Data Sheet'!H62,0) -> 8904.77 | J57: =IFERROR('Data Sheet'!I62,0) -> 9219.3 | ... L57: =IFERROR('Data Sheet'!K62,0) -> 10440.24
B58: Capital Work in Progress | C58: =IFERROR('Data Sheet'!B63,0) -> 224.61 | D58: =IFERROR('Data Sheet'!C63,0) -> 43.66 | E58: =IFERROR('Data Sheet'!D63,0) -> 97.43 | F58: =IFERROR('Data Sheet'!E63,0) -> 83.88 | G58: =IFERROR('Data Sheet'!F63,0) -> 52.06 | H58: =IFERROR('Data Sheet'!G63,0) -> 57.04 | I58: =IFERROR('Data Sheet'!H63,0) -> 57.43 | J58: =IFERROR('Data Sheet'!I63,0) -> 116.44 | ... L58: =IFERROR('Data Sheet'!K63,0) -> 83.36
B59: Investments | C59: =IFERROR('Data Sheet'!B64,0) -> 185.69 | D59: =IFERROR('Data Sheet'!C64,0) -> 189.5 | E59: =IFERROR('Data Sheet'!D64,0) -> 933.54 | F59: =IFERROR('Data Sheet'!E64,0) -> 997.28 | G59: =IFERROR('Data Sheet'!F64,0) -> 515.98 | H59: =IFERROR('Data Sheet'!G64,0) -> 671.98 | I59: =IFERROR('Data Sheet'!H64,0) -> 679.1 | J59: =IFERROR('Data Sheet'!I64,0) -> 1015.43 | ... L59: =IFERROR('Data Sheet'!K64,0) -> 3503.67
B60: Other Assets | C60: =IFERROR('Data Sheet'!B65-SUM('Data Sheet'!B67:B69),0) -> 393.26 | D60: =IFERROR('Data Sheet'!C65-SUM('Data Sheet'!C67:C69),0) -> 335.39 | E60: =IFERROR('Data Sheet'!D65-SUM('Data Sheet'!D67:D69),0) -> 472.49 | F60: =IFERROR('Data Sheet'!E65-SUM('Data Sheet'!E67:E69),0) -> 684.18 | G60: =IFERROR('Data Sheet'!F65-SUM('Data Sheet'!F67:F69),0) -> 1109.04 | H60: =IFERROR('Data Sheet'!G65-SUM('Data Sheet'!G67:G69),0) -> 1289.33 | I60: =IFERROR('Data Sheet'!H65-SUM('Data Sheet'!H67:H69),0) -> 1209.53 | J60: =IFERROR('Data Sheet'!I65-SUM('Data Sheet'!I67:I69),0) -> 1377.01 | ... L60: =IFERROR('Data Sheet'!K65-SUM('Data Sheet'!K67:K69),0) -> 1011.58
B61: Total Non Current Assets | C61: =SUM(C57:C60) -> 6354.51 | D61: =SUM(D57:D60) -> 6499.96 | E61: =SUM(E57:E60) -> 9586.35 | F61: =SUM(F57:F60) -> 10080.34 | G61: =SUM(G57:G60) -> 10347.34 | H61: =SUM(H57:H60) -> 11249.75 | I61: =SUM(I57:I60) -> 10850.83 | J61: =SUM(J57:J60) -> 11728.18 | ... L61: =SUM(L57:L60) -> 15038.85
B63: Receivables | C63: =IFERROR('Data Sheet'!B67,0) -> 804.58 | D63: =IFERROR('Data Sheet'!C67,0) -> 1118.01 | E63: =IFERROR('Data Sheet'!D67,0) -> 1028.74 | F63: =IFERROR('Data Sheet'!E67,0) -> 1245.5 | G63: =IFERROR('Data Sheet'!F67,0) -> 1292.9 | H63: =IFERROR('Data Sheet'!G67,0) -> 1157.25 | I63: =IFERROR('Data Sheet'!H67,0) -> 1004.5 | J63: =IFERROR('Data Sheet'!I67,0) -> 1116.32 | ... L63: =IFERROR('Data Sheet'!K67,0) -> 1535.37
B64: Inventory | C64: =IFERROR('Data Sheet'!B68,0) -> 1071.71 | D64: =IFERROR('Data Sheet'!C68,0) -> 1306.98 | E64: =IFERROR('Data Sheet'!D68,0) -> 1412.5 | F64: =IFERROR('Data Sheet'!E68,0) -> 1577.72 | G64: =IFERROR('Data Sheet'!F68,0) -> 1558.59 | H64: =IFERROR('Data Sheet'!G68,0) -> 1703.12 | I64: =IFERROR('Data Sheet'!H68,0) -> 1716.25 | J64: =IFERROR('Data Sheet'!I68,0) -> 2129.85 | ... L64: =IFERROR('Data Sheet'!K68,0) -> 1270.92
B65: Cash & Bank | C65: =IFERROR('Data Sheet'!B69,0) -> 894.22 | D65: =IFERROR('Data Sheet'!C69,0) -> 753.79 | E65: =IFERROR('Data Sheet'!D69,0) -> 912.66 | F65: =IFERROR('Data Sheet'!E69,0) -> 960.21 | G65: =IFERROR('Data Sheet'!F69,0) -> 894.72 | H65: =IFERROR('Data Sheet'!G69,0) -> 770.16 | I65: =IFERROR('Data Sheet'!H69,0) -> 672.21 | J65: =IFERROR('Data Sheet'!I69,0) -> 1107.77 | ... L65: =IFERROR('Data Sheet'!K69,0) -> 546.94
B66: Total Current Assets | C66: =IFERROR(SUM(C63:C65),0) -> 2770.51 | D66: =IFERROR(SUM(D63:D65),0) -> 3178.78 | E66: =IFERROR(SUM(E63:E65),0) -> 3353.9 | F66: =IFERROR(SUM(F63:F65),0) -> 3783.43 | G66: =IFERROR(SUM(G63:G65),0) -> 3746.21 | H66: =IFERROR(SUM(H63:H65),0) -> 3630.53 | I66: =IFERROR(SUM(I63:I65),0) -> 3392.96 | J66: =IFERROR(SUM(J63:J65),0) -> 4353.94 | ... L66: =IFERROR(SUM(L63:L65),0) -> 3353.23
B68: Total Assets | C68: =IFERROR(C66+C61,0) -> 9125.02 | D68: =IFERROR(D66+D61,0) -> 9678.74 | E68: =IFERROR(E66+E61,0) -> 12940.25 | F68: =IFERROR(F66+F61,0) -> 13863.77 | G68: =IFERROR(G66+G61,0) -> 14093.55 | H68: =IFERROR(H66+H61,0) -> 14880.28 | I68: =IFERROR(I66+I61,0) -> 14243.79 | J68: =IFERROR(J66+J61,0) -> 16082.12 | ... L68: =IFERROR(L66+L61,0) -> 18392.08
B70: Check | C70: =C68=C55 -> TRUE | D70: =D68=D55 -> TRUE | E70: =E68=E55 -> TRUE | F70: =F68=F55 -> TRUE | G70: =G68=G55 -> TRUE | H70: =H68=H55 -> TRUE | I70: =I68=I55 -> TRUE | J70: =J68=J55 -> TRUE | ... L70: =L68=L55 -> TRUE
A72: # | B72: Cash Flow Statements
B73: Operating Activities
B74: Profit from operations | C74: =IFERROR('Cash Flow Data'!C4,0) -> 1397 | D74: =IFERROR('Cash Flow Data'!D4,0) -> 1669 | E74: =IFERROR('Cash Flow Data'!E4,0) -> 1947 | F74: =IFERROR('Cash Flow Data'!F4,0) -> 2147 | G74: =IFERROR('Cash Flow Data'!G4,0) -> 2181 | H74: =IFERROR('Cash Flow Data'!H4,0) -> 2185 | I74: =IFERROR('Cash Flow Data'!I4,0) -> 2472 | J74: =IFERROR('Cash Flow Data'!J4,0) -> 2434 | ... L74: =IFERROR('Cash Flow Data'!L4,0) -> 2900
B75: Receivables | C75: =IFERROR('Cash Flow Data'!C5,0) -> -81 | D75: =IFERROR('Cash Flow Data'!D5,0) -> -323 | E75: =IFERROR('Cash Flow Data'!E5,0) -> 166 | F75: =IFERROR('Cash Flow Data'!F5,0) -> -245 | G75: =IFERROR('Cash Flow Data'!G5,0) -> -174 | H75: =IFERROR('Cash Flow Data'!H5,0) -> 130 | I75: =IFERROR('Cash Flow Data'!I5,0) -> 81 | J75: =IFERROR('Cash Flow Data'!J5,0) -> -89 | ... L75: =IFERROR('Cash Flow Data'!L5,0) -> -479
B76: Inventory | C76: =IFERROR('Cash Flow Data'!C6,0) -> 26 | D76: =IFERROR('Cash Flow Data'!D6,0) -> -235 | E76: =IFERROR('Cash Flow Data'!E6,0) -> 46 | F76: =IFERROR('Cash Flow Data'!F6,0) -> -165 | G76: =IFERROR('Cash Flow Data'!G6,0) -> -20 | H76: =IFERROR('Cash Flow Data'!H6,0) -> -169 | I76: =IFERROR('Cash Flow Data'!I6,0) -> -70 | J76: =IFERROR('Cash Flow Data'!J6,0) -> -384 | ... L76: =IFERROR('Cash Flow Data'!L6,0) -> -71
B77: Payables | C77: =IFERROR('Cash Flow Data'!C7,0) -> 0 | D77: =IFERROR('Cash Flow Data'!D7,0) -> 17 | E77: =IFERROR('Cash Flow Data'!E7,0) -> 196 | F77: =IFERROR('Cash Flow Data'!F7,0) -> 613 | G77: =IFERROR('Cash Flow Data'!G7,0) -> 274 | H77: =IFERROR('Cash Flow Data'!H7,0) -> -95 | I77: =IFERROR('Cash Flow Data'!I7,0) -> -473 | J77: =IFERROR('Cash Flow Data'!J7,0) -> 83 | ... L77: =IFERROR('Cash Flow Data'!L7,0) -> 91
B78: Loans Advances | C78: =IFERROR('Cash Flow Data'!C8,0) -> 8 | D78: =IFERROR('Cash Flow Data'!D8,0) -> 1 | E78: =IFERROR('Cash Flow Data'!E8,0) -> -3 | F78: =IFERROR('Cash Flow Data'!F8,0) -> 1 | G78: =IFERROR('Cash Flow Data'!G8,0) -> -1 | H78: =IFERROR('Cash Flow Data'!H8,0) -> -3 | I78: =IFERROR('Cash Flow Data'!I8,0) -> 1 | J78: =IFERROR('Cash Flow Data'!J8,0) -> 0 | ... L78: =IFERROR('Cash Flow Data'!L8,0) -> 0
B79: Other WC items | C79: =IFERROR('Cash Flow Data'!C9,0) -> -39 | D79: =IFERROR('Cash Flow Data'!D9,0) -> 75 | E79: =IFERROR('Cash Flow Data'!E9,0) -> -65 | F79: =IFERROR('Cash Flow Data'!F9,0) -> -219 | G79: =IFERROR('Cash Flow Data'!G9,0) -> -79 | H79: =IFERROR('Cash Flow Data'!H9,0) -> -116 | I79: =IFERROR('Cash Flow Data'!I9,0) -> 416 | J79: =IFERROR('Cash Flow Data'!J9,0) -> -146 | ... L79: =IFERROR('Cash Flow Data'!L9,0) -> 3
B80: Working capital changes | C80: =IFERROR('Cash Flow Data'!C10,0) -> -87 | D80: =IFERROR('Cash Flow Data'!D10,0) -> -465 | E80: =IFERROR('Cash Flow Data'!E10,0) -> 341 | F80: =IFERROR('Cash Flow Data'!F10,0) -> -16 | G80: =IFERROR('Cash Flow Data'!G10,0) -> 1 | H80: =IFERROR('Cash Flow Data'!H10,0) -> -253 | I80: =IFERROR('Cash Flow Data'!I10,0) -> -45 | J80: =IFERROR('Cash Flow Data'!J10,0) -> -536 | ... L80: =IFERROR('Cash Flow Data'!L10,0) -> -456
B81: Direct taxes | C81: =IFERROR('Cash Flow Data'!C11,0) -> -257 | D81: =IFERROR('Cash Flow Data'!D11,0) -> -336 | E81: =IFERROR('Cash Flow Data'!E11,0) -> -407 | F81: =IFERROR('Cash Flow Data'!F11,0) -> -393 | G81: =IFERROR('Cash Flow Data'!G11,0) -> -435 | H81: =IFERROR('Cash Flow Data'!H11,0) -> -344 | I81: =IFERROR('Cash Flow Data'!I11,0) -> -397 | J81: =IFERROR('Cash Flow Data'!J11,0) -> -448 | ... L81: =IFERROR('Cash Flow Data'!L11,0) -> -374
B82: Cash from Operating Activities | C82: =SUM(C74:C81) -> 967 | D82: =SUM(D74:D81) -> 403 | E82: =SUM(E74:E81) -> 2221 | F82: =SUM(F74:F81) -> 1723 | G82: =SUM(G74:G81) -> 1747 | H82: =SUM(H74:H81) -> 1335 | I82: =SUM(I74:I81) -> 1985 | J82: =SUM(J74:J81) -> 914 | ... L82: =SUM(L74:L81) -> 1614
B84: Investing Activities
B85: Fixed assets purchased | C85: =IFERROR('Cash Flow Data'!C13,0) -> -213 | D85: =IFERROR('Cash Flow Data'!D13,0) -> -208 | E85: =IFERROR('Cash Flow Data'!E13,0) -> -180 | F85: =IFERROR('Cash Flow Data'!F13,0) -> -311 | G85: =IFERROR('Cash Flow Data'!G13,0) -> -208 | H85: =IFERROR('Cash Flow Data'!H13,0) -> -152 | I85: =IFERROR('Cash Flow Data'!I13,0) -> -164 | J85: =IFERROR('Cash Flow Data'!J13,0) -> 0 | ... L85: =IFERROR('Cash Flow Data'!L13,0) -> 0
B86: Fixed assets sold | C86: =IFERROR('Cash Flow Data'!C14,0) -> 0 | D86: =IFERROR('Cash Flow Data'!D14,0) -> 0 | E86: =IFERROR('Cash Flow Data'!E14,0) -> 0 | F86: =IFERROR('Cash Flow Data'!F14,0) -> 0 | G86: =IFERROR('Cash Flow Data'!G14,0) -> 0 | H86: =IFERROR('Cash Flow Data'!H14,0) -> 0 | I86: =IFERROR('Cash Flow Data'!I14,0) -> 0 | J86: =IFERROR('Cash Flow Data'!J14,0) -> 3 | ... L86: =IFERROR('Cash Flow Data'!L14,0) -> 31
B87: Investments purchased | C87: =IFERROR('Cash Flow Data'!C15,0) -> -40 | D87: =IFERROR('Cash Flow Data'!D15,0) -> 0 | E87: =IFERROR('Cash Flow Data'!E15,0) -> -574 | F87: =IFERROR('Cash Flow Data'!F15,0) -> -309 | G87: =IFERROR('Cash Flow Data'!G15,0) -> 0 | H87: =IFERROR('Cash Flow Data'!H15,0) -> 0 | I87: =IFERROR('Cash Flow Data'!I15,0) -> -139 | J87: =IFERROR('Cash Flow Data'!J15,0) -> -452 | ... L87: =IFERROR('Cash Flow Data'!L15,0) -> -307
B88: Investments sold | C88: =IFERROR('Cash Flow Data'!C16,0) -> 0 | D88: =IFERROR('Cash Flow Data'!D16,0) -> 92 | E88: =IFERROR('Cash Flow Data'!E16,0) -> 0 | F88: =IFERROR('Cash Flow Data'!F16,0) -> 349 | G88: =IFERROR('Cash Flow Data'!G16,0) -> 195 | H88: =IFERROR('Cash Flow Data'!H16,0) -> 270 | I88: =IFERROR('Cash Flow Data'!I16,0) -> 35 | J88: =IFERROR('Cash Flow Data'!J16,0) -> 0 | ... L88: =IFERROR('Cash Flow Data'!L16,0) -> 0
B89: Interest received | C89: =IFERROR('Cash Flow Data'!C17,0) -> 31 | D89: =IFERROR('Cash Flow Data'!D17,0) -> 43 | E89: =IFERROR('Cash Flow Data'!E17,0) -> 41 | F89: =IFERROR('Cash Flow Data'!F17,0) -> 66 | G89: =IFERROR('Cash Flow Data'!G17,0) -> 92 | H89: =IFERROR('Cash Flow Data'!H17,0) -> 57 | I89: =IFERROR('Cash Flow Data'!I17,0) -> 59 | J89: =IFERROR('Cash Flow Data'!J17,0) -> 59 | ... L89: =IFERROR('Cash Flow Data'!L17,0) -> 231
B90: Invest in subsidiaries | C90: =IFERROR('Cash Flow Data'!C18,0) -> -630 | D90: =IFERROR('Cash Flow Data'!D18,0) -> -647 | E90: =IFERROR('Cash Flow Data'!E18,0) -> 0 | F90: =IFERROR('Cash Flow Data'!F18,0) -> 0 | G90: =IFERROR('Cash Flow Data'!G18,0) -> 0 | H90: =IFERROR('Cash Flow Data'!H18,0) -> 0 | I90: =IFERROR('Cash Flow Data'!I18,0) -> 0 | J90: =IFERROR('Cash Flow Data'!J18,0) -> 0 | ... L90: =IFERROR('Cash Flow Data'!L18,0) -> 0
B91: Investment in group cos | C91: =IFERROR('Cash Flow Data'!C19,0) -> 0 | D91: =IFERROR('Cash Flow Data'!D19,0) -> 0 | E91: =IFERROR('Cash Flow Data'!E19,0) -> 0 | F91: =IFERROR('Cash Flow Data'!F19,0) -> 0 | G91: =IFERROR('Cash Flow Data'!G19,0) -> 0 | H91: =IFERROR('Cash Flow Data'!H19,0) -> 0 | I91: =IFERROR('Cash Flow Data'!I19,0) -> 0 | J91: =IFERROR('Cash Flow Data'!J19,0) -> 0 | ... L91: =IFERROR('Cash Flow Data'!L19,0) -> 0
B92: Redemp n Canc of Shares | C92: =IFERROR('Cash Flow Data'!C20,0) -> 0 | D92: =IFERROR('Cash Flow Data'!D20,0) -> 0 | E92: =IFERROR('Cash Flow Data'!E20,0) -> 0 | F92: =IFERROR('Cash Flow Data'!F20,0) -> 0 | G92: =IFERROR('Cash Flow Data'!G20,0) -> 0 | H92: =IFERROR('Cash Flow Data'!H20,0) -> 0 | I92: =IFERROR('Cash Flow Data'!I20,0) -> 0 | J92: =IFERROR('Cash Flow Data'!J20,0) -> 0 | ... L92: =IFERROR('Cash Flow Data'!L20,0) -> 372
B93: Acquisition of companies | C93: =IFERROR('Cash Flow Data'!C21,0) -> 0 | D93: =IFERROR('Cash Flow Data'!D21,0) -> 0 | E93: =IFERROR('Cash Flow Data'!E21,0) -> -1431 | F93: =IFERROR('Cash Flow Data'!F21,0) -> 0 | G93: =IFERROR('Cash Flow Data'!G21,0) -> 0 | H93: =IFERROR('Cash Flow Data'!H21,0) -> 0 | I93: =IFERROR('Cash Flow Data'!I21,0) -> 0 | J93: =IFERROR('Cash Flow Data'!J21,0) -> -387 | ... L93: =IFERROR('Cash Flow Data'!L21,0) -> 0
B94: Other investing items | C94: =IFERROR('Cash Flow Data'!C22,0) -> -385 | D94: =IFERROR('Cash Flow Data'!D22,0) -> 99 | E94: =IFERROR('Cash Flow Data'!E22,0) -> -99 | F94: =IFERROR('Cash Flow Data'!F22,0) -> -131 | G94: =IFERROR('Cash Flow Data'!G22,0) -> 195 | H94: =IFERROR('Cash Flow Data'!H22,0) -> -727 | I94: =IFERROR('Cash Flow Data'!I22,0) -> -84 | J94: =IFERROR('Cash Flow Data'!J22,0) -> -67 | ... L94: =IFERROR('Cash Flow Data'!L22,0) -> -3762
B95: Cash from Investing Activities | C95: =SUM(C85:C94) -> -1237 | D95: =SUM(D85:D94) -> -621 | E95: =SUM(E85:E94) -> -2243 | F95: =SUM(F85:F94) -> -336 | G95: =SUM(G85:G94) -> 274 | H95: =SUM(H85:H94) -> -552 | I95: =SUM(I85:I94) -> -293 | J95: =SUM(J85:J94) -> -844 | ... L95: =SUM(L85:L94) -> -3435
B97: Financing Activities
B98: Proceeds from shares | C98: =IFERROR('Cash Flow Data'!C24,0) -> 0 | D98: =IFERROR('Cash Flow Data'!D24,0) -> 0 | E98: =IFERROR('Cash Flow Data'!E24,0) -> 0 | F98: =IFERROR('Cash Flow Data'!F24,0) -> 0 | G98: =IFERROR('Cash Flow Data'!G24,0) -> 0 | H98: =IFERROR('Cash Flow Data'!H24,0) -> 0 | I98: =IFERROR('Cash Flow Data'!I24,0) -> 0 | J98: =IFERROR('Cash Flow Data'!J24,0) -> 0 | ... L98: =IFERROR('Cash Flow Data'!L24,0) -> 0
B99: Redemption of debentures | C99: =IFERROR('Cash Flow Data'!C25,0) -> 0 | D99: =IFERROR('Cash Flow Data'!D25,0) -> 0 | E99: =IFERROR('Cash Flow Data'!E25,0) -> 0 | F99: =IFERROR('Cash Flow Data'!F25,0) -> 0 | G99: =IFERROR('Cash Flow Data'!G25,0) -> 0 | H99: =IFERROR('Cash Flow Data'!H25,0) -> 0 | I99: =IFERROR('Cash Flow Data'!I25,0) -> 0 | J99: =IFERROR('Cash Flow Data'!J25,0) -> 0 | ... L99: =IFERROR('Cash Flow Data'!L25,0) -> 0
B100: Proceeds from borrowings | C100: =IFERROR('Cash Flow Data'!C26,0) -> -50 | D100: =IFERROR('Cash Flow Data'!D26,0) -> -278 | E100: =IFERROR('Cash Flow Data'!E26,0) -> 0 | F100: =IFERROR('Cash Flow Data'!F26,0) -> 0 | G100: =IFERROR('Cash Flow Data'!G26,0) -> 0 | H100: =IFERROR('Cash Flow Data'!H26,0) -> 0 | I100: =IFERROR('Cash Flow Data'!I26,0) -> 0 | J100: =IFERROR('Cash Flow Data'!J26,0) -> 0 | ... L100: =IFERROR('Cash Flow Data'!L26,0) -> 0
B101: Repayment of borrowings | C101: =IFERROR('Cash Flow Data'!C27,0) -> 368 | D101: =IFERROR('Cash Flow Data'!D27,0) -> 0 | E101: =IFERROR('Cash Flow Data'!E27,0) -> 0 | F101: =IFERROR('Cash Flow Data'!F27,0) -> 0 | G101: =IFERROR('Cash Flow Data'!G27,0) -> 0 | H101: =IFERROR('Cash Flow Data'!H27,0) -> 247 | I101: =IFERROR('Cash Flow Data'!I27,0) -> 737 | J101: =IFERROR('Cash Flow Data'!J27,0) -> 535 | ... L101: =IFERROR('Cash Flow Data'!L27,0) -> 2681
B102: Proceeds from deposits | C102: =IFERROR('Cash Flow Data'!C28,0) -> 0 | D102: =IFERROR('Cash Flow Data'!D28,0) -> 0 | E102: =IFERROR('Cash Flow Data'!E28,0) -> 0 | F102: =IFERROR('Cash Flow Data'!F28,0) -> 0 | G102: =IFERROR('Cash Flow Data'!G28,0) -> -345 | H102: =IFERROR('Cash Flow Data'!H28,0) -> -375 | I102: =IFERROR('Cash Flow Data'!I28,0) -> -2357 | J102: =IFERROR('Cash Flow Data'!J28,0) -> -755 | ... L102: =IFERROR('Cash Flow Data'!L28,0) -> -416
B103: Interest paid fin | C103: =IFERROR('Cash Flow Data'!C29,0) -> -119 | D103: =IFERROR('Cash Flow Data'!D29,0) -> -119 | E103: =IFERROR('Cash Flow Data'!E29,0) -> -124 | F103: =IFERROR('Cash Flow Data'!F29,0) -> -158 | G103: =IFERROR('Cash Flow Data'!G29,0) -> -215 | H103: =IFERROR('Cash Flow Data'!H29,0) -> -156 | I103: =IFERROR('Cash Flow Data'!I29,0) -> -166 | J103: =IFERROR('Cash Flow Data'!J29,0) -> -119 | ... L103: =IFERROR('Cash Flow Data'!L29,0) -> -267
B104: Dividends paid | C104: =IFERROR('Cash Flow Data'!C30,0) -> -179 | D104: =IFERROR('Cash Flow Data'!D30,0) -> -187 | E104: =IFERROR('Cash Flow Data'!E30,0) -> -196 | F104: =IFERROR('Cash Flow Data'!F30,0) -> -613 | G104: =IFERROR('Cash Flow Data'!G30,0) -> -1227 | H104: =IFERROR('Cash Flow Data'!H30,0) -> -818 | I104: =IFERROR('Cash Flow Data'!I30,0) -> 0 | J104: =IFERROR('Cash Flow Data'!J30,0) -> 0 | ... L104: =IFERROR('Cash Flow Data'!L30,0) -> -511
B105: Financial liabilities | C105: =IFERROR('Cash Flow Data'!C31,0) -> 0 | D105: =IFERROR('Cash Flow Data'!D31,0) -> 0 | E105: =IFERROR('Cash Flow Data'!E31,0) -> 0 | F105: =IFERROR('Cash Flow Data'!F31,0) -> 0 | G105: =IFERROR('Cash Flow Data'!G31,0) -> 0 | H105: =IFERROR('Cash Flow Data'!H31,0) -> -25 | I105: =IFERROR('Cash Flow Data'!I31,0) -> -31 | J105: =IFERROR('Cash Flow Data'!J31,0) -> -41 | ... L105: =IFERROR('Cash Flow Data'!L31,0) -> -80
B106: Other financing items | C106: =IFERROR('Cash Flow Data'!C32,0) -> -32 | D106: =IFERROR('Cash Flow Data'!D32,0) -> 381 | E106: =IFERROR('Cash Flow Data'!E32,0) -> 984 | F106: =IFERROR('Cash Flow Data'!F32,0) -> -613 | G106: =IFERROR('Cash Flow Data'!G32,0) -> -253 | H106: =IFERROR('Cash Flow Data'!H32,0) -> -168 | I106: =IFERROR('Cash Flow Data'!I32,0) -> 0 | J106: =IFERROR('Cash Flow Data'!J32,0) -> 0 | ... L106: =IFERROR('Cash Flow Data'!L32,0) -> 0
B107: Cash from Financing Activities | C107: =SUM(C98:C106) -> -12 | D107: =SUM(D98:D106) -> -203 | E107: =SUM(E98:E106) -> 664 | F107: =SUM(F98:F106) -> -1384 | G107: =SUM(G98:G106) -> -2040 | H107: =SUM(H98:H106) -> -1295 | I107: =SUM(I98:I106) -> -1817 | J107: =SUM(J98:J106) -> -380 | ... L107: =SUM(L98:L106) -> 1407
B109: Net Cash Flow | C109: =IFERROR(C82+C95+C107,0) -> -282 | D109: =IFERROR(D82+D95+D107,0) -> -421 | E109: =IFERROR(E82+E95+E107,0) -> 642 | F109: =IFERROR(F82+F95+F107,0) -> 3 | G109: =IFERROR(G82+G95+G107,0) -> -19 | H109: =IFERROR(H82+H95+H107,0) -> -512 | I109: =IFERROR(I82+I95+I107,0) -> -125 | J109: =IFERROR(J82+J95+J107,0) -> -310 | ... L109: =IFERROR(L82+L95+L107,0) -> -414

Sheet Ratio Analysis
B2: ='Data Sheet'!B1 -> GODREJ CONSUMER PRODUCTS LTD
B3: (GODREJCP | BSE Code: 532424)
B5: ="Ratio Analysis of - "&'[2]Data Sheet'!B1 -> Ratio Analysis of - GODREJ CONSUMER PRODUCTS LTD
B6: Years | C6: ='[2]Data Sheet'!B16 -> 42094 | D6: ='[2]Data Sheet'!C16 -> 42460 | E6: ='[2]Data Sheet'!D16 -> 42825 | F6: ='[2]Data Sheet'!E16 -> 43190 | G6: ='[2]Data Sheet'!F16 -> 43555 | H6: ='[2]Data Sheet'!G16 -> 43921 | I6: ='[2]Data Sheet'!H16 -> 44286 | J6: ='[2]Data Sheet'!I16 -> 44651 | ... L6: ='[2]Data Sheet'!K16 -> 45382 | M6: Trend | N6: Mean | O6: Median
B8: SalesGrowth | C8: - | D8: =IFERROR(HistoricalFS!D10,0) -> 0.018219179 | E8: =IFERROR(HistoricalFS!E10,0) -> 0.10019492 | F8: =IFERROR(HistoricalFS!F10,0) -> 0.06252974 | G8: =IFERROR(HistoricalFS!G10,0) -> 0.047414402 | H8: =IFERROR(HistoricalFS!H10,0) -> -0.039124171 | I8: =IFERROR(HistoricalFS!I10,0) -> 0.11278807 | J8: =IFERROR(HistoricalFS!J10,0) -> 0.11314924 | K8: =IFERROR(HistoricalFS!K10,0) -> 0.084671527 | L8: =IFERROR(HistoricalFS!L10,0) -> 0.058586795 | N8: =IFERROR(AVERAGE(D8:L8),0) -> 0.062047745 | O8: =IFERROR(MEDIAN(C8:L8),0) -> 0.06252974
B9: EBITDA Growth | C9: - | D9: =IFERROR(HistoricalFS!D21/HistoricalFS!C21-1,0) -> 0.2019145 | E9: =IFERROR(HistoricalFS!E21/HistoricalFS!D21-1,0) -> 0.15043623 | F9: =IFERROR(HistoricalFS!F21/HistoricalFS!E21-1,0) -> 0.093191938 | G9: =IFERROR(HistoricalFS!G21/HistoricalFS!F21-1,0) -> 0.022630013 | H9: =IFERROR(HistoricalFS!H21/HistoricalFS!G21-1,0) -> 0.010405476 | I9: =IFERROR(HistoricalFS!I21/HistoricalFS!H21-1,0) -> 0.11399187 | J9: =IFERROR(HistoricalFS!J21/HistoricalFS!I21-1,0) -> 0.0041346082 | K9: =IFERROR(HistoricalFS!K21/HistoricalFS!J21-1,0) -> 0.014120987 | L9: =IFERROR(HistoricalFS!L21/HistoricalFS!K21-1,0) -> 0.21042895 | N9: =IFERROR(AVERAGE(D9:L9),0) -> 0.091250508 | O9: =IFERROR(MEDIAN(C9:L9),0) -> 0.093191938
B10: EBIT Growth | C10: - | D10: =IFERROR(HistoricalFS!D30/HistoricalFS!C30-1,0) -> 0.21518912 | E10: =IFERROR(HistoricalFS!E30/HistoricalFS!D30-1,0) -> 0.12755563 | F10: =IFERROR(HistoricalFS!F30/HistoricalFS!E30-1,0) -> 0.089791738 | G10: =IFERROR(HistoricalFS!G30/HistoricalFS!F30-1,0) -> -0.0183527 | H10: =IFERROR(HistoricalFS!H30/HistoricalFS!G30-1,0) -> 0.0028780652 | I10: =IFERROR(HistoricalFS!I30/HistoricalFS!H30-1,0) -> 0.19059907 | J10: =IFERROR(HistoricalFS!J30/HistoricalFS!I30-1,0) -> 0.0093451131 | K10: =IFERROR(HistoricalFS!K30/HistoricalFS!J30-1,0) -> -0.028194647 | L10: =IFERROR(HistoricalFS!L30/HistoricalFS!K30-1,0) -> 0.19240697 | N10: =IFERROR(AVERAGE(D10:L10),0) -> 0.08680204 | O10: =IFERROR(MEDIAN(C10:L10),0) -> 0.089791738
B11: Net Profit Growth | C11: - | D11: =IFERROR(HistoricalFS!D36/HistoricalFS!C36-1,0) -> 0.20947068 | E11: =IFERROR(HistoricalFS!E36/HistoricalFS!D36-1,0) -> 0.12733147 | F11: =IFERROR(HistoricalFS!F36/HistoricalFS!E36-1,0) -> 0.096696677 | G11: =IFERROR(HistoricalFS!G36/HistoricalFS!F36-1,0) -> 0.46537864 | H11: =IFERROR(HistoricalFS!H36/HistoricalFS!G36-1,0) -> -0.2601865 | I11: =IFERROR(HistoricalFS!I36/HistoricalFS!H36-1,0) -> 0.15957447 | J11: =IFERROR(HistoricalFS!J36/HistoricalFS!I36-1,0) -> 0.0040630778 | K11: =IFERROR(HistoricalFS!K36/HistoricalFS!J36-1,0) -> -0.068593413 | L11: =IFERROR(HistoricalFS!L36/HistoricalFS!K36-1,0) -> 0.03768512 | N11: =IFERROR(AVERAGE(D11:L11),0) -> 0.085713356 | O11: =IFERROR(MEDIAN(C11:L11),0) -> 0.096696677
B12: Dividend Growth | C12: - | D12: =IFERROR(HistoricalFS!D44/HistoricalFS!C44-1,0) -> 0.045570291 | E12: =IFERROR(HistoricalFS!E44/HistoricalFS!D44-1,0) -> 1.6089177 | F12: =IFERROR(HistoricalFS!F44/HistoricalFS!E44-1,0) -> 0.3332681 | G12: =IFERROR(HistoricalFS!G44/HistoricalFS!F44-1,0) -> 0.50007339 | H12: =IFERROR(HistoricalFS!H44/HistoricalFS!G44-1,0) -> -0.2 | I12: =IFERROR(HistoricalFS!I44/HistoricalFS!H44-1,0) -> -1 | J12: =IFERROR(HistoricalFS!J44/HistoricalFS!I44-1,0) -> 0 | K12: =IFERROR(HistoricalFS!K44/HistoricalFS!J44-1,0) -> 0 | L12: =IFERROR(HistoricalFS!L44/HistoricalFS!K44-1,0) -> 0 | N12: =IFERROR(AVERAGE(D12:L12),0) -> 0.14309217 | O12: =IFERROR(MEDIAN(C12:L12),0) -> 0
B14: Gross Margin | C14: =IFERROR(HistoricalFS!C16,0) -> 0.40139367 | D14: =IFERROR(HistoricalFS!D16,0) -> 0.38774175 | E14: =IFERROR(HistoricalFS!E16,0) -> 0.40516794 | F14: =IFERROR(HistoricalFS!F16,0) -> 0.41592578 | G14: =IFERROR(HistoricalFS!G16,0) -> 0.41132152 | H14: =IFERROR(HistoricalFS!H16,0) -> 0.4170521 | I14: =IFERROR(HistoricalFS!I16,0) -> 0.4055249 | J14: =IFERROR(HistoricalFS!J16,0) -> 0.36928115 | ... L14: =IFERROR(HistoricalFS!L16,0) -> 0.42247045 | N14: =IFERROR(AVERAGE(C14:L14),0) -> 0.40044713 | O14: =IFERROR(MEDIAN(C14:L14),0) -> 0.40534642
B15: EBITDA Margin | C15: =IFERROR(HistoricalFS!C22,0) -> 0.16667775 | D15: =IFERROR(HistoricalFS!D22,0) -> 0.19674782 | E15: =IFERROR(HistoricalFS!E22,0) -> 0.20573247 | F15: =IFERROR(HistoricalFS!F22,0) -> 0.21166944 | G15: =IFERROR(HistoricalFS!G22,0) -> 0.20666082 | H15: =IFERROR(HistoricalFS!H22,0) -> 0.21731344 | I15: =IFERROR(HistoricalFS!I22,0) -> 0.21754852 | J15: =IFERROR(HistoricalFS!J22,0) -> 0.19624323 | ... L15: =IFERROR(HistoricalFS!L22,0) -> 0.20979689 | N15: =IFERROR(AVERAGE(C15:L15),0) -> 0.20118693 | O15: =IFERROR(MEDIAN(C15:L15),0) -> 0.20619665
B16: EBIT Margin | C16: =IFERROR((HistoricalFS!C21-HistoricalFS!C27)/HistoricalFS!C9,0) -> 0.1557049 | D16: =IFERROR((HistoricalFS!D21-HistoricalFS!D27)/HistoricalFS!D9,0) -> 0.18480202 | E16: =IFERROR((HistoricalFS!E21-HistoricalFS!E27)/HistoricalFS!E9,0) -> 0.19045718 | F16: =IFERROR((HistoricalFS!F21-HistoricalFS!F27)/HistoricalFS!F9,0) -> 0.19586024 | G16: =IFERROR((HistoricalFS!G21-HistoricalFS!G27)/HistoricalFS!G9,0) -> 0.19018086 | H16: =IFERROR((HistoricalFS!H21-HistoricalFS!H27)/HistoricalFS!H9,0) -> 0.19740788 | I16: =IFERROR((HistoricalFS!I21-HistoricalFS!I27)/HistoricalFS!I9,0) -> 0.1990648 | J16: =IFERROR((HistoricalFS!J21-HistoricalFS!J27)/HistoricalFS!J9,0) -> 0.17914308 | ... L16: =IFERROR((HistoricalFS!L21-HistoricalFS!L27)/HistoricalFS!L9,0) -> 0.19270281 | N16: =IFERROR(AVERAGE(C16:L16),0) -> 0.18510578 | O16: =IFERROR(MEDIAN(C16:L16),0) -> 0.19031902
B17: EBT Margin | C17: =IFERROR(HistoricalFS!C31,0) -> 0.14211153 | D17: =IFERROR(HistoricalFS!D31,0) -> 0.16960237 | E17: =IFERROR(HistoricalFS!E31,0) -> 0.1738202 | F17: =IFERROR(HistoricalFS!F31,0) -> 0.17828002 | G17: =IFERROR(HistoricalFS!G31,0) -> 0.16708582 | H17: =IFERROR(HistoricalFS!H31,0) -> 0.17438955 | I17: =IFERROR(HistoricalFS!I31,0) -> 0.18658363 | J17: =IFERROR(HistoricalFS!J31,0) -> 0.16918421 | ... L17: =IFERROR(HistoricalFS!L31,0) -> 0.17074143 | N17: =IFERROR(AVERAGE(C17:L17),0) -> 0.16833784 | O17: =IFERROR(MEDIAN(C17:L17),0) -> 0.1701719
B18: Net Profit Margin | C18: =IFERROR(HistoricalFS!C37,0) -> 0.10919904 | D18: =IFERROR(HistoricalFS!D37,0) -> 0.12970982 | E18: =IFERROR(HistoricalFS!E37,0) -> 0.13290915 | F18: =IFERROR(HistoricalFS!F37,0) -> 0.137183 | G18: =IFERROR(HistoricalFS!G37,0) -> 0.19192503 | H18: =IFERROR(HistoricalFS!H37,0) -> 0.14777011 | I18: =IFERROR(HistoricalFS!I37,0) -> 0.153983 | J18: =IFERROR(HistoricalFS!J37,0) -> 0.13889301 | ... L18: =IFERROR(HistoricalFS!L37,0) -> 0.1169124 | N18: =IFERROR(AVERAGE(C18:L18),0) -> 0.13777519 | O18: =IFERROR(MEDIAN(C18:L18),0) -> 0.13504607
B20: SalesExpenses%Sales | C20: =IFERROR(HistoricalFS!C19,0) -> 0.23471592 | D20: =IFERROR(HistoricalFS!D19,0) -> 0.19099394 | E20: =IFERROR(HistoricalFS!E19,0) -> 0.19943547 | F20: =IFERROR(HistoricalFS!F19,0) -> 0.20425634 | G20: =IFERROR(HistoricalFS!G19,0) -> 0.2046607 | H20: =IFERROR(HistoricalFS!H19,0) -> 0.19973867 | I20: =IFERROR(HistoricalFS!I19,0) -> 0.18797637 | J20: =IFERROR(HistoricalFS!J19,0) -> 0.17303792 | ... L20: =IFERROR(HistoricalFS!L19,0) -> 0.21267357 | N20: =IFERROR(AVERAGE(C20:L20),0) -> 0.1992602 | O20: =IFERROR(MEDIAN(C20:L20),0) -> 0.19958707
B21: Depreciation%Sales | C21: =IFERROR(HistoricalFS!C28,0) -> 0.010972846 | D21: =IFERROR(HistoricalFS!D28,0) -> 0.011945802 | E21: =IFERROR(HistoricalFS!E28,0) -> 0.015275289 | F21: =IFERROR(HistoricalFS!F28,0) -> 0.015809201 | G21: =IFERROR(HistoricalFS!G28,0) -> 0.016479969 | H21: =IFERROR(HistoricalFS!H28,0) -> 0.019905558 | I21: =IFERROR(HistoricalFS!I28,0) -> 0.018483727 | J21: =IFERROR(HistoricalFS!J28,0) -> 0.017100151 | ... L21: =IFERROR(HistoricalFS!L28,0) -> 0.017094078 | N21: =IFERROR(AVERAGE(C21:L21),0) -> 0.016081148 | O21: =IFERROR(MEDIAN(C21:L21),0) -> 0.016787023
B22: OperatingIncome%Sales | C22: =C16 -> 0.1557049 | D22: =D16 -> 0.18480202 | E22: =E16 -> 0.19045718 | F22: =F16 -> 0.19586024 | G22: =G16 -> 0.19018086 | H22: =H16 -> 0.19740788 | I22: =I16 -> 0.1990648 | J22: =J16 -> 0.17914308 | ... L22: =L16 -> 0.19270281 | N22: =IFERROR(AVERAGE(C22:L22),0) -> 0.18510578 | O22: =IFERROR(MEDIAN(C22:L22),0) -> 0.19031902
B24: Return on Capital Employed | C24: =IFERROR((HistoricalFS!C21-HistoricalFS!C27)/SUM(HistoricalFS!C51:C53),0) -> 0.18329529 | D24: =IFERROR((HistoricalFS!D21-HistoricalFS!D27)/SUM(HistoricalFS!D51:D53),0) -> 0.2174815 | E24: =IFERROR((HistoricalFS!E21-HistoricalFS!E27)/SUM(HistoricalFS!E51:E53),0) -> 0.18974124 | F24: =IFERROR((HistoricalFS!F21-HistoricalFS!F27)/SUM(HistoricalFS!F51:F53),0) -> 0.19749577 | G24: =IFERROR((HistoricalFS!G21-HistoricalFS!G27)/SUM(HistoricalFS!G51:G53),0) -> 0.18420467 | H24: =IFERROR((HistoricalFS!H21-HistoricalFS!H27)/SUM(HistoricalFS!H51:H53),0) -> 0.17052329 | I24: =IFERROR((HistoricalFS!I21-HistoricalFS!I27)/SUM(HistoricalFS!I51:I53),0) -> 0.19423474 | J24: =IFERROR((HistoricalFS!J21-HistoricalFS!J27)/SUM(HistoricalFS!J51:J53),0) -> 0.16585258 | ... L24: =IFERROR((HistoricalFS!L21-HistoricalFS!L27)/SUM(HistoricalFS!L51:L53),0) -> 0.17169582 | N24: =IFERROR(AVERAGE(C24:L24),0) -> 0.18224034 | O24: =IFERROR(MEDIAN(C24:L24),0) -> 0.18374998
B25: Retained Earnings% | C25: =IFERROR(HistoricalFS!C47,0) -> 0.79276527 | D25: =IFERROR(HistoricalFS!D47,0) -> 0.82081343 | E25: =IFERROR(HistoricalFS!E47,0) -> 0.58523774 | F25: =IFERROR(HistoricalFS!F47,0) -> 0.49566955 | G25: =IFERROR(HistoricalFS!G47,0) -> 0.48362784 | H25: =IFERROR(HistoricalFS!H47,0) -> 0.44156447 | I25: =IFERROR(HistoricalFS!I47,0) -> 1 | J25: =IFERROR(HistoricalFS!J47,0) -> 1 | ... L25: =IFERROR(HistoricalFS!L47,0) -> 1 | N25: =IFERROR(AVERAGE(C25:L25),0) -> 0.76196783 | O25: =IFERROR(MEDIAN(C25:L25),0) -> 0.80678935
B26: Return on Equity% | C26: =IFERROR(HistoricalFS!C36/(SUM(HistoricalFS!C51:C52)),0) -> 0.20957666 | D26: =IFERROR(HistoricalFS!D36/(SUM(HistoricalFS!D51:D52)),0) -> 0.25607458 | E26: =IFERROR(HistoricalFS!E36/(SUM(HistoricalFS!E51:E52)),0) -> 0.23232773 | F26: =IFERROR(HistoricalFS!F36/(SUM(HistoricalFS!F51:F52)),0) -> 0.215857 | G26: =IFERROR(HistoricalFS!G36/(SUM(HistoricalFS!G51:G52)),0) -> 0.27240977 | H26: =IFERROR(HistoricalFS!H36/(SUM(HistoricalFS!H51:H52)),0) -> 0.18542077 | I26: =IFERROR(HistoricalFS!I36/(SUM(HistoricalFS!I51:I52)),0) -> 0.17991715 | J26: =IFERROR(HistoricalFS!J36/(SUM(HistoricalFS!J51:J52)),0) -> 0.14755368 | ... L26: =IFERROR(HistoricalFS!L36/(SUM(HistoricalFS!L51:L52)),0) -> 0.13080929 | N26: =IFERROR(AVERAGE(C26:L26),0) -> 0.19450788 | O26: =IFERROR(MEDIAN(C26:L26),0) -> 0.19749871
B27: Self Sustained Growth Rate | C27: =IFERROR(C25*C26,0) -> 0.1661451 | D27: =IFERROR(D25*D26,0) -> 0.21018946 | E27: =IFERROR(E25*E26,0) -> 0.13596696 | F27: =IFERROR(F25*F26,0) -> 0.10699374 | G27: =IFERROR(G25*G26,0) -> 0.13174495 | H27: =IFERROR(H25*H26,0) -> 0.081875225 | I27: =IFERROR(I25*I26,0) -> 0.17991715 | J27: =IFERROR(J25*J26,0) -> 0.14755368 | ... L27: =IFERROR(L25*L26,0) -> 0.13080929 | N27: =IFERROR(AVERAGE(C27:L27),0) -> 0.14063277 | O27: =IFERROR(MEDIAN(C27:L27),0) -> 0.13385595
B28: Interest Coverage Ratio | C28: =IFERROR((HistoricalFS!C21-HistoricalFS!C27)/HistoricalFS!C24,0) -> 11.454473 | D28: =IFERROR((HistoricalFS!D21-HistoricalFS!D27)/HistoricalFS!D24,0) -> 12.15831 | E28: =IFERROR((HistoricalFS!E21-HistoricalFS!E27)/HistoricalFS!E24,0) -> 11.447824 | F28: =IFERROR((HistoricalFS!F21-HistoricalFS!F27)/HistoricalFS!F24,0) -> 11.140943 | G28: =IFERROR((HistoricalFS!G21-HistoricalFS!G27)/HistoricalFS!G24,0) -> 8.2347089 | H28: =IFERROR((HistoricalFS!H21-HistoricalFS!H27)/HistoricalFS!H24,0) -> 8.5761189 | I28: =IFERROR((HistoricalFS!I21-HistoricalFS!I27)/HistoricalFS!I24,0) -> 15.949219 | J28: =IFERROR((HistoricalFS!J21-HistoricalFS!J27)/HistoricalFS!J24,0) -> 17.988304 | ... L28: =IFERROR((HistoricalFS!L21-HistoricalFS!L27)/HistoricalFS!L24,0) -> 8.7746229 | N28: =IFERROR(AVERAGE(C28:L28),0) -> 11.743351 | O28: =IFERROR(MEDIAN(C28:L28),0) -> 11.451148
B30: Debtor Turnover Ratio | C30: =IFERROR(HistoricalFS!C9/HistoricalFS!C63,0) -> 10.28257 | D30: =IFERROR(HistoricalFS!D9/HistoricalFS!D63,0) -> 7.534709 | E30: =IFERROR(HistoricalFS!E9/HistoricalFS!E63,0) -> 9.0089916 | F30: =IFERROR(HistoricalFS!F9/HistoricalFS!F63,0) -> 7.9064071 | G30: =IFERROR(HistoricalFS!G9/HistoricalFS!G63,0) -> 7.9776781 | H30: =IFERROR(HistoricalFS!H9/HistoricalFS!H63,0) -> 8.5640959 | I30: =IFERROR(HistoricalFS!I9/HistoricalFS!I63,0) -> 10.979214 | J30: =IFERROR(HistoricalFS!J9/HistoricalFS!J63,0) -> 10.997295 | ... L30: =IFERROR(HistoricalFS!L9/HistoricalFS!L63,0) -> 9.1809206 | N30: =IFERROR(AVERAGE(C30:L30),0) -> 9.3125034 | O30: =IFERROR(MEDIAN(C30:L30),0) -> 9.0949561
B31: Creditor Turnover Ratio | C31: =IFERROR(HistoricalFS!C9/HistoricalFS!C54,0) -> 3.9448927 | D31: =IFERROR(HistoricalFS!D9/HistoricalFS!D54,0) -> 3.3419343 | E31: =IFERROR(HistoricalFS!E9/HistoricalFS!E54,0) -> 2.5479701 | F31: =IFERROR(HistoricalFS!F9/HistoricalFS!F54,0) -> 2.4030489 | G31: =IFERROR(HistoricalFS!G9/HistoricalFS!G54,0) -> 2.994368 | H31: =IFERROR(HistoricalFS!H9/HistoricalFS!H54,0) -> 2.9089948 | I31: =IFERROR(HistoricalFS!I9/HistoricalFS!I54,0) -> 3.7500578 | J31: =IFERROR(HistoricalFS!J9/HistoricalFS!J54,0) -> 4.3505147 | ... L31: =IFERROR(HistoricalFS!L9/HistoricalFS!L54,0) -> 5.4820733 | N31: =IFERROR(AVERAGE(C31:L31),0) -> 3.702174 | O31: =IFERROR(MEDIAN(C31:L31),0) -> 3.545996
B32: Inventory Turnover | C32: =IFERROR(HistoricalFS!C9/HistoricalFS!C64,0) -> 7.719579 | D32: =IFERROR(HistoricalFS!D9/HistoricalFS!D64,0) -> 6.4453014 | E32: =IFERROR(HistoricalFS!E9/HistoricalFS!E64,0) -> 6.5613522 | F32: =IFERROR(HistoricalFS!F9/HistoricalFS!F64,0) -> 6.2415574 | G32: =IFERROR(HistoricalFS!G9/HistoricalFS!G64,0) -> 6.6177378 | H32: =IFERROR(HistoricalFS!H9/HistoricalFS!H64,0) -> 5.8192024 | I32: =IFERROR(HistoricalFS!I9/HistoricalFS!I64,0) -> 6.4259985 | J32: =IFERROR(HistoricalFS!J9/HistoricalFS!J64,0) -> 5.7640209 | ... L32: =IFERROR(HistoricalFS!L9/HistoricalFS!L64,0) -> 11.091265 | N32: =IFERROR(AVERAGE(C32:L32),0) -> 7.134878 | O32: =IFERROR(MEDIAN(C32:L32),0) -> 6.5033268
B33: Fixed Asset Turnover | C33: =IFERROR(HistoricalFS!C9/HistoricalFS!C57,0) -> 1.4904025 | D33: =IFERROR(HistoricalFS!D9/HistoricalFS!D57,0) -> 1.4202154 | E33: =IFERROR(HistoricalFS!E9/HistoricalFS!E57,0) -> 1.1466085 | F33: =IFERROR(HistoricalFS!F9/HistoricalFS!F57,0) -> 1.1842971 | G33: =IFERROR(HistoricalFS!G9/HistoricalFS!G57,0) -> 1.1896229 | H33: =IFERROR(HistoricalFS!H9/HistoricalFS!H57,0) -> 1.0735966 | I33: =IFERROR(HistoricalFS!I9/HistoricalFS!I57,0) -> 1.238507 | J33: =IFERROR(HistoricalFS!J9/HistoricalFS!J57,0) -> 1.3316087 | ... L33: =IFERROR(HistoricalFS!L9/HistoricalFS!L57,0) -> 1.3501711 | N33: =IFERROR(AVERAGE(C33:L33),0) -> 1.276552 | O33: =IFERROR(MEDIAN(C33:L33),0) -> 1.2850578
B34: Capital Turnover Ratio | C34: =IFERROR(HistoricalFS!C9/(SUM(HistoricalFS!C51:C52)),0) -> 1.9192171 | D34: =IFERROR(HistoricalFS!D9/(SUM(HistoricalFS!D51:D52)),0) -> 1.9742111 | E34: =IFERROR(HistoricalFS!E9/(SUM(HistoricalFS!E51:E52)),0) -> 1.7480191 | F34: =IFERROR(HistoricalFS!F9/(SUM(HistoricalFS!F51:F52)),0) -> 1.5734967 | G34: =IFERROR(HistoricalFS!G9/(SUM(HistoricalFS!G51:G52)),0) -> 1.4193551 | H34: =IFERROR(HistoricalFS!H9/(SUM(HistoricalFS!H51:H52)),0) -> 1.2547921 | I34: =IFERROR(HistoricalFS!I9/(SUM(HistoricalFS!I51:I52)),0) -> 1.1684222 | J34: =IFERROR(HistoricalFS!J9/(SUM(HistoricalFS!J51:J52)),0) -> 1.062355 | ... L34: =IFERROR(HistoricalFS!L9/(SUM(HistoricalFS!L51:L52)),0) -> 1.1188659 | N34: =IFERROR(AVERAGE(C34:L34),0) -> 1.4204063 | O34: =IFERROR(MEDIAN(C34:L34),0) -> 1.3370736
B36: Debtor Days | C36: =IFERROR(365/C30,0) -> 35.496963 | D36: =IFERROR(365/D30,0) -> 48.442481 | E36: =IFERROR(365/E30,0) -> 40.515078 | F36: =IFERROR(365/F30,0) -> 46.165091 | G36: =IFERROR(365/G30,0) -> 45.752661 | H36: =IFERROR(365/H30,0) -> 42.619794 | I36: =IFERROR(365/I30,0) -> 33.24464 | J36: =IFERROR(365/J30,0) -> 33.189981 | ... L36: =IFERROR(365/L30,0) -> 39.756362 | N36: =IFERROR(AVERAGE(C36:L36),0) -> 39.931704 | O36: =IFERROR(MEDIAN(C36:L36),0) -> 40.13572
B37: Payable Days | C37: =IFERROR(365/C31,0) -> 92.524697 | D37: =IFERROR(365/D31,0) -> 109.21819 | E37: =IFERROR(365/E31,0) -> 143.25129 | F37: =IFERROR(365/F31,0) -> 151.89038 | G37: =IFERROR(365/G31,0) -> 121.89551 | H37: =IFERROR(365/H31,0) -> 125.47289 | I37: =IFERROR(365/I31,0) -> 97.331833 | J37: =IFERROR(365/J31,0) -> 83.898118 | ... L37: =IFERROR(365/L31,0) -> 66.580649 | N37: =IFERROR(AVERAGE(C37:L37),0) -> 106.0959 | O37: =IFERROR(MEDIAN(C37:L37),0) -> 103.27501
B38: Inventory Days | C38: =IFERROR(365/C32,0) -> 47.282371 | D38: =IFERROR(365/D32,0) -> 56.630401 | E38: =IFERROR(365/E32,0) -> 55.628777 | F38: =IFERROR(365/F32,0) -> 58.478994 | G38: =IFERROR(365/G32,0) -> 55.154799 | H38: =IFERROR(365/H32,0) -> 62.723372 | I38: =IFERROR(365/I32,0) -> 56.800511 | J38: =IFERROR(365/J32,0) -> 63.32385 | ... L38: =IFERROR(365/L32,0) -> 32.908781 | N38: =IFERROR(AVERAGE(C38:L38),0) -> 53.106621 | O38: =IFERROR(MEDIAN(C38:L38),0) -> 56.129589
B39: Cash Conversion Cycle (in days) | C39: =IFERROR(SUM(C36,C38)-C37,0) -> -9.745363 | D39: =IFERROR(SUM(D36,D38)-D37,0) -> -4.1453048 | E39: =IFERROR(SUM(E36,E38)-E37,0) -> -47.107433 | F39: =IFERROR(SUM(F36,F38)-F37,0) -> -47.246292 | G39: =IFERROR(SUM(G36,G38)-G37,0) -> -20.988047 | H39: =IFERROR(SUM(H36,H38)-H37,0) -> -20.129727 | I39: =IFERROR(SUM(I36,I38)-I37,0) -> -7.2866823 | J39: =IFERROR(SUM(J36,J38)-J37,0) -> 12.615713 | ... L39: =IFERROR(SUM(L36,L38)-L37,0) -> 6.0844942 | N39: =IFERROR(AVERAGE(C39:L39),0) -> -13.057571 | O39: =IFERROR(MEDIAN(C39:L39),0) -> -8.5160226
B41: CFO/Sales | C41: =IFERROR(HistoricalFS!C82/HistoricalFS!C9,0) -> 0.11688414 | D41: =IFERROR(HistoricalFS!D82/HistoricalFS!D9,0) -> 0.047840188 | E41: =IFERROR(HistoricalFS!E82/HistoricalFS!E9,0) -> 0.23964411 | F41: =IFERROR(HistoricalFS!F82/HistoricalFS!F9,0) -> 0.17496951 | G41: =IFERROR(HistoricalFS!G82/HistoricalFS!G9,0) -> 0.16937584 | H41: =IFERROR(HistoricalFS!H82/HistoricalFS!H9,0) -> 0.13470154 | I41: =IFERROR(HistoricalFS!I82/HistoricalFS!I9,0) -> 0.17998625 | J41: =IFERROR(HistoricalFS!J82/HistoricalFS!J9,0) -> 0.074451187 | ... L41: =IFERROR(HistoricalFS!L82/HistoricalFS!L9,0) -> 0.11449967 | N41: =IFERROR(AVERAGE(C41:L41),0) -> 0.1420947 | O41: =IFERROR(MEDIAN(C41:L41),0) -> 0.15164804
B42: CFO/Total Assets | C42: =IFERROR(HistoricalFS!C82/HistoricalFS!C68,0) -> 0.10597237 | D42: =IFERROR(HistoricalFS!D82/HistoricalFS!D68,0) -> 0.041637651 | E42: =IFERROR(HistoricalFS!E82/HistoricalFS!E68,0) -> 0.17163501 | F42: =IFERROR(HistoricalFS!F82/HistoricalFS!F68,0) -> 0.12428077 | G42: =IFERROR(HistoricalFS!G82/HistoricalFS!G68,0) -> 0.12395741 | H42: =IFERROR(HistoricalFS!H82/HistoricalFS!H68,0) -> 0.089716054 | I42: =IFERROR(HistoricalFS!I82/HistoricalFS!I68,0) -> 0.13935898 | J42: =IFERROR(HistoricalFS!J82/HistoricalFS!J68,0) -> 0.056833303 | ... L42: =IFERROR(HistoricalFS!L82/HistoricalFS!L68,0) -> 0.087755164 | N42: =IFERROR(AVERAGE(C42:L42),0) -> 0.1069894 | O42: =IFERROR(MEDIAN(C42:L42),0) -> 0.11496489
B43: CFO/Total Debt | C43: =IFERROR(HistoricalFS!C82/HistoricalFS!C53,0) -> 0.3558876 | D43: =IFERROR(HistoricalFS!D82/HistoricalFS!D53,0) -> 0.13939235 | E43: =IFERROR(HistoricalFS!E82/HistoricalFS!E53,0) -> 0.55512093 | F43: =IFERROR(HistoricalFS!F82/HistoricalFS!F53,0) -> 0.49122327 | G43: =IFERROR(HistoricalFS!G82/HistoricalFS!G53,0) -> 0.51655061 | H43: =IFERROR(HistoricalFS!H82/HistoricalFS!H53,0) -> 0.37342971 | I43: =IFERROR(HistoricalFS!I82/HistoricalFS!I53,0) -> 1.0649313 | J43: =IFERROR(HistoricalFS!J82/HistoricalFS!J53,0) -> 0.53627797 | ... L43: =IFERROR(HistoricalFS!L82/HistoricalFS!L53,0) -> 0.50090001 | N43: =IFERROR(AVERAGE(C43:L43),0) -> 0.65211781 | O43: =IFERROR(MEDIAN(C43:L43),0) -> 0.50872531

Sheet Common Size Statement
B2: ='Data Sheet'!B1 -> GODREJ CONSUMER PRODUCTS LTD
B3: (GODREJCP | BSE Code: 532424)
B5: Common Size Income Statement - GODREJ CONSUMER PRODUCTS LTD
B7: Particulars | C7: 42094 | D7: 42460 | E7: 42825 | F7: 43190 | G7: 43555 | H7: 43921 | I7: 44286 | J7: 44651 | K7: 45016 | L7: 45382
B9: Sales | C9: 1 | D9: 1 | E9: 1 | F9: 1 | G9: 1 | H9: 1 | I9: 1 | J9: 1 | K9: 1 | L9: 1
B10: Raw Material Cost | C10: 0.46010045 | D10: 0.46999008 | E10: 0.46028177 | F10: 0.42837167 | G10: 0.42657019 | H10: 0.44747447 | I10: 0.45080618 | J10: 0.49986804 | K10: 0.48737343 | L10: 0.44930339
B11: Change in Inventory | C11: -0.004235388 | D11: 0.010909462 | E11: 0.014386199 | F11: -0.0056867629 | G11: -0.014983024 | H11: 0.01747084 | I11: 0.003840009 | J11: 0.0050128294 | K11: -0.015991325 | L11: 0.00093146265
B12: Power and Fuel | C12: 0.013286354 | D12: 0.013056929 | E12: 0.0096051861 | F12: 0.010267654 | G12: 0.011565452 | H12: 0.011935464 | I12: 0.0096322115 | J12: 0.01087362 | K12: 0.011612372 | L12: 0.010701534
B13: Other Mfr. Exp | C13: 0.027071913 | D13: 0.028042897 | E13: 0.03267727 | F13: 0.032368852 | G13: 0.031974901 | H13: 0.038209832 | I13: 0.036019919 | J13: 0.035050707 | K13: 0.032961174 | L13: 0.029825959
B14: Employee Cost | C14: 0.093912234 | D14: 0.11207781 | E14: 0.10665404 | F14: 0.10737929 | G14: 0.10358491 | H14: 0.10279897 | I14: 0.10185681 | J14: 0.089939315 | K14: 0.083469698 | L14: 0.088630126
B15: Selling and admin | C15: 0.21984975 | D15: 0.17390799 | E15: 0.17796785 | F15: 0.18032725 | G15: 0.18312951 | H15: 0.17860617 | I15: 0.16400329 | J15: 0.14959394 | K15: 0.16104272 | L15: 0.18726159
B16: Other Expenses | C16: 0.014866163 | D16: 0.017085951 | E16: 0.021467623 | F16: 0.023929086 | G16: 0.021531189 | H16: 0.021132502 | I16: 0.023973081 | J16: 0.023443978 | K16: 0.024070346 | L16: 0.025411975
B17: Other Income | C17: 0.0088249337 | D17: -0.031106806 | E17: 0.0082197604 | F17: 0.028766897 | G17: 0.035091921 | H17: 0.0032348549 | I17: 0.0020492138 | J17: 0.0063755957 | K17: 0.0085836781 | L17: -0.15667869
B18: Depreciation | C18: 0.010972846 | D18: 0.011945802 | E18: 0.015275289 | F18: 0.015809201 | G18: 0.016479969 | H18: 0.019905558 | I18: 0.018483727 | J18: 0.017100151 | K18: 0.017744858 | L18: 0.017094078
B19: Interest | C19: 0.013593371 | D19: 0.015199647 | E19: 0.016636976 | F19: 0.017580221 | G19: 0.023095031 | H19: 0.023018323 | I19: 0.012481163 | J19: 0.0099588645 | K19: 0.014154433 | L19: 0.021961378
... B24: EBITDA | C24: 0.16712498 | D24: 0.16528369 | E24: 0.2135325 | F24: 0.24043634 | G24: 0.24175274 | H24: 0.22054829 | I24: 0.21959774 | J24: 0.20261882 | K24: 0.19206261 | L24: 0.053118201
B26: Common Size Balance Sheet - GODREJ CONSUMER PRODUCTS LTD
B28: Particulars | C28: 42094 | D28: 42460 | E28: 42825 | F28: 43190 | G28: 43555 | H28: 43921 | I28: 44286 | J28: 44651 | K28: 45016 | L28: 45382
B30: Total Liabilities | C30: 1 | D30: 1 | E30: 1 | F30: 1 | G30: 1 | H30: 1 | I30: 1 | J30: 1 | K30: 1 | L30: 1
B31: Equity Share Capital | C31: 0.0037304028 | D31: 0.0035180199 | E31: 0.0026320975 | F31: 0.0049142477 | G31: 0.0072529632 | H31: 0.0068701664 | I31: 0.0071785669 | J31: 0.0063586144 | K31: 0.005865027 | L31: 0.0055610893
B32: Reserves | C32: 0.46867295 | D32: 0.43734102 | E32: 0.40709337 | F32: 0.44650048 | G32: 0.5083673 | H32: 0.52392361 | I32: 0.65548916 | J32: 0.71219901 | K32: 0.78521281 | L32: 0.67943865
B33: Borrowings | C33: 0.29776921 | D33: 0.2987083 | E33: 0.30918491 | F33: 0.25300261 | G33: 0.23997148 | H33: 0.24024884 | I33: 0.13086194 | J33: 0.10597732 | K33: 0.064779673 | L33: 0.17519498
B34: Other Liabilities | C34: 0.22982744 | D34: 0.26043266 | E34: 0.28108962 | F34: 0.29558266 | G34: 0.24440826 | H34: 0.22895739 | I34: 0.20647033 | J34: 0.17546505 | K34: 0.14414249 | L34: 0.13980529
B36: Total Assets | C36: 1 | D36: 1 | E36: 1 | F36: 1 | G36: 1 | H36: 1 | I36: 1 | J36: 1 | K36: 1 | L36: 1
B37: Net Block | C37: 0.60832195 | D37: 0.61282874 | E37: 0.62463167 | F37: 0.59976471 | G37: 0.61519348 | H37: 0.62037811 | I37: 0.62516858 | J37: 0.57326397 | K37: 0.5696801 | L37: 0.56764868
B38: Capital Work in Progress | C38: 0.024614741 | D38: 0.0045109177 | E38: 0.0075292208 | F38: 0.0060503023 | G38: 0.0036938883 | H38: 0.0038332612 | I38: 0.0040319325 | J38: 0.007240339 | K38: 0.002604767 | L38: 0.0045323857
B39: Investments | C39: 0.020349544 | D39: 0.019578995 | E39: 0.072142347 | F39: 0.071934257 | G39: 0.036611074 | H39: 0.045159096 | I39: 0.047676917 | J39: 0.063140307 | K39: 0.17370734 | L39: 0.19049885
B40: Other Assets | C40: 0.043096892 | D40: 0.034652238 | E40: 0.036513205 | F40: 0.049350213 | G40: 0.078691316 | H40: 0.086646891 | I40: 0.084916304 | J40: 0.085623662 | K40: 0.072032533 | L40: 0.055000848
B41: Receivables | C41: 0.088172957 | D41: 0.11551194 | E41: 0.079499237 | F41: 0.089838478 | G41: 0.091737 | H41: 0.077770714 | I41: 0.070521961 | J41: 0.069413734 | K41: 0.07141489 | L41: 0.083479954
... B43: Cash & Bank | C43: 0.097996498 | D43: 0.077881005 | E43: 0.070528776 | F43: 0.069260382 | G43: 0.06348436 | H43: 0.051757091 | I43: 0.047193198 | J43: 0.068882088 | K43: 0.02240719 | L43: 0.0297378

Sheet Forcasting
B2: ='Data Sheet'!B1 -> GODREJ CONSUMER PRODUCTS LTD
B3: (GODREJCP | BSE Code: 532424)
B5: Forecasting - GODREJ CONSUMER PRODUCTS LTD
B7: ='Data Sheet'!$B$1&" - "&'Data Sheet'!A17&" Forecasting" -> GODREJ CONSUMER PRODUCTS LTD - Sales Forecasting | G7: ='Data Sheet'!$B$1&" - "&'Data Sheet'!A34&" Forecasting" -> GODREJ CONSUMER PRODUCTS LTD - EBITDA Forecasting | L7: ='Data Sheet'!$B$1&" - "&" EPS Forecasting" -> GODREJ CONSUMER PRODUCTS LTD - EPS Forecasting
B8: Year Weight | C8: Year | D8: Sales | E8: Sales Growth | G8: Year Weight | H8: Year | I8: EBITDA | J8: EBITDA Growth | L8: Year Weight | M8: Year | N8: EPS | O8: EPS Growth
B9: 1 | C9: ='Data Sheet'!$B$16 -> 42094 | D9: {=TRANSPOSE('Data Sheet'!B17:K17)} -> 8273.15 | E9: - | G9: 1 | H9: ='Data Sheet'!$B$16 -> 42094 | I9: {=TRANSPOSE(HistoricalFS!C21:L21)} -> 1378.95 | J9: - | L9: 1 | M9: ='Data Sheet'!$B$16 -> 42094 | N9: {=TRANSPOSE(HistoricalFS!C41:L41)} -> 8.8449187
B10: =B9+1 -> 2 | C10: =C9+365 -> 42459 | D10: 8423.88 | E10: =D10/D9-1 -> 0.018219179 | G10: =G9+1 -> 2 | H10: =H9+365 -> 42459 | I10: 1657.38 | J10: =I10/I9-1 -> 0.2019145 | L10: =L9+1 -> 2 | M10: =M9+365 -> 42459 | N10: 10.695576 | O10: =N10/N9-1 -> 0.2092339
B11: =B10+1 -> 3 | C11: =C10+365 -> 42824 | D11: 9267.91 | E11: =D11/D10-1 -> 0.10019492 | G11: =G10+1 -> 3 | H11: =H10+365 -> 42824 | I11: 1906.71 | J11: =I11/I10-1 -> 0.15043623 | L11: =L10+1 -> 3 | M11: =M10+365 -> 42824 | N11: 12.055099 | O11: =N11/N10-1 -> 0.12711081
B12: =B11+1 -> 4 | C12: =C11+365 -> 43189 | D12: 9847.43 | E12: =D12/D11-1 -> 0.06252974 | G12: =G11+1 -> 4 | H12: =H11+365 -> 43189 | I12: 2084.4 | J12: =I12/I11-1 -> 0.093191938 | L12: =L11+1 -> 4 | M12: =M11+365 -> 43189 | N12: 13.2182 | O12: =N12/N11-1 -> 0.096482059
B13: =B12+1 -> 5 | C13: =C12+365 -> 43554 | D13: 10314.34 | E13: =D13/D12-1 -> 0.047414402 | G13: =G12+1 -> 5 | H13: =H12+365 -> 43554 | I13: 2131.57 | J13: =I13/I12-1 -> 0.022630013 | L13: =L12+1 -> 5 | M13: =M12+365 -> 43554 | N13: 19.365878 | O13: =N13/N12-1 -> 0.46509193
B14: =B13+1 -> 6 | C14: =C13+365 -> 43919 | D14: 9910.8 | E14: =D14/D13-1 -> -0.039124171 | G14: =G13+1 -> 6 | H14: =H13+365 -> 43919 | I14: 2153.75 | J14: =I14/I13-1 -> 0.010405476 | L14: =L13+1 -> 6 | M14: =M13+365 -> 43919 | N14: 14.325736 | O14: =N14/N13-1 -> -0.26025887
B15: =B14+1 -> 7 | C15: =C14+365 -> 44284 | D15: 11028.62 | E15: =D15/D14-1 -> 0.11278807 | G15: =G14+1 -> 7 | H15: =H14+365 -> 44284 | I15: 2399.26 | J15: =I15/I14-1 -> 0.11399187 | L15: =L14+1 -> 7 | M15: =M14+365 -> 44284 | N15: 16.608509 | O15: =N15/N14-1 -> 0.15934766
B16: =B15+1 -> 8 | C16: =C15+365 -> 44649 | D16: 12276.5 | E16: =D16/D15-1 -> 0.11314924 | G16: =G15+1 -> 8 | H16: =H15+365 -> 44649 | I16: 2409.18 | J16: =I16/I15-1 -> 0.0041346082 | L16: =L15+1 -> 8 | M16: =M15+365 -> 44649 | N16: 16.674359 | O16: =N16/N15-1 -> 0.0039648905
B17: =B16+1 -> 9 | C17: =C16+365 -> 45014 | D17: 13315.97 | E17: =D17/D16-1 -> 0.084671527 | G17: =G16+1 -> 9 | H17: =H16+365 -> 45014 | I17: 2443.2 | J17: =I17/I16-1 -> 0.014120987 | L17: =L16+1 -> 9 | M17: =M16+365 -> 45014 | N17: 15.52909 | O17: =N17/N16-1 -> -0.068684486
B18: =B17+1 -> 10 | C18: =C17+365 -> 45379 | D18: 14096.11 | E18: =D18/D17-1 -> 0.058586795 | G18: =G17+1 -> 10 | H18: =H17+365 -> 45379 | I18: 2957.32 | J18: =I18/I17-1 -> 0.21042895 | L18: =L17+1 -> 10 | M18: =M17+365 -> 45379 | N18: 16.11273 | O18: =N18/N17-1 -> 0.037583665
B19: =B18+1 -> 11 | C19: =C18+365 -> 45744 | D19: =FORECAST(B19,D9:D18,B9:B18) -> 14169.946 | E19: =D19/D18-1 -> 0.0052380408 | G19: =G18+1 -> 11 | H19: =H18+365 -> 45744 | I19: =FORECAST(G19,I9:I18,G9:G18) -> 2925.0113 | J19: =I19/I18-1 -> -0.010924982 | L19: =L18+1 -> 11 | M19: =M18+365 -> 45744 | N19: =FORECAST(L19,N9:N18,L9:L18) -> 18.592076 | O19: =N19/N18-1 -> 0.15387497
B20: =B19+1 -> 12 | C20: =C19+365 -> 46109 | D20: =FORECAST(B20,D10:D19,B10:B19) -> 14927.117 | E20: =D20/D19-1 -> 0.053435 | G20: =G19+1 -> 12 | H20: =H19+365 -> 46109 | I20: =FORECAST(G20,I10:I19,G10:G19) -> 3027.9545 | J20: =I20/I19-1 -> 0.03519412 | L20: =L19+1 -> 12 | M20: =M19+365 -> 46109 | N20: =FORECAST(L20,N10:N19,L10:L19) -> 18.825545 | O20: =N20/N19-1 -> 0.012557446
B21: =B20+1 -> 13 | C21: =C20+365 -> 46474 | D21: =FORECAST(B21,D11:D20,B11:B20) -> 15634.231 | E21: =D21/D20-1 -> 0.047371132 | G21: =G20+1 -> 13 | H21: =H20+365 -> 46474 | I21: =FORECAST(G21,I11:I20,G11:G20) -> 3143.2523 | J21: =I21/I20-1 -> 0.038077759 | L21: =L20+1 -> 13 | M21: =M20+365 -> 46474 | N21: =FORECAST(L21,N11:N20,L11:L20) -> 18.996099 | O21: =N21/N20-1 -> 0.0090597434
B22: =B21+1 -> 14 | C22: =C21+365 -> 46839 | D22: =FORECAST(B22,D12:D21,B12:B21) -> 16415.717 | E22: =D22/D21-1 -> 0.049985554 | G22: =G21+1 -> 14 | H22: =H21+365 -> 46839 | I22: =FORECAST(G22,I12:I21,G12:G21) -> 3279.7854 | J22: =I22/I21-1 -> 0.043436914 | L22: =L21+1 -> 14 | M22: =M21+365 -> 46839 | N22: =FORECAST(L22,N12:N21,L12:L21) -> 19.055417 | O22: =N22/N21-1 -> 0.0031226438
B23: =B22+1 -> 15 | C23: =C22+365 -> 47204 | D23: =FORECAST(B23,D13:D22,B13:B22) -> 17239.914 | E23: =D23/D22-1 -> 0.050207812 | G23: =G22+1 -> 15 | H23: =H22+365 -> 47204 | I23: =FORECAST(G23,I13:I22,G13:G22) -> 3435.8797 | J23: =I23/I22-1 -> 0.047592839 | L23: =L22+1 -> 15 | M23: =M22+365 -> 47204 | N23: =FORECAST(L23,N13:N22,L13:L22) -> 18.985889 | O23: =N23/N22-1 -> -0.0036487199
B24: =B23+1 -> 16 | C24: =C23+365 -> 47569 | D24: =FORECAST(B24,D14:D23,B14:B23) -> 18080.414 | E24: =D24/D23-1 -> 0.048753123 | G24: =G23+1 -> 16 | H24: =H23+365 -> 47569 | I24: =FORECAST(G24,I14:I23,G14:G23) -> 3587.2981 | J24: =I24/I23-1 -> 0.044069739 | L24: =L23+1 -> 16 | M24: =M23+365 -> 47569 | N24: =FORECAST(L24,N14:N23,L14:L23) -> 20.138783 | O24: =N24/N23-1 -> 0.060723724

Sheet Beta Regression
B2: ='Data Sheet'!B1 -> GODREJ CONSUMER PRODUCTS LTD
B3: (GODREJCP | BSE Code: 532424)
B5: Beta Regression - GODREJ CONSUMER PRODUCTS LTD
B7: Regression Beta - 1 Year Weekly
B9: Godrej Consumer Products Weekly Returns | F9: NIFTY Returns | I9: Beta Drifting
B11: Date | C11: Closing Price | D11: Return | F11: Closing Price | G11: Return | I11: Levered Raw Beta | J11: =O11 -> 0.740835 | N11: beta 1 | O11: =SLOPE(D12:D65,G12:G65) -> 0.740835
B12: 45208 | C12: 967.26 | F12: 19751.05 | I12: Raw Beta Weight | J12: 0.75
B13: 45215 | C13: 972.38 | D13: =C13/C12-1 -> 0.0052933027 | F13: 19542.65 | G13: =F13/F12-1 -> -0.010551338 | N13: beta 2 | O13: =(_xlfn.COVARIANCE.S(D12:D65,G12:G65))/_xlfn.VAR.S(G12:G65) -> 0.740835
B14: 45222 | C14: 971.49 | D14: =C14/C13-1 -> -0.00091528003 | F14: 19047.25 | G14: =F14/F13-1 -> -0.025349684 | I14: Market Beta | J14: 1
B15: 45229 | C15: 1004.41 | D15: =C15/C14-1 -> 0.033886092 | F15: 19230.6 | G15: =F15/F14-1 -> 0.0096260615 | I15: Market Beta Weight | J15: 0.25 | N15: beta 3 | O15: =O37 -> 0.740835
B16: 45236 | C16: 968.59 | D16: =C16/C15-1 -> -0.035662727 | F16: 19425.35 | G16: =F16/F15-1 -> 0.010127089
B17: 45243 | C17: 985.89 | D17: =C17/C16-1 -> 0.017861014 | F17: 19731.8 | G17: =F17/F16-1 -> 0.015775778 | I17: Adjusted Beta | J17: =(J11*J12)+(J14*J15) -> 0.80562625
B18: 45250 | C18: 998.3 | D18: =C18/C17-1 -> 0.012587611 | F18: 19794.7 | G18: =F18/F17-1 -> 0.0031877477
B19: 45257 | C19: 1014.03 | D19: =C19/C18-1 -> 0.015756787 | F19: 20267.9 | G19: =F19/F18-1 -> 0.023905389
B20: 45264 | C20: 1010.22 | D20: =C20/C19-1 -> -0.0037572853 | F20: 20969.4 | G20: =F20/F19-1 -> 0.034611381 | N20: SUMMARY OUTPUT
B21: 45271 | C21: 1030.59 | D21: =C21/C20-1 -> 0.020163925 | F21: 21456.65 | G21: =F21/F20-1 -> 0.023236239
B22: 45278 | C22: 1062.33 | D22: =C22/C21-1 -> 0.030797892 | F22: 21349.4 | G22: =F22/F21-1 -> -0.0049984504 | N22: Regression Statistics
B23: 45285 | C23: 1118.65 | D23: =C23/C22-1 -> 0.053015541 | F23: 21731.4 | G23: =F23/F22-1 -> 0.017892775 | N23: Multiple R | O23: 0.34239135
B24: 45292 | C24: 1206.32 | D24: =C24/C23-1 -> 0.078371251 | F24: 21710.8 | G24: =F24/F23-1 -> -0.00094793709 | N24: R Square | O24: 0.11723184
B25: 45299 | C25: 1142.68 | D25: =C25/C24-1 -> -0.052755488 | F25: 21894.55 | G25: =F25/F24-1 -> 0.0084635297 | N25: Adjusted R Square | O25: 0.099922657
B26: 45306 | C26: 1136.5 | D26: =C26/C25-1 -> -0.0054083383 | F26: 21622.4 | G26: =F26/F25-1 -> -0.012430034 | N26: Standard Error | O26: 0.031829075
B27: 45313 | C27: 1144.46 | D27: =C27/C26-1 -> 0.0070039595 | F27: 21352.6 | G27: =F27/F26-1 -> -0.012477801 | N27: Observations | O27: 53
B28: 45320 | C28: 1223.13 | D28: =C28/C27-1 -> 0.068739842 | F28: 21853.8 | G28: =F28/F27-1 -> 0.023472551
B29: 45327 | C29: 1205.13 | D29: =C29/C28-1 -> -0.014716342 | F29: 21782.5 | G29: =F29/F28-1 -> -0.0032625905 | N29: ANOVA
B30: 45334 | C30: 1227.58 | D30: =C30/C29-1 -> 0.018628696 | F30: 22040.7 | G30: =F30/F29-1 -> 0.011853552 | O30: df | P30: SS | Q30: MS | R30: F | S30: Significance F
B31: 45341 | C31: 1237.07 | D31: =C31/C30-1 -> 0.0077306571 | F31: 22212.7 | G31: =F31/F30-1 -> 0.0078037449 | N31: Regression | O31: 1 | P31: 0.0068614691 | Q31: 0.0068614691 | R31: 6.7728129 | S31: 0.012087864
B32: 45348 | C32: 1253.39 | D32: =C32/C31-1 -> 0.013192463 | F32: 22338.75 | G32: =F32/F31-1 -> 0.0056746816 | N32: Residual | O32: 51 | P32: 0.05166759 | Q32: 0.00101309
B33: 45355 | C33: 1220.56 | D33: =C33/C32-1 -> -0.026192965 | F33: 22493.55 | G33: =F33/F32-1 -> 0.0069296626 | N33: Total | O33: 52 | P33: 0.058529059
B34: 45362 | C34: 1199.25 | D34: =C34/C33-1 -> -0.017459199 | F34: 22023.35 | G34: =F34/F33-1 -> -0.02090377
B35: 45369 | C35: 1208.1 | D35: =C35/C34-1 -> 0.0073796123 | F35: 22096.75 | G35: =F35/F34-1 -> 0.0033328263 | O35: Coefficients | P35: Standard Error | Q35: t Stat | R35: P-value | S35: Lower 95% | T35: Upper 95% | U35: Lower 95.0% | V35: Upper 95.0%
B36: 45376 | C36: 1237.92 | D36: =C36/C35-1 -> 0.024683387 | F36: 22326.9 | G36: =F36/F35-1 -> 0.010415559 | N36: Intercept | O36: 0.0033462633 | P36: 0.0045529703 | Q36: 0.73496268 | R36: 0.46572853 | S36: -0.0057942061 | T36: 0.012486733 | U36: -0.0057942061 | V36: 0.012486733
B37: 45383 | C37: 1196.68 | D37: =C37/C36-1 -> -0.033313946 | F37: 22513.7 | G37: =F37/F36-1 -> 0.0083665892 | N37: X Variable 1 | O37: 0.740835 | P37: 0.28466689 | Q37: 2.6024629 | R37: 0.012087864 | S37: 0.16934238 | T37: 1.3123276 | U37: 0.16934238 | V37: 1.3123276
B38: 45390 | C38: 1186.44 | D38: =C38/C37-1 -> -0.0085570077 | F38: 22519.4 | G38: =F38/F37-1 -> 0.00025317918
B39: 45397 | C39: 1155.89 | D39: =C39/C38-1 -> -0.0257493 | F39: 22147 | G39: =F39/F38-1 -> -0.016536853
B40: 45404 | C40: 1189.16 | D40: =C40/C39-1 -> 0.028783016 | F40: 22419.95 | G40: =F40/F39-1 -> 0.012324468
B41: 45411 | C41: 1237.32 | D41: =C41/C40-1 -> 0.040499176 | F41: 22475.85 | G41: =F41/F40-1 -> 0.0024933151
B42: 45418 | C42: 1306.3 | D42: =C42/C41-1 -> 0.055749523 | F42: 22055.2 | G42: =F42/F41-1 -> -0.018715644
B43: 45425 | C43: 1284.99 | D43: =C43/C42-1 -> -0.016313251 | F43: 22466.1 | G43: =F43/F42-1 -> 0.018630527
B44: 45432 | C44: 1305.57 | D44: =C44/C43-1 -> 0.016015689 | F44: 22957.1 | G44: =F44/F43-1 -> 0.021855151
B45: 45439 | C45: 1265.72 | D45: =C45/C44-1 -> -0.030523067 | F45: 22530.7 | G45: =F45/F44-1 -> -0.018573775
B46: 45446 | C46: 1422.69 | D46: =C46/C45-1 -> 0.12401637 | F46: 23290.15 | G46: =F46/F45-1 -> 0.033707342
B47: 45453 | C47: 1387.87 | D47: =C47/C46-1 -> -0.024474763 | F47: 23465.6 | G47: =F47/F46-1 -> 0.0075332276
B48: 45460 | C48: 1351.9 | D48: =C48/C47-1 -> -0.025917413 | F48: 23501.1 | G48: =F48/F47-1 -> 0.0015128529
B49: 45467 | C49: 1370.83 | D49: =C49/C48-1 -> 0.014002515 | F49: 24010.6 | G49: =F49/F48-1 -> 0.021679836
... B65: 45579 | C65: 1336.15 | D65: =C65/C64-1 -> 0.015543057 | F65: 24854.05 | G65: =F65/F64-1 -> -0.0044143125

Sheet WACC
B2: ='Data Sheet'!B1 -> GODREJ CONSUMER PRODUCTS LTD
B3: (GODREJCP | BSE Code: 532424)
B5: Weighted Average Cost of Capital- GODREJ CONSUMER PRODUCTS LTD
B7: All figures are in INR unless stated otherwise.
B9: Peer Comps
G10: Debt/ | H10: Debt/ | I10: Levered | J10: Unlevered
B11: Name | C11: Country | D11: Total Debt | E11: Total Equity | F11: Tax Rate 1 | G11: Equity | H11: Capital | I11: Beta 2 | J11: Beta 3
B13: Godrej Consumer | C13: India | D13: 3222.2 | E13: 136678 | F13: 0.3 | G13: =D13/E13 -> 0.023575118 | H13: =D13/(D13+E13) -> 0.023032133 | I13: 0.74 | J13: =I13/(1+(1-F13)*G13) -> 0.72798635
B14: Dabur India | C14: India | D14: 1365.09 | E14: 101269.87 | F14: 0.3 | G14: =D14/E14 -> 0.013479725 | H14: =D14/(D14+E14) -> 0.013300439 | I14: 0.69029221 | J14: =I14/(1+(1-F14)*G14) -> 0.68383963
B15: Emami | C15: India | D15: 93.95 | E15: 30592.1 | F15: 0.3 | G15: =D15/E15 -> 0.0030710543 | H15: =D15/(D15+E15) -> 0.0030616518 | I15: 0.41363446 | J15: =I15/(1+(1-F15)*G15) -> 0.41274716
B16: Jyothy Labs | C16: India | D16: 50.56 | E16: 18804.75 | F16: 0.3 | G16: =D16/E16 -> 0.0026886824 | H16: =D16/(D16+E16) -> 0.0026814728 | I16: 0.58255317 | J16: =I16/(1+(1-F16)*G16) -> 0.58145881
B17: Bajaj Consumer | C17: India | D17: 8.75 | E17: 3269.69 | F17: 0.3 | G17: =D17/E17 -> 0.0026760947 | H17: =D17/(D17+E17) -> 0.0026689523 | I17: 0.47654062 | J17: =I17/(1+(1-F17)*G17) -> 0.4756496
E19: Average | F19: =AVERAGE(F14:F17) -> 0.3 | G19: =AVERAGE(G14:G17) -> 0.0054788891 | H19: =AVERAGE(H14:H17) -> 0.0054281289 | I19: =AVERAGE(I14:I17) -> 0.54075511 | J19: =AVERAGE(J14:J17) -> 0.5384238
E20: Median | F20: =MEDIAN(F14:F17) -> 0.3 | G20: =MEDIAN(G14:G17) -> 0.0028798683 | H20: =MEDIAN(H14:H17) -> 0.0028715623 | I20: =MEDIAN(I14:I17) -> 0.52954689 | J20: =MEDIAN(J14:J17) -> 0.52855421
B23: Cost of Debt | G23: Cost of Equity
B25: Pre-tax Cost of Debt | E25: =310/3222.2 -> 0.09620756 | G25: Risk Free Rate | J25: 0.06946
B26: Tax Rate | E26: =F20 -> 0.3 | G26: Equity Risk Premium | J26: =(0.1677-J25) -> 0.09824
B27: After Tax Cost of Debt | E27: =E25*(1-E26) -> 0.067345292 | G27: Levered Beta 4 | J27: =J36 -> 0.68625505
G28: Cost of Equity | J28: =J25+(J26*J27) -> 0.1368777
B31: Capital Structure | G31: Levered Beta
D33: Current | E33: Target | G33: Comps Median Unlevered Beta | J33: =J20 -> 0.52855421
B34: Total Debt | C34: =D13 -> 3222.2 | D34: =C34/$C$36 -> 0.023032133 | E34: =H19 -> 0.0054281289 | G34: Target Debt/ Equity | J34: =E38 -> 0.0054577543
B35: Market Capitalization | C35: =E13 -> 136678 | D35: =C35/$C$36 -> 0.97696787 | E35: =E36-E34 -> 0.99457187 | G35: Tax Rate | J35: =E26 -> 0.3
B36: Total Capitalization | C36: =SUM(C34:C35) -> 139900.2 | D36: 1 | E36: 1 | G36: Levered Beta | J36: =J33*(1+(1-J34)*J35) -> 0.68625505
B38: Debt / Equity | D38: =D34/D35 -> 0.023575118 | E38: =E34/E35 -> 0.0054577543 | G38: Weighted Average Cost of Capital
B40: 1. Tax Rate considered as Marginal Tax Rate for the country | G40: Cost of Equity | J40: =J28 -> 0.1368777
B41: 2. Levered Beta is based on 5 year monthly data | G41: Equity Weight | J41: =E35 -> 0.99457187
B42: 3. Unlevered Beta = Levered Beta/(1+(1-Tax Rate) x Debt/Equity)
B43: 3. Levered Beta = Unlevered Beta/(1+(1-Tax Rate) x Debt/Equity) | G43: Cost of Debt | J43: =E27 -> 0.067345292
G44: Debt Weight | J44: =E34 -> 0.0054281289
G46: WACC | J46: =(J40*J41)+(J43*J44) -> 0.13650027

Sheet Intrinsic Growth
B2: ='Data Sheet'!B1 -> GODREJ CONSUMER PRODUCTS LTD
B3: (GODREJCP | BSE Code: 532424)
B5: Intrinsic Growth - GODREJ CONSUMER PRODUCTS LTD
B7: Calculation of ROIC | G7: ='Raw FS'!J$1 -> 43891 | H7: ='Raw FS'!K$1 -> 44256 | I7: ='Raw FS'!L$1 -> 44621 | J7: ='Raw FS'!M$1 -> 44986 | K7: ='Raw FS'!N$1 -> 45352
B9: Current Assets
B10: ='Raw FS'!B35 -> Inventories | G10: ='Raw FS'!J35 -> 1703 | H10: ='Raw FS'!K35 -> 1716 | I10: ='Raw FS'!L35 -> 2130 | J10: ='Raw FS'!M35 -> 1537 | K10: ='Raw FS'!N35 -> 1271
B11: ='Raw FS'!B36 -> Trade receivables | G11: ='Raw FS'!J36 -> 1157 | H11: ='Raw FS'!K36 -> 1004 | I11: ='Raw FS'!L36 -> 1116 | J11: ='Raw FS'!M36 -> 1245 | K11: ='Raw FS'!N36 -> 1535
B12: ='Raw FS'!B39 -> Other asset items | G12: ='Raw FS'!J39 -> 1289 | H12: ='Raw FS'!K39 -> 1209 | I12: ='Raw FS'!L39 -> 1377 | J12: ='Raw FS'!M39 -> 1256 | K12: ='Raw FS'!N39 -> 1012
B13: Total Current Assets | G13: =SUM(G10:G12) -> 4149 | H13: =SUM(H10:H12) -> 3929 | I13: =SUM(I10:I12) -> 4623 | J13: =SUM(J10:J12) -> 4038 | K13: =SUM(K10:K12) -> 3818
B15: Current Liabilities
B16: ='Raw FS'!B11 -> Trade Payables | G16: ='Raw FS'!J11 -> 2480 | H16: ='Raw FS'!K11 -> 2012 | I16: ='Raw FS'!L11 -> 2163 | J16: ='Raw FS'!M11 -> 1823 | K16: ='Raw FS'!N11 -> 1675
B17: ='Raw FS'!B12 -> Advance from Customers | G17: ='Raw FS'!J12 -> 25 | H17: ='Raw FS'!K12 -> 27 | I17: ='Raw FS'!L12 -> 30 | J17: ='Raw FS'!M12 -> 38 | K17: ='Raw FS'!N12 -> 30
B18: ='Raw FS'!B13 -> Other liability items | G18: ='Raw FS'!J13 -> 901 | H18: ='Raw FS'!K13 -> 901 | I18: ='Raw FS'!L13 -> 629 | J18: ='Raw FS'!M13 -> 652 | K18: ='Raw FS'!N13 -> 865
B19: Total Current Liabilities | G19: =SUM(G16:G18) -> 3406 | H19: =SUM(H16:H18) -> 2940 | I19: =SUM(I16:I18) -> 2822 | J19: =SUM(J16:J18) -> 2513 | K19: =SUM(K16:K18) -> 2570
B21: Net Working Capital | G21: =G13-G19 -> 743 | H21: =H13-H19 -> 989 | I21: =I13-I19 -> 1801 | J21: =J13-J19 -> 1525 | K21: =K13-K19 -> 1248
B23: Non Current Assets
B24: ='Raw FS'!B17 -> Land | G24: ='Raw FS'!J17 -> 146 | H24: ='Raw FS'!K17 -> 144 | I24: ='Raw FS'!L17 -> 147 | J24: ='Raw FS'!M17 -> 145 | K24: ='Raw FS'!N17 -> 157
B25: ='Raw FS'!B18 -> Building | G25: ='Raw FS'!J18 -> 699 | H25: ='Raw FS'!K18 -> 757 | I25: ='Raw FS'!L18 -> 812 | J25: ='Raw FS'!M18 -> 854 | K25: ='Raw FS'!N18 -> 791
B26: ='Raw FS'!B19 -> Plant Machinery | G26: ='Raw FS'!J19 -> 713 | H26: ='Raw FS'!K19 -> 809 | I26: ='Raw FS'!L19 -> 942 | J26: ='Raw FS'!M19 -> 1178 | K26: ='Raw FS'!N19 -> 1186
B27: ='Raw FS'!B20 -> Ships Vessels | G27: ='Raw FS'!J20 -> 0 | H27: ='Raw FS'!K20 -> 1 | I27: ='Raw FS'!L20 -> 2 | J27: ='Raw FS'!M20 -> 12 | K27: ='Raw FS'!N20 -> 17
B28: ='Raw FS'!B21 -> Equipments | G28: ='Raw FS'!J21 -> 33 | H28: ='Raw FS'!K21 -> 36 | I28: ='Raw FS'!L21 -> 41 | J28: ='Raw FS'!M21 -> 51 | K28: ='Raw FS'!N21 -> 47
B29: ='Raw FS'!B22 -> Computers | G29: ='Raw FS'!J22 -> 59 | H29: ='Raw FS'!K22 -> 64 | I29: ='Raw FS'!L22 -> 75 | J29: ='Raw FS'!M22 -> 78 | K29: ='Raw FS'!N22 -> 67
B30: ='Raw FS'!B23 -> Furniture n fittings | G30: ='Raw FS'!J23 -> 35 | H30: ='Raw FS'!K23 -> 37 | I30: ='Raw FS'!L23 -> 36 | J30: ='Raw FS'!M23 -> 35 | K30: ='Raw FS'!N23 -> 30
B31: ='Raw FS'!B24 -> Vehicles | G31: ='Raw FS'!J24 -> 44 | H31: ='Raw FS'!K24 -> 60 | I31: ='Raw FS'!L24 -> 65 | J31: ='Raw FS'!M24 -> 63 | K31: ='Raw FS'!N24 -> 31
B32: ='Raw FS'!B25 -> Intangible Assets | G32: ='Raw FS'!J25 -> 8036 | H32: ='Raw FS'!K25 -> 7753 | I32: ='Raw FS'!L25 -> 8083 | J32: ='Raw FS'!M25 -> 8687 | K32: ='Raw FS'!N25 -> 10696
B33: ='Raw FS'!B26 -> Other fixed assets | G33: ='Raw FS'!J26 -> 126 | H33: ='Raw FS'!K26 -> 130 | I33: ='Raw FS'!L26 -> 144 | J33: ='Raw FS'!M26 -> 145 | K33: ='Raw FS'!N26 -> 151
B35: Gross Block | G35: =SUM(G24:G34) -> 9891 | H35: =SUM(H24:H34) -> 9791 | I35: =SUM(I24:I34) -> 10347 | J35: =SUM(J24:J34) -> 11248 | K35: =SUM(K24:K34) -> 13173
B36: Accumulated Depreciation | G36: =-'Raw FS'!J28 -> -661 | H36: =-'Raw FS'!K28 -> -886 | I36: =-'Raw FS'!L28 -> -1127 | J36: =-'Raw FS'!M28 -> -1315 | K36: =-'Raw FS'!N28 -> -2732
B37: Net Non Current Assets | G37: =SUM(G35:G36) -> 9230 | H37: =SUM(H35:H36) -> 8905 | I37: =SUM(I35:I36) -> 9220 | J37: =SUM(J35:J36) -> 9933 | K37: =SUM(K35:K36) -> 10441
B39: Invested Capital | G39: =G37+G21 -> 9973 | H39: =H37+H21 -> 9894 | I39: =I37+I21 -> 11021 | J39: =J37+J21 -> 11458 | K39: =K37+K21 -> 11689
B40: EBIT | G40: =HistoricalFS!H30+HistoricalFS!H24 -> 1956.47 | H40: =HistoricalFS!I30+HistoricalFS!I24 -> 2195.41 | I40: =HistoricalFS!J30+HistoricalFS!J24 -> 2199.25 | J40: =HistoricalFS!K30+HistoricalFS!K24 -> 2206.91 | K40: =HistoricalFS!L30+HistoricalFS!L24 -> 2716.36
B42: ROIC | G42: =G40/G39 -> 0.19617668 | H42: =H40/H39 -> 0.22189307 | I42: =I40/I39 -> 0.19955086 | J42: =J40/J39 -> 0.19260866 | K42: =K40/K39 -> 0.232386
B44: Calculation of Reinvestment Rate | G44: =G7 -> 43891 | H44: =H7 -> 44256 | I44: =I7 -> 44621 | J44: =J7 -> 44986 | K44: =K7 -> 45352
B46: Net Capex | G46: =SUM('Raw FS'!J56:J57) -> -152 | H46: =SUM('Raw FS'!K56:K57) -> -164 | I46: =SUM('Raw FS'!L56:L57) -> 3 | J46: =SUM('Raw FS'!M56:M57) -> 8 | K46: =SUM('Raw FS'!N56:N57) -> 31
B47: Change in Working Capital | H47: =H21-G21 -> 246 | I47: =I21-H21 -> 812 | J47: =J21-I21 -> -276 | K47: =K21-J21 -> -277
B49: EBIT | G49: =G40 -> 1956.47 | H49: =H40 -> 2195.41 | I49: =I40 -> 2199.25 | J49: =J40 -> 2206.91 | K49: =K40 -> 2716.36
B50: Marginal Tax Rate | G50: 0.3 | H50: 0.3 | I50: 0.3 | J50: 0.3 | K50: 0.3
B51: EBIT(1-T) | G51: =G49*(1-G50) -> 1369.529 | H51: =H49*(1-H50) -> 1536.787 | I51: =I49*(1-I50) -> 1539.475 | J51: =J49*(1-J50) -> 1544.837 | K51: =K49*(1-K50) -> 1901.452
B53: Reinvestment | H53: =SUM(H46:H47) -> 82 | I53: =SUM(I46:I47) -> 815 | J53: =SUM(J46:J47) -> -268 | K53: =SUM(K46:K47) -> -246
B55: Reinvestment Rate | H55: =H53/H51 -> 0.053358078 | I55: =I53/I51 -> 0.52940126 | J55: =J53/J51 -> -0.17348109 | K55: =K53/K51 -> -0.12937481
I57: 4 Year Average | K57: =AVERAGE(H55:K55) -> 0.069975859
I58: 4 Year Median | K58: =MEDIAN(H55:K55) -> -0.038008369
B60: Calculation of Growth Rate | G60: =G44 -> 43891 | H60: =H44 -> 44256 | I60: =I44 -> 44621 | J60: =J44 -> 44986 | K60: =K44 -> 45352
B62: Reinvestment Rate | H62: =H55 -> 0.053358078 | I62: =I55 -> 0.52940126 | J62: =J55 -> -0.17348109 | K62: =K55 -> -0.12937481
B63: ROIC | H63: =H42 -> 0.22189307 | I63: =I42 -> 0.19955086 | J63: =J42 -> 0.19260866 | K63: =K42 -> 0.232386
B65: Intrinsic Growth | H65: =H62*H63 -> 0.011839787 | I65: =I62*I63 -> 0.10564247 | J65: =J62*J63 -> -0.033413959 | K65: =K62*K63 -> -0.030064896
I67: 4 Year Average | K67: =AVERAGE(H65:K65) -> 0.013500852
I68: 4 Year Median | K68: =MEDIAN(H65:K65) -> -0.0091125544

Sheet DCF
B2: ='Data Sheet'!B1 -> GODREJ CONSUMER PRODUCTS LTD
B3: (GODREJCP | BSE Code: 532424)
B5: Discounted Cash Flow - GODREJ CONSUMER PRODUCTS LTD
F6: 0 | G6: 0.5 | H6: 1.5 | I6: 2.5 | J6: 3.5 | K6: 4.5
B7: Calculation of PV of FCFF | F7: ='Data Sheet'!K16 -> 45382 | G7: =F7+365 -> 45747 | H7: =G7+365 -> 46112 | I7: =H7+365 -> 46477 | J7: =I7+365 -> 46842 | K7: =J7+365 -> 47207
B9: EBIT | F9: =SUM(HistoricalFS!L30+HistoricalFS!L24) -> 2716.36 | G9: =F9*(1+$E$23) -> 2849.7333 | H9: =G9*(1+$E$23) -> 2989.6552 | I9: =H9*(1+$E$23) -> 3136.4472 | J9: =I9*(1+$E$23) -> 3290.4468 | K9: =J9*(1+$E$23) -> 3452.0077
B11: Tax Rate | F11: 0.3 | G11: =F11 -> 0.3 | H11: =G11 -> 0.3 | I11: =H11 -> 0.3 | J11: =I11 -> 0.3 | K11: =J11 -> 0.3
B13: EBIT (1-T) | F13: =F9*(1-F11) -> 1901.452 | G13: =G9*(1-G11) -> 1994.8133 | H13: =H9*(1-H11) -> 2092.7586 | I13: =I9*(1-I11) -> 2195.5131 | J13: =J9*(1-J11) -> 2303.3128 | K13: =K9*(1-K11) -> 2416.4054
B15: Less: Reinvestment Rate | F15: 0.5415 | G15: =F15 -> 0.5415 | H15: =G15 -> 0.5415 | I15: =H15 -> 0.5415 | J15: =I15 -> 0.5415 | K15: =J15 -> 0.5415
B17: Free Cash Flow to Firm | F17: =F13*(1-F15) -> 871.81574 | G17: =G13*(1-G15) -> 914.62189 | H17: =H13*(1-H15) -> 959.52983 | I17: =I13*(1-I15) -> 1006.6427 | J17: =J13*(1-J15) -> 1056.0689 | K17: =K13*(1-K15) -> 1107.9219
B19: Discounting Factor | F19: =1/(1+$E$30)^F6 -> 1 | G19: =1/(1+$E$30)^G6 -> 0.93802676 | H19: =1/(1+$E$30)^H6 -> 0.82536431 | I19: =1/(1+$E$30)^I6 -> 0.72623328 | J19: =1/(1+$E$30)^J6 -> 0.63900846 | K19: =1/(1+$E$30)^K6 -> 0.56225984
B21: PV of FCFF | F21: =F19*F17 -> 871.81574 | G21: =G19*G17 -> 857.93981 | H21: =H19*H17 -> 791.96168 | I21: =I19*I17 -> 731.05746 | J21: =J19*J17 -> 674.83696 | K21: =K19*K17 -> 622.93998
B23: Expected Growth | E23: 0.0491
B24: Terminal Growth | E24: 0.055
B27: Calculation of Terminal Value | G27: Sensitivity Analysis
G28: =E46 -> 88.85678 | H28: 0.18 | I28: 0.2004 | J28: 0.22 | K28: 0.24
B29: FCFF (n+1) | E29: =K17*(1+E23) -> 1162.3209 | G29: 0.03 | I29: 250.51413 | J29: 222.06243 | K29: 198.73198
B30: WACC | E30: =WACC!J46 -> 0.13650027 | G30: 0.04 | H30: 301.2508 | I30: 259.6659 | J30: 228.86229 | K30: 203.87832
B31: Terminal Growth Rate | E31: =E24 -> 0.055 | G31: 0.0538 | H31: 322.35498 | I31: 274.34568 | J31: 239.58988 | K31: 211.88805
G32: 0.06 | H32: 333.41683 | I32: 281.88044 | J32: 245.01198 | K32: 215.88646
B33: Terminal Value | E33: =E29/(E30-E31) -> 14261.559 | G33: 0.07 | H33: 353.88613 | I33: 295.54306 | J33: 254.70179 | K33: 222.95007
B36: Calculation of Enterprise Value
B38: PV of FCFF | E38: =SUM(G21:K21) -> 3678.7359
B39: PV of Terminal Value | E39: =E33*K19 -> 8018.7019
B40: Value of Operating Asset | E40: =SUM(E38:E39) -> 11697.438
B42: Add: Cash | E42: ='Data Sheet'!K69 -> 546.94
B43: Less: Debt | E43: =SUM('Raw FS'!N5:N6) -> 3155
B44: Value of Equity | E44: =E40+E42-E43 -> 9089.3778
B45: No. of Shares | E45: ='Data Sheet'!B6 -> 102.29245
B46: Value per Share | E46: =E44/E45 -> 88.85678

Sheet Comparable Pricing
B2: ='Data Sheet'!B1 -> GODREJ CONSUMER PRODUCTS LTD
B3: (GODREJCP | BSE Code: 532424)
B5: Comparable Company Valuation - GODREJ CONSUMER PRODUCTS LTD
D7: Market Data | K7: Financials | O7: Valuation
B8: Company | C8: Ticker | D8: Share Price | E8: Shares Outstanding | F8: Equity Value | G8: Net Debt | H8: Enterprise Value | K8: Revenue | L8: EBITDA | M8: Net Income | O8: EV/Revenue | P8: EV/EBITDA | Q8: P/E
B9: ='Relative Data'!C3 -> Godrej Consumer | D9: ='Relative Data'!D3 -> 1181.1 | E9: ='Relative Data'!E3 -> 102.3 | F9: =E9*D9 -> 120826.53 | G9: ='Relative Data'!G3-'Relative Data'!H3 -> 3281.53 | H9: =+F9+G9 -> 124108.06 | K9: ='Relative Data'!J3 -> 14043.16 | L9: ='Relative Data'!K3 -> 3371.5854 | M9: ='Relative Data'!L3 -> -370.15 | O9: =$H9/K9 -> 8.8376163 | P9: =$H9/L9 -> 36.81 | Q9: =F9/M9 -> -326.42585
B10: ='Relative Data'!C4 -> Dabur India | D10: ='Relative Data'!D4 -> 521.15 | E10: ='Relative Data'!E4 -> 177.23 | F10: =E10*D10 -> 92363.414 | G10: ='Relative Data'!G4-'Relative Data'!H4 -> 1085.26 | H10: =+F10+G10 -> 93448.674 | K10: ='Relative Data'!J4 -> 12447.4 | L10: ='Relative Data'!K4 -> 2878.8871 | M10: ='Relative Data'!L4 -> 1759.53 | O10: =$H10/K10 -> 7.5074855 | P10: =$H10/L10 -> 32.46 | Q10: =F10/M10 -> 52.493231
B11: ='Relative Data'!C5 -> Emami | D11: ='Relative Data'!D5 -> 595.75 | E11: ='Relative Data'!E5 -> 43.65 | F11: =E11*D11 -> 26004.487 | G11: ='Relative Data'!G5-'Relative Data'!H5 -> -126.99 | H11: =+F11+G11 -> 25877.497 | K11: ='Relative Data'!J5 -> 3684.22 | L11: ='Relative Data'!K5 -> 1045.1332 | M11: ='Relative Data'!L5 -> 768.99 | O11: =$H11/K11 -> 7.0238741 | P11: =$H11/L11 -> 24.76 | Q11: =F11/M11 -> 33.816418
B12: ='Relative Data'!C6 -> Jyothy Labs | D12: ='Relative Data'!D6 -> 408.1 | E12: ='Relative Data'!E6 -> 36.72 | F12: =E12*D12 -> 14985.432 | G12: ='Relative Data'!G6-'Relative Data'!H6 -> -110.18 | H12: =+F12+G12 -> 14875.252 | K12: ='Relative Data'!J6 -> 2813.06 | L12: ='Relative Data'!K6 -> 547.48811 | M12: ='Relative Data'!L6 -> 375.78 | O12: =$H12/K12 -> 5.2879256 | P12: =$H12/L12 -> 27.17 | Q12: =F12/M12 -> 39.878205
B13: ='Relative Data'!C7 -> Bajaj Consumer | D13: ='Relative Data'!D7 -> 195.24 | E13: ='Relative Data'!E7 -> 14.28 | F13: =E13*D13 -> 2788.0272 | G13: ='Relative Data'!G7-'Relative Data'!H7 -> -37.96 | H13: =+F13+G13 -> 2750.0672 | K13: ='Relative Data'!J7 -> 959.03 | L13: ='Relative Data'!K7 -> 182.00312 | M13: ='Relative Data'!L7 -> 140.9 | O13: =$H13/K13 -> 2.8675508 | P13: =$H13/L13 -> 15.11 | Q13: =F13/M13 -> 19.787276
B15: High | O15: =MAX(O9:O13) -> 8.8376163 | P15: =MAX(P9:P13) -> 36.81 | Q15: =MAX(Q9:Q13) -> 52.493231
B16: 75th Percentile | O16: =QUARTILE(O9:O13,3) -> 7.5074855 | P16: =QUARTILE(P9:P13,3) -> 32.46 | Q16: =QUARTILE(Q9:Q13,3) -> 39.878205
B17: Average | O17: =AVERAGE(O9:O13) -> 6.3048905 | P17: =AVERAGE(P9:P13) -> 27.262 | Q17: =AVERAGE(Q9:Q13) -> -36.090145
B18: Median | O18: =MEDIAN(O9:O13) -> 7.0238741 | P18: =MEDIAN(P9:P13) -> 27.17 | Q18: =MEDIAN(Q9:Q13) -> 33.816418
B19: 25th Percentile | O19: =QUARTILE(O9:O13,1) -> 5.2879256 | P19: =QUARTILE(P9:P13,1) -> 24.76 | Q19: =QUARTILE(Q9:Q13,1) -> 19.787276
B20: Low | O20: =MIN(O9:O13) -> 2.8675508 | P20: =MIN(P9:P13) -> 15.11 | Q20: =MIN(Q9:Q13) -> -326.42585
B22: Cipla Comparable Valuation | O22: EV/Revenue | P22: EV/EBITDA | Q22: P/E
B24: Implied Enterprise Value | O24: =O18*K9 -> 98637.388 | P24: =P18*L9 -> 91605.976 | Q24: =+Q26+Q25 -> -9235.6172
B25: Net Debt | O25: =$G$9 -> 3281.53 | P25: =$G$9 -> 3281.53 | Q25: =$G$9 -> 3281.53
B26: Implied Market Value | O26: =O24-O25 -> 95355.858 | P26: =P24-P25 -> 88324.446 | Q26: =Q18*M9 -> -12517.147
B27: Shares Outstanding | O27: =$E$9 -> 102.3 | P27: =$E$9 -> 102.3 | Q27: =$E$9 -> 102.3
B29: Implied Value per Share | O29: =O26/O27 -> 932.11982 | P29: =P26/P27 -> 863.38657 | Q29: =Q26/Q27 -> -122.35726
O32: =IF(O29>$D$11,"Undervalued","Overvalued") -> Undervalued | P32: =IF(P29>$D$11,"Undervalued","Overvalued") -> Undervalued | Q32: =IF(Q29>$D$11,"Undervalued","Overvalued") -> Overvalued

Sheet VAR
B2: ='Data Sheet'!B1 -> GODREJ CONSUMER PRODUCTS LTD
B3: (GODREJCP | BSE Code: 532424)
B5: Value at Risk - GODREJ CONSUMER PRODUCTS LTD
B7: Date | C7: Adj Close | D7: Return | E7: Sorted Returns | G7: Replication | H7: Simulated Returns | J7: Calculation of Value at Risk - Godrej Consumer (Simulation)
B8: Feb 1, 2024 | C8: 1240.39 | D8: =LN(C8/C9) -> -0.13673693 | E8: 0.074586224 | G8: 1 | H8: =_xlfn.NORM.INV(RAND(),$N$10,$N$11) -> -0.015827581
B9: Jun 5, 2024 | C9: 1422.14 | D9: =LN(C9/C10) -> 0.49625257 | E9: 0.056862301 | G9: 2 | H9: =_xlfn.NORM.INV(RAND(),$N$10,$N$11) -> -0.024704192 | J9: Historical Approach
B10: Jul 6, 2022 | C10: 865.81 | D10: =LN(C10/C11) -> -0.41211493 | E10: 0.055801205 | G10: 3 | H10: =_xlfn.NORM.INV(RAND(),$N$10,$N$11) -> 0.011812736 | J10: Mean | N10: =AVERAGE(E8:E725) -> 0.00018710917
B11: May 7, 2024 | C11: 1307.38 | D11: =LN(C11/C12) -> 0.63779979 | E11: 0.055433055 | G11: 4 | H11: =_xlfn.NORM.INV(RAND(),$N$10,$N$11) -> -0.027670075 | J11: Std Deviation | N11: =_xlfn.STDEV.S(E8:E725) -> 0.016905252
B12: Mar 8, 2022 | C12: 690.89 | D12: =LN(C12/C13) -> -0.036579047 | E12: 0.055194423 | G12: 5 | H12: =_xlfn.NORM.INV(RAND(),$N$10,$N$11) -> 0.013460536 | J12: Max | N12: =MAX(E8:E725) -> 0.074586224
B13: Mar 30, 2022 | C13: 716.63 | D13: =LN(C13/C14) -> -0.041679531 | E13: 0.04623632 | G13: 6 | H13: =_xlfn.NORM.INV(RAND(),$N$10,$N$11) -> 0.02392579 | J13: Min | N13: =MIN(E8:E725) -> -0.091199185
B14: Jun 20, 2022 | C14: 747.13 | D14: =LN(C14/C15) -> -0.41977736 | E14: 0.045468288 | G14: 7 | H14: =_xlfn.NORM.INV(RAND(),$N$10,$N$11) -> 0.0087005515 | J14: CMP | N14: 1071.9
B15: Jan 19, 2024 | C15: 1136.85 | D15: =LN(C15/C16) -> 0.37546702 | E15: 0.044241874 | G15: 8 | H15: =_xlfn.NORM.INV(RAND(),$N$10,$N$11) -> 0.005499654
B16: Apr 26, 2022 | C16: 780.98 | D16: =LN(C16/C17) -> -0.023224335 | E16: 0.041023151 | G16: 9 | H16: =_xlfn.NORM.INV(RAND(),$N$10,$N$11) -> 0.021568026 | J16: Percentile | K16: Confidence | L16: VaR | M16: Share Price | N16: VaR(INR)
B17: Jul 4, 2022 | C17: 799.33 | D17: =LN(C17/C18) -> -0.15195895 | E17: 0.040374845 | G17: 10 | H17: =_xlfn.NORM.INV(RAND(),$N$10,$N$11) -> -0.0048305363 | J17: 0.05 | K17: =100%-J17 -> 0.95 | L17: =_xlfn.PERCENTILE.INC($E$8:$E$725,J17) -> -0.025934726 | M17: =$N$14*(1-L17) -> 1099.6994 | N17: =$N$14-M17 -> -27.799433
B18: Sep 7, 2022 | C18: 930.51 | D18: =LN(C18/C19) -> 0.055560947 | E18: 0.038708008 | G18: 11 | H18: =_xlfn.NORM.INV(RAND(),$N$10,$N$11) -> -0.0019924893 | J18: 0.01 | K18: =100%-J18 -> 0.99 | L18: =_xlfn.PERCENTILE.INC($E$8:$E$725,J18) -> -0.041246416 | M18: =$N$14*(1-L18) -> 1116.112 | N18: =$N$14-M18 -> -44.212033
B19: Jan 25, 2022 | C19: 880.22 | D19: =LN(C19/C20) -> 0.097011201 | E19: 0.038577445 | G19: 12 | H19: =_xlfn.NORM.INV(RAND(),$N$10,$N$11) -> -0.016322225 | J19: 0.005 | K19: =100%-J19 -> 0.995 | L19: =_xlfn.PERCENTILE.INC($E$8:$E$725,J19) -> -0.047936594 | M19: =$N$14*(1-L19) -> 1123.2832 | N19: =$N$14-M19 -> -51.383235
B20: Apr 8, 2022 | C20: 798.84 | D20: =LN(C20/C21) -> 0.037978683 | E20: 0.037978683 | G20: 13 | H20: =_xlfn.NORM.INV(RAND(),$N$10,$N$11) -> 0.024830097 | J20: 0.1 | K20: =100%-J20 -> 0.9 | L20: =_xlfn.PERCENTILE.INC($E$8:$E$725,J20) -> -0.019605463 | M20: =$N$14*(1-L20) -> 1092.9151 | N20: =$N$14-M20 -> -21.015096
B21: Apr 7, 2022 | C21: 769.07 | D21: =LN(C21/C22) -> -0.6136526 | E21: 0.037545806 | G21: 14 | H21: =_xlfn.NORM.INV(RAND(),$N$10,$N$11) -> 0.00046214129
B22: Jul 8, 2024 | C22: 1420.6 | D22: =LN(C22/C23) -> -0.053485385 | E22: 0.036859993 | G22: 15 | H22: =_xlfn.NORM.INV(RAND(),$N$10,$N$11) -> 0.014290203 | J22: Monte Carlo Simulation
B23: Sep 9, 2024 | C23: 1498.65 | D23: =LN(C23/C24) -> 0.03978271 | E23: 0.036489984 | G23: 16 | H23: =_xlfn.NORM.INV(RAND(),$N$10,$N$11) -> 0.0063236704 | J23: Mean | N23: =AVERAGE(H8:H3007) -> -9.3632241e-05
B24: Aug 22, 2024 | C24: 1440.2 | D24: =LN(C24/C25) -> 0.60783493 | E24: 0.034435624 | G24: 17 | H24: =_xlfn.NORM.INV(RAND(),$N$10,$N$11) -> 0.042564993 | J24: Std Deviation | N24: =_xlfn.STDEV.S(H8:H3007) -> 0.016870076
B25: May 13, 2022 | C25: 784.23 | D25: =LN(C25/C26) -> 0.02233289 | E25: 0.033755142 | G25: 18 | H25: =_xlfn.NORM.INV(RAND(),$N$10,$N$11) -> -0.018208252 | J25: Max | N25: =MAX(H8:H3007) -> 0.060821472
B26: May 26, 2022 | C26: 766.91 | D26: =LN(C26/C27) -> -0.67942077 | E26: 0.032804601 | G26: 19 | H26: =_xlfn.NORM.INV(RAND(),$N$10,$N$11) -> -0.0092656962 | J26: Min | N26: =MIN(H8:H3007) -> -0.060851789
B27: Jul 23, 2024 | C27: 1512.91 | D27: =LN(C27/C28) -> 0.51638888 | E27: 0.031947651 | G27: 20 | H27: =_xlfn.NORM.INV(RAND(),$N$10,$N$11) -> 0.020620879 | J27: CMP | N27: 1071.9
B28: Jan 5, 2023 | C28: 902.71 | D28: =LN(C28/C29) -> 0.13662687 | E28: 0.031897723 | G28: 21 | H28: =_xlfn.NORM.INV(RAND(),$N$10,$N$11) -> 0.014180544
B29: Apr 20, 2022 | C29: 787.43 | D29: =LN(C29/C30) -> -0.054589103 | E29: 0.031870376 | G29: 22 | H29: =_xlfn.NORM.INV(RAND(),$N$10,$N$11) -> -0.017374039 | J29: Percentile | K29: Confidence | L29: VaR | M29: Share Price | N29: VaR(INR)
B30: Nov 14, 2022 | C30: 831.61 | D30: =LN(C30/C31) -> -0.23675642 | E30: 0.031552829 | G30: 23 | H30: =_xlfn.NORM.INV(RAND(),$N$10,$N$11) -> 0.0040135778 | J30: 0.05 | K30: =100%-J30 -> 0.95 | L30: =_xlfn.PERCENTILE.INC($H$8:$H$3007,J30) -> -0.027519598 | M30: =$N$14*(1-L30) -> 1101.3983 | N30: =$N$14-M30 -> -29.498257
B31: Jun 28, 2023 | C31: 1053.76 | D31: =LN(C31/C32) -> 0.15406528 | E31: 0.031405899 | G31: 24 | H31: =_xlfn.NORM.INV(RAND(),$N$10,$N$11) -> -0.037595336 | J31: 0.01 | K31: =100%-J31 -> 0.99 | L31: =_xlfn.PERCENTILE.INC($H$8:$H$3007,J31) -> -0.038763007 | M31: =$N$14*(1-L31) -> 1113.4501 | N31: =$N$14-M31 -> -41.550067
B32: Aug 18, 2022 | C32: 903.3 | D32: =LN(C32/C33) -> -0.39700103 | E32: 0.031259572 | G32: 25 | H32: =_xlfn.NORM.INV(RAND(),$N$10,$N$11) -> 0.0087840727 | J32: 0.005 | K32: =100%-J32 -> 0.995 | L32: =_xlfn.PERCENTILE.INC($H$8:$H$3007,J32) -> -0.0427948 | M32: =$N$14*(1-L32) -> 1117.7717 | N32: =$N$14-M32 -> -45.871747
B33: Jun 4, 2024 | C33: 1343.53 | D33: =LN(C33/C34) -> 0.086393792 | E33: 0.031222299 | G33: 26 | H33: =_xlfn.NORM.INV(RAND(),$N$10,$N$11) -> 0.0047714868 | J33: 0.1 | K33: =100%-J33 -> 0.9 | L33: =_xlfn.PERCENTILE.INC($H$8:$H$3007,J33) -> -0.021343589 | M33: =$N$14*(1-L33) -> 1094.7782 | N33: =$N$14-M33 -> -22.878193
B34: Apr 8, 2024 | C34: 1232.33 | D34: =LN(C34/C35) -> 0.51729499 | E34: 0.029982561 | G34: 27 | H34: =_xlfn.NORM.INV(RAND(),$N$10,$N$11) -> 0.006961629
B35: Mar 16, 2022 | C35: 734.63 | D35: =LN(C35/C36) -> -0.044032061 | E35: 0.029703239 | G35: 28 | H35: =_xlfn.NORM.INV(RAND(),$N$10,$N$11) -> 0.018410673
B36: Jul 1, 2022 | C36: 767.7 | D36: =LN(C36/C37) -> -0.46439492 | E36: 0.029665881 | G36: 29 | H36: =_xlfn.NORM.INV(RAND(),$N$10,$N$11) -> -0.0050845771
B37: Mar 27, 2024 | C37: 1221.45 | D37: =LN(C37/C38) -> -0.14340208 | E37: 0.029368064 | G37: 30 | H37: =_xlfn.NORM.INV(RAND(),$N$10,$N$11) -> -0.012671315
B38: Jun 26, 2024 | C38: 1409.79 | D38: =LN(C38/C39) -> 0.47572721 | E38: 0.029367515 | G38: 31 | H38: =_xlfn.NORM.INV(RAND(),$N$10,$N$11) -> 0.031171573
B39: Aug 16, 2022 | C39: 876.09 | D39: =LN(C39/C40) -> -0.39636463 | E39: 0.029174213 | G39: 32 | H39: =_xlfn.NORM.INV(RAND(),$N$10,$N$11) -> -0.017605661
B40: Jun 3, 2024 | C40: 1302.23 | D40: =LN(C40/C41) -> 0.008506161 | E40: 0.028990247 | G40: 33 | H40: =_xlfn.NORM.INV(RAND(),$N$10,$N$11) -> 0.028901941
B41: Oct 25, 2024 | C41: 1291.2 | D41: =LN(C41/C42) -> 0.11589704 | E41: 0.028834932 | G41: 34 | H41: =_xlfn.NORM.INV(RAND(),$N$10,$N$11) -> -0.019548558
B42: Jan 24, 2024 | C42: 1149.9 | D42: =LN(C42/C43) -> 0.13537424 | E42: 0.028742021 | G42: 35 | H42: =_xlfn.NORM.INV(RAND(),$N$10,$N$11) -> 0.011465353
B43: Nov 3, 2023 | C43: 1004.31 | D43: =LN(C43/C44) -> 0.21915375 | E43: 0.028675402 | G43: 36 | H43: =_xlfn.NORM.INV(RAND(),$N$10,$N$11) -> -0.0092020719
B44: May 17, 2022 | C44: 806.66 | D44: =LN(C44/C45) -> -0.12903365 | E44: 0.02839121 | G44: 37 | H44: =_xlfn.NORM.INV(RAND(),$N$10,$N$11) -> 0.023288315
B45: Mar 16, 2023 | C45: 917.76 | D45: =LN(C45/C46) -> -0.2586544 | E45: 0.027943019 | G45: 38 | H45: =_xlfn.NORM.INV(RAND(),$N$10,$N$11) -> 0.019492445
... B725: Dec 9, 2024 | C725: 1127.9 | D725: =LN(C725/C726) -> #DIV/0! | E725: -0.091199185 | G725: 718 | H725: =_xlfn.NORM.INV(RAND(),$N$10,$N$11) -> 0.0083197577
G726: 719 | H726: =_xlfn.NORM.INV(RAND(),$N$10,$N$11) -> -0.012785168
G727: 720 | H727: =_xlfn.NORM.INV(RAND(),$N$10,$N$11) -> -0.022428425
G728: 721 | H728: =_xlfn.NORM.INV(RAND(),$N$10,$N$11) -> 0.010280123
G729: 722 | H729: =_xlfn.NORM.INV(RAND(),$N$10,$N$11) -> -0.013431687
G730: 723 | H730: =_xlfn.NORM.INV(RAND(),$N$10,$N$11) -> -0.0025274498
G731: 724 | H731: =_xlfn.NORM.INV(RAND(),$N$10,$N$11) -> 0.0014223439
G732: 725 | H732: =_xlfn.NORM.INV(RAND(),$N$10,$N$11) -> -0.011787669
G733: 726 | H733: =_xlfn.NORM.INV(RAND(),$N$10,$N$11) -> 0.0063198281
G734: 727 | H734: =_xlfn.NORM.INV(RAND(),$N$10,$N$11) -> -0.051032533
G735: 728 | H735: =_xlfn.NORM.INV(RAND(),$N$10,$N$11) -> 0.017000066
G736: 729 | H736: =_xlfn.NORM.INV(RAND(),$N$10,$N$11) -> 0.028297527
G737: 730 | H737: =_xlfn.NORM.INV(RAND(),$N$10,$N$11) -> 0.0019849414
... G3007: 3000 | H3007: =_xlfn.NORM.INV(RAND(),$N$10,$N$11) -> 0.037580966

Sheet Dupont Analysis
B3: ='Data Sheet'!B1 -> GODREJ CONSUMER PRODUCTS LTD
B4: =CONCATENATE(" ","(",VLOOKUP(B3,'[3]List of Stocks'!A2:C5442,3,1)," | ","BSE Code: ",VLOOKUP(B3,'[3]List of Stocks'!A2:B5442,2,1),")") -> (GODREJCP | BSE Code: 532424)
B5: =CONCATENATE(" ","INR "&'Data Sheet'!B8) -> INR 1343.75
B6: 52 Week (High - INR 1542 & Low - 1055)
B8: About the company
B9: Godrej Consumer Products Limited (GCPL) is an Indian Multinational consumer goods company based in Mumbai, India. GCPL's products include soap, hair colorants, toiletries, and liquid detergents. Its brands include 'Cinthol', 'Godrej Fair Glow', 'Godrej No.1' and 'Godrej Shikakai' in soaps, 'Godrej Powder Hair Dye', 'Renew', 'ColourSoft' in hair colourants and 'Ezee' iquid detergent. GCPL operates several manufacturing facilities in India spread over seven locations and grouped into four operating clusters at Malanpur (Madhya Pradesh), Guwahati (Assam), Baddi- Thana (Himachal Pradesh), Baddi- Katha (Himachal Pradesh), Pondicherry, Chennai and Sikkim.
B14: Financial Summary
B60: Return on Equity (ROE)
C61: ='Data Sheet'!E16 -> 43190 | D61: ='Data Sheet'!F16 -> 43555 | E61: ='Data Sheet'!G16 -> 43921 | F61: ='Data Sheet'!H16 -> 44286 | G61: ='Data Sheet'!I16 -> 44651 | H61: ='Data Sheet'!J16 -> 45016 | I61: ='Data Sheet'!K16 -> 45382
B62: Net Profit | C62: ='Data Sheet'!E30 -> 1634.18 | D62: ='Data Sheet'!F30 -> 2341.53 | E62: ='Data Sheet'!G30 -> 1496.58 | F62: ='Data Sheet'!H30 -> 1720.82 | G62: ='Data Sheet'!I30 -> 1783.39 | H62: ='Data Sheet'!J30 -> 1702.46 | I62: ='Data Sheet'!K30 -> -560.55
B63: Average Shareholder Equity | C63: =(('Data Sheet'!E57+'Data Sheet'!E58)+('Data Sheet'!D57+'Data Sheet'!D58))/2 -> 5780.13 | D63: =(('Data Sheet'!F57+'Data Sheet'!F58)+('Data Sheet'!E57+'Data Sheet'!E58))/2 -> 6762.615 | E63: =(('Data Sheet'!G57+'Data Sheet'!G58)+('Data Sheet'!F57+'Data Sheet'!F58))/2 -> 7582.64 | F63: =(('Data Sheet'!H57+'Data Sheet'!H58)+('Data Sheet'!G57+'Data Sheet'!G58))/2 -> 8668.63 | G63: =(('Data Sheet'!I57+'Data Sheet'!I58)+('Data Sheet'!H57+'Data Sheet'!H58))/2 -> 10497.415 | H63: =(('Data Sheet'!J57+'Data Sheet'!J58)+('Data Sheet'!I57+'Data Sheet'!I58))/2 -> 12675.08 | I63: =(('Data Sheet'!K57+'Data Sheet'!K58)+('Data Sheet'!J57+'Data Sheet'!J58))/2 -> 13196.4
B64: Return on Equity | C64: =C62/C63 -> 0.28272374 | D64: =D62/D63 -> 0.34624624 | E64: =E62/E63 -> 0.19736925 | F64: =F62/F63 -> 0.19851118 | G64: =G62/G63 -> 0.16988849 | H64: =H62/H63 -> 0.13431552 | I64: =I62/I63 -> -0.042477494
B66: ROE - Dupont Equation
C67: =C61 -> 43190 | D67: =D61 -> 43555 | E67: =E61 -> 43921 | F67: =F61 -> 44286 | G67: =G61 -> 44651 | H67: =H61 -> 45016 | I67: =I61 -> 45382
B68: =B62 -> Net Profit | C68: =C62 -> 1634.18 | D68: =D62 -> 2341.53 | E68: =E62 -> 1496.58 | F68: =F62 -> 1720.82 | G68: =G62 -> 1783.39 | H68: =H62 -> 1702.46 | I68: =I62 -> -560.55
B69: Revenue | C69: ='Data Sheet'!E17 -> 9847.43 | D69: ='Data Sheet'!F17 -> 10314.34 | E69: ='Data Sheet'!G17 -> 9910.8 | F69: ='Data Sheet'!H17 -> 11028.62 | G69: ='Data Sheet'!I17 -> 12276.5 | H69: ='Data Sheet'!J17 -> 13315.97 | I69: ='Data Sheet'!K17 -> 14096.11
B70: Net Profit Margin (A) | C70: =C68/C69 -> 0.1659499 | D70: =D68/D69 -> 0.22701695 | E70: =E68/E69 -> 0.15100496 | F70: =F68/F69 -> 0.15603221 | G70: =G68/G69 -> 0.1452686 | H70: =H68/H69 -> 0.12785099 | I70: =I68/I69 -> -0.03976629
B72: Revenue | C72: =C69 -> 9847.43 | D72: =D69 -> 10314.34 | E72: =E69 -> 9910.8 | F72: =F69 -> 11028.62 | G72: =G69 -> 12276.5 | H72: =H69 -> 13315.97 | I72: =I69 -> 14096.11
B73: Average Total Asset | C73: =('Data Sheet'!E66+'Data Sheet'!D66)/2 -> 13402.01 | D73: =('Data Sheet'!F66+'Data Sheet'!E66)/2 -> 13978.66 | E73: =('Data Sheet'!G66+'Data Sheet'!F66)/2 -> 14486.915 | F73: =('Data Sheet'!H66+'Data Sheet'!G66)/2 -> 14562.035 | G73: =('Data Sheet'!I66+'Data Sheet'!H66)/2 -> 15162.955 | H73: =('Data Sheet'!J66+'Data Sheet'!I66)/2 -> 16759.69 | I73: =('Data Sheet'!K66+'Data Sheet'!J66)/2 -> 17914.67
B74: Asset Turnover Ratio (B) | C74: =C72/C73 -> 0.73477262 | D74: =D72/D73 -> 0.73786329 | E74: =E72/E73 -> 0.68412081 | F74: =F72/F73 -> 0.75735431 | G74: =G72/G73 -> 0.8096377 | H74: =H72/H73 -> 0.79452365 | I74: =I72/I73 -> 0.78684732
B76: =B73 -> Average Total Asset | C76: =C73 -> 13402.01 | D76: =D73 -> 13978.66 | E76: =E73 -> 14486.915 | F76: =F73 -> 14562.035 | G76: =G73 -> 15162.955 | H76: =H73 -> 16759.69 | I76: =I73 -> 17914.67
B77: =B63 -> Average Shareholder Equity | C77: =C63 -> 5780.13 | D77: =D63 -> 6762.615 | E77: =E63 -> 7582.64 | F77: =F63 -> 8668.63 | G77: =G63 -> 10497.415 | H77: =H63 -> 12675.08 | I77: =I63 -> 13196.4
B78: Equity Multiplier (C) | C78: =C76/C77 -> 2.3186347 | D78: =D76/D77 -> 2.0670495 | E78: =E76/E77 -> 1.9105371 | F78: =F76/F77 -> 1.6798543 | G78: =G76/G77 -> 1.4444466 | H78: =H76/H77 -> 1.3222552 | I78: =I76/I77 -> 1.3575422
B80: Return on Equity (A*B*C) | C80: =C78*C74*C70 -> 0.28272374 | D80: =D78*D74*D70 -> 0.34624624 | E80: =E78*E74*E70 -> 0.19736925 | F80: =F78*F74*F70 -> 0.19851118 | G80: =G78*G74*G70 -> 0.16988849 | H80: =H78*H74*H70 -> 0.13431552 | I80: =I78*I74*I70 -> -0.042477494
B82: Return on Asset
C83: =C67 -> 43190 | D83: =D67 -> 43555 | E83: =E67 -> 43921 | F83: =F67 -> 44286 | G83: =G67 -> 44651 | H83: =H67 -> 45016 | I83: =I67 -> 45382
B84: Net Profit | C84: =C68 -> 1634.18 | D84: =D68 -> 2341.53 | E84: =E68 -> 1496.58 | F84: =F68 -> 1720.82 | G84: =G68 -> 1783.39 | H84: =H68 -> 1702.46 | I84: =I68 -> -560.55
B85: =B76 -> Average Total Asset | C85: =C73 -> 13402.01 | D85: =D73 -> 13978.66 | E85: =E73 -> 14486.915 | F85: =F73 -> 14562.035 | G85: =G73 -> 15162.955 | H85: =H73 -> 16759.69 | I85: =I73 -> 17914.67
B86: Return on Asset | C86: =C84/C85 -> 0.12193544 | D86: =D84/D85 -> 0.16750747 | E86: =E84/E85 -> 0.10330564 | F86: =F84/F85 -> 0.11817167 | G86: =G84/G85 -> 0.11761494 | H86: =H84/H85 -> 0.10158064 | I86: =I84/I85 -> -0.031289999
B88: ROA - Dupont Equation
C89: =C83 -> 43190 | D89: =D83 -> 43555 | E89: =E83 -> 43921 | F89: =F83 -> 44286 | G89: =G83 -> 44651 | H89: =H83 -> 45016 | I89: =I83 -> 45382
B90: =B84 -> Net Profit | C90: =C84 -> 1634.18 | D90: =D84 -> 2341.53 | E90: =E84 -> 1496.58 | F90: =F84 -> 1720.82 | G90: =G84 -> 1783.39 | H90: =H84 -> 1702.46 | I90: =I84 -> -560.55
B91: Revenue | C91: =C72 -> 9847.43 | D91: =D72 -> 10314.34 | E91: =E72 -> 9910.8 | F91: =F72 -> 11028.62 | G91: =G72 -> 12276.5 | H91: =H72 -> 13315.97 | I91: =I72 -> 14096.11
B92: Net Profit Margin (A) | C92: =C90/C91 -> 0.1659499 | D92: =D90/D91 -> 0.22701695 | E92: =E90/E91 -> 0.15100496 | F92: =F90/F91 -> 0.15603221 | G92: =G90/G91 -> 0.1452686 | H92: =H90/H91 -> 0.12785099 | I92: =I90/I91 -> -0.03976629
B94: Revenue | C94: =C91 -> 9847.43 | D94: =D91 -> 10314.34 | E94: =E91 -> 9910.8 | F94: =F91 -> 11028.62 | G94: =G91 -> 12276.5 | H94: =H91 -> 13315.97 | I94: =I91 -> 14096.11
B95: Average Total Asset | C95: =C85 -> 13402.01 | D95: =D85 -> 13978.66 | E95: =E85 -> 14486.915 | F95: =F85 -> 14562.035 | G95: =G85 -> 15162.955 | H95: =H85 -> 16759.69 | I95: =I85 -> 17914.67
B96: Asset Turnover Ratio (B) | C96: =C94/C95 -> 0.73477262 | D96: =D94/D95 -> 0.73786329 | E96: =E94/E95 -> 0.68412081 | F96: =F94/F95 -> 0.75735431 | G96: =G94/G95 -> 0.8096377 | H96: =H94/H95 -> 0.79452365 | I96: =I94/I95 -> 0.78684732
B98: Return on Asset (A*B) | C98: =C96*C92 -> 0.12193544 | D98: =D96*D92 -> 0.16750747 | E98: =E96*E92 -> 0.10330564 | F98: =F96*F92 -> 0.11817167 | G98: =G96*G92 -> 0.11761494 | H98: =H96*H92 -> 0.10158064 | I98: =I96*I92 -> -0.031289999

Sheet Altman Z Score
B3: ='Data Sheet'!B1 -> GODREJ CONSUMER PRODUCTS LTD
B4: =CONCATENATE(" ","(",VLOOKUP(B3,'List of Stocks'!A2:C5442,3,1)," | ","BSE Code: ",VLOOKUP(B3,'List of Stocks'!A2:B5442,2,1),")") -> (GODREJCP | BSE Code: 532424)
B5: =CONCATENATE(" ","INR "& 'Data Sheet'!B8) -> INR 1343.75
B6: 52 Week (High - INR 1542 & Low - 1055)
B8: Altman's Z Score Analysis
B9: Godrej Consumer Products Limited (GCPL) is an Indian Multinational consumer goods company based in Mumbai, India. GCPL's products include soap, hair colorants, toiletries, and liquid detergents. Its brands include 'Cinthol', 'Godrej Fair Glow', 'Godrej No.1' and 'Godrej Shikakai' in soaps, 'Godrej Powder Hair Dye', 'Renew', 'ColourSoft' in hair colourants and 'Ezee' iquid detergent. GCPL operates several manufacturing facilities in India spread over seven locations and grouped into four operating clusters at Malanpur (Madhya Pradesh), Guwahati (Assam), Baddi- Thana (Himachal Pradesh), Baddi- Katha (Himachal Pradesh), Pondicherry, Chennai and Sikkim.
B14: Financial Summary
B60: Working Capital / Total Assets
C61: ='Data Sheet'!E16 -> 43190 | D61: ='Data Sheet'!F16 -> 43555 | E61: ='Data Sheet'!G16 -> 43921 | F61: ='Data Sheet'!H16 -> 44286 | G61: ='Data Sheet'!I16 -> 44651 | H61: ='Data Sheet'!J16 -> 45016 | I61: ='Data Sheet'!K16 -> 45382
B62: Working Capital | C62: ='Data Sheet'!E65-'Data Sheet'!E60 -> 369.72 | D62: ='Data Sheet'!F65-'Data Sheet'!F60 -> 1410.67 | E62: ='Data Sheet'!G65-'Data Sheet'!G60 -> 1512.91 | F62: ='Data Sheet'!H65-'Data Sheet'!H60 -> 1661.57 | G62: ='Data Sheet'!I65-'Data Sheet'!I60 -> 2909.1 | H62: ='Data Sheet'!J65-'Data Sheet'!J60 -> 1915.75 | I62: ='Data Sheet'!K65-'Data Sheet'!K60 -> 1793.5
B63: Total Assets | C63: ='Data Sheet'!E66 -> 13863.77 | D63: ='Data Sheet'!F66 -> 14093.55 | E63: ='Data Sheet'!G66 -> 14880.28 | F63: ='Data Sheet'!H66 -> 14243.79 | G63: ='Data Sheet'!I66 -> 16082.12 | H63: ='Data Sheet'!J66 -> 17437.26 | I63: ='Data Sheet'!K66 -> 18392.08
B64: Working Capital / Total Assets (A) | C64: =C62/C63 -> 0.026668071 | D64: =D62/D63 -> 0.10009331 | E64: =E62/E63 -> 0.10167215 | F64: =F62/F63 -> 0.11665224 | G64: =G62/G63 -> 0.18089033 | H64: =H62/H63 -> 0.10986531 | I64: =I62/I63 -> 0.0975148
B66: Retained Earnings / Total Assets
C67: =C61 -> 43190 | D67: =D61 -> 43555 | E67: =E61 -> 43921 | F67: =F61 -> 44286 | G67: =G61 -> 44651 | H67: =H61 -> 45016 | I67: =I61 -> 45382
B68: Retained Earnings | C68: =HistoricalFS!F47*HistoricalFS!F41*HistoricalFS!F39 -> 669.6 | D68: =HistoricalFS!G47*HistoricalFS!G41*HistoricalFS!G39 -> 957.38 | E68: =HistoricalFS!H47*HistoricalFS!H41*HistoricalFS!H39 -> 646.68 | F68: =HistoricalFS!I47*HistoricalFS!I41*HistoricalFS!I39 -> 1698.22 | G68: =HistoricalFS!J47*HistoricalFS!J41*HistoricalFS!J39 -> 1705.12 | H68: =HistoricalFS!K47*HistoricalFS!K41*HistoricalFS!K39 -> 1588.16 | I68: =HistoricalFS!L47*HistoricalFS!L41*HistoricalFS!L39 -> 1648.01
B69: Total Assets | C69: =C$63 -> 13863.77 | D69: =D$63 -> 14093.55 | E69: =E$63 -> 14880.28 | F69: =F$63 -> 14243.79 | G69: =G$63 -> 16082.12 | H69: =H$63 -> 17437.26 | I69: =I$63 -> 18392.08
B70: Retained Earnings / Total Assets (B) | C70: =C68/C69 -> 0.048298551 | D70: =D68/D69 -> 0.067930365 | E70: =E68/E69 -> 0.04345886 | F70: =F68/F69 -> 0.11922529 | G70: =G68/G69 -> 0.10602582 | H70: =H68/H69 -> 0.09107853 | I70: =I68/I69 -> 0.08960433
B72: EBIT / Total Assets
C73: =C67 -> 43190 | D73: =D67 -> 43555 | E73: =E67 -> 43921 | F73: =F67 -> 44286 | G73: =G67 -> 44651 | H73: =H67 -> 45016 | I73: =I67 -> 45382
B74: EBIT | C74: =HistoricalFS!F30+HistoricalFS!F24 -> 1928.72 | D74: =HistoricalFS!G30+HistoricalFS!G24 -> 1961.59 | E74: =HistoricalFS!H30+HistoricalFS!H24 -> 1956.47 | F74: =HistoricalFS!I30+HistoricalFS!I24 -> 2195.41 | G74: =HistoricalFS!J30+HistoricalFS!J24 -> 2199.25 | H74: =HistoricalFS!K30+HistoricalFS!K24 -> 2206.91 | I74: =HistoricalFS!L30+HistoricalFS!L24 -> 2716.36
B75: Total Assets | C75: =C$63 -> 13863.77 | D75: =D$63 -> 14093.55 | E75: =E$63 -> 14880.28 | F75: =F$63 -> 14243.79 | G75: =G$63 -> 16082.12 | H75: =H$63 -> 17437.26 | I75: =I$63 -> 18392.08
B76: EBIT/Total Assets (C) | C76: =C74/C75 -> 0.13911945 | D76: =D74/D75 -> 0.13918353 | E76: =E74/E75 -> 0.13148072 | F76: =F74/F75 -> 0.15413103 | G76: =G74/G75 -> 0.13675125 | H76: =H74/H75 -> 0.12656289 | I76: =I74/I75 -> 0.14769183
B78: Market Cap / Long term Liabilities
C79: =C67 -> 43190 | D79: =D67 -> 43555 | E79: =E67 -> 43921 | F79: =F67 -> 44286 | G79: =G67 -> 44651 | H79: =H67 -> 45016 | I79: =I67 -> 45382
B80: Market Cap | C80: =('Data Sheet'!E90*'Data Sheet'!E70)/10000000 -> 49675.735 | D80: =('Data Sheet'!F90*'Data Sheet'!F70)/10000000 -> 70120.594 | E80: =('Data Sheet'!G90*'Data Sheet'!G70)/10000000 -> 53247.347 | F80: =('Data Sheet'!H90*'Data Sheet'!H70)/10000000 -> 74605.711 | G80: =('Data Sheet'!I90*'Data Sheet'!I70)/10000000 -> 76417.484 | H80: =('Data Sheet'!J90*'Data Sheet'!J70)/10000000 -> 99012.247 | I80: =('Data Sheet'!K90*'Data Sheet'!K70)/10000000 -> 128036.65
B81: Long term Liabilities | C81: ='Data Sheet'!E59 -> 3507.57 | D81: ='Data Sheet'!F59 -> 3382.05 | E81: ='Data Sheet'!G59 -> 3574.97 | F81: ='Data Sheet'!H59 -> 1863.97 | G81: ='Data Sheet'!I59 -> 1704.34 | H81: ='Data Sheet'!J59 -> 1129.58 | I81: ='Data Sheet'!K59 -> 3222.2
B82: Market Cap / Long term Liabilities (D) | C82: =C80/C81 -> 14.162436 | D82: =D80/D81 -> 20.733163 | E82: =E80/E81 -> 14.894488 | F82: =F80/F81 -> 40.025167 | G82: =G80/G81 -> 44.836995 | H82: =H80/H81 -> 87.654037 | I82: =I80/I81 -> 39.735786
B84: Sales / Total Assets
C85: =C67 -> 43190 | D85: =D67 -> 43555 | E85: =E67 -> 43921 | F85: =F67 -> 44286 | G85: =G67 -> 44651 | H85: =H67 -> 45016 | I85: =I67 -> 45382
B86: Total Sales | C86: ='Data Sheet'!E17 -> 9847.43 | D86: ='Data Sheet'!F17 -> 10314.34 | E86: ='Data Sheet'!G17 -> 9910.8 | F86: ='Data Sheet'!H17 -> 11028.62 | G86: ='Data Sheet'!I17 -> 12276.5 | H86: ='Data Sheet'!J17 -> 13315.97 | I86: ='Data Sheet'!K17 -> 14096.11
B87: Total Assets | C87: =C75 -> 13863.77 | D87: =D75 -> 14093.55 | E87: =E75 -> 14880.28 | F87: =F75 -> 14243.79 | G87: =G75 -> 16082.12 | H87: =H75 -> 17437.26 | I87: =I75 -> 18392.08
B88: Total Sales / Total Assets (E) | C88: =C86/C87 -> 0.71029958 | D88: =D86/D87 -> 0.73184826 | E88: =E86/E87 -> 0.66603585 | F88: =F86/F87 -> 0.77427567 | G88: =G86/G87 -> 0.76336329 | H88: =H86/H87 -> 0.76365037 | I88: =I86/I87 -> 0.76642283
B90: Altman's Z Score
C91: =C85 -> 43190 | D91: =D85 -> 43555 | E91: =E85 -> 43921 | F91: =F85 -> 44286 | G91: =G85 -> 44651 | H91: =H85 -> 45016 | I91: =I85 -> 45382
B92: Final Score | C92: =(C64*1.2)+(C70*1.4)+(C76*3.3)+(C82*0.6)*(C88*1) -> 6.5944572 | D92: =(D64*1.2)+(D70*1.4)+(D76*3.3)+(D82*0.6)*(D88*1) -> 9.7786377 | E92: =(E64*1.2)+(E70*1.4)+(E76*3.3)+(E82*0.6)*(E88*1) -> 6.5688931 | F92: =(F64*1.2)+(F70*1.4)+(F76*3.3)+(F82*0.6)*(F88*1) -> 19.409838 | G92: =(G64*1.2)+(G70*1.4)+(G76*3.3)+(G82*0.6)*(G88*1) -> 21.352933 | H92: =(H64*1.2)+(H70*1.4)+(H76*3.3)+(H82*0.6)*(H88*1) -> 40.839228 | I92: =(I64*1.2)+(I70*1.4)+(I76*3.3)+(I82*0.6)*(I88*1) -> 19.002495
B93: Financial Stability | C93: =IF(C92<1.81," Distressed",IF(C92>3,"Strong","Grey Zone")) -> Strong | D93: =IF(D92<1.81," Distressed",IF(D92>3,"Strong","Grey Zone")) -> Strong | E93: =IF(E92<1.81," Distressed",IF(E92>3,"Strong","Grey Zone")) -> Strong | F93: =IF(F92<1.81," Distressed",IF(F92>3,"Strong","Grey Zone")) -> Strong | G93: =IF(G92<1.81," Distressed",IF(G92>3,"Strong","Grey Zone")) -> Strong | H93: =IF(H92<1.81," Distressed",IF(H92>3,"Strong","Grey Zone")) -> Strong | I93: =IF(I92<1.81," Distressed",IF(I92>3,"Strong","Grey Zone")) -> Strong

Sheet Data>

Sheet Data Sheet
A1: COMPANY NAME | B1: GODREJ CONSUMER PRODUCTS LTD | E1: =IF(B2<>B3, "A NEW VERSION OF THE WORKSHEET IS AVAILABLE", "")
A2: LATEST VERSION | B2: 2.1 | E2: PLEASE DO NOT MAKE ANY CHANGES TO THIS SHEET
A3: CURRENT VERSION | B3: 2.1
A5: META
A6: Number of shares | B6: =IF(B9>0, B9/B8, 0) -> 102.29245
A7: Face Value | B7: 1
A8: Current Price | B8: 1343.75
A9: Market Capitalization | B9: 137455.48
A15: PROFIT & LOSS | B15: =B26+B34 -> 1473.43 | K15: =K17-K18-K20-K21-K22-K23-K19 -> 3289.27
A16: Report Date | B16: 42094 | C16: 42460 | D16: 42825 | E16: 43190 | F16: 43555 | G16: 43921 | H16: 44286 | I16: 44651 | J16: 45016 | K16: 45382
A17: Sales | B17: 8273.15 | C17: 8423.88 | D17: 9267.91 | E17: 9847.43 | F17: 10314.34 | G17: 9910.8 | H17: 11028.62 | I17: 12276.5 | J17: 13315.97 | K17: 14096.11
A18: Raw Material Cost | B18: 3806.48 | C18: 3959.14 | D18: 4265.85 | E18: 4218.36 | F18: 4399.79 | G18: 4434.83 | H18: 4971.77 | I18: 6136.63 | J18: 6489.85 | K18: 6333.43
A19: Change in Inventory | B19: -35.04 | C19: 91.9 | D19: 133.33 | E19: -56 | F19: -154.54 | G19: 173.15 | H19: 42.35 | I19: 61.54 | J19: -212.94 | K19: 13.13
A20: Power and Fuel | B20: 109.92 | C20: 109.99 | D20: 89.02 | E20: 101.11 | F20: 119.29 | G20: 118.29 | H20: 106.23 | I20: 133.49 | J20: 154.63 | K20: 150.85
A21: Other Mfr. Exp | B21: 223.97 | C21: 236.23 | D21: 302.85 | E21: 318.75 | F21: 329.8 | G21: 378.69 | H21: 397.25 | I21: 430.3 | J21: 438.91 | K21: 420.43
A22: Employee Cost | B22: 776.95 | C22: 944.13 | D22: 988.46 | E22: 1057.41 | F22: 1068.41 | G22: 1018.82 | H22: 1123.34 | I22: 1104.14 | J22: 1111.48 | K22: 1249.34
A23: Selling and admin | B23: 1818.85 | C23: 1464.98 | D23: 1649.39 | E23: 1775.76 | F23: 1888.86 | G23: 1770.13 | H23: 1808.73 | I23: 1836.49 | J23: 2144.44 | K23: 2639.66
A24: Other Expenses | B24: 122.99 | C24: 143.93 | D24: 198.96 | E24: 235.64 | F24: 222.08 | G24: 209.44 | H24: 264.39 | I24: 287.81 | J24: 320.52 | K24: 358.21
A25: Other Income | B25: 73.01 | C25: -262.04 | D25: 76.18 | E25: 283.28 | F25: 361.95 | G25: 32.06 | H25: 22.6 | I25: 78.27 | J25: 114.3 | K25: -2208.56
A26: Depreciation | B26: 90.78 | C26: 100.63 | D26: 141.57 | E26: 155.68 | F26: 169.98 | G26: 197.28 | H26: 203.85 | I26: 209.93 | J26: 236.29 | K26: 240.96
A27: Interest | B27: 112.46 | C27: 128.04 | D27: 154.19 | E27: 173.12 | F27: 238.21 | G27: 228.13 | H27: 137.65 | I27: 122.26 | J27: 188.48 | K27: 309.57
... A30: Net profit | B30: 907.12 | C30: 827.61 | D30: 1304.08 | E30: 1634.18 | F30: 2341.53 | G30: 1496.58 | H30: 1720.82 | I30: 1783.39 | J30: 1702.46 | K30: -560.55
A31: Dividend Amount | B31: 187.22 | C31: 195.79 | D31: 510.9 | E31: 681.3 | F31: 1022.2 | G31: 817.84
A32: Effective Tax Rate | B32: =B29/B28 -> 0.21805529 | C32: =C29/C28 -> 0.28804203 | D32: =D29/D28 -> 0.22473668 | E32: =E29/E28 -> 0.19849133 | F32: =F29/F28 -> -0.12285825 | G32: =G29/G28 -> 0.14986367 | H32: =H29/H28 -> 0.17282586 | I32: =I29/I28 -> 0.17254067 | ... K32: =K29/K28 -> 3.8277758
A34: EBITDA | B34: =+B30+B29+B27+B26 -> 1382.65 | C34: =+C30+C29+C27+C26 -> 1392.33 | D34: =+D30+D29+D27+D26 -> 1979 | E34: =+E30+E29+E27+E26 -> 2367.68 | F34: =+F30+F29+F27+F26 -> 2493.52 | G34: =+G30+G29+G27+G26 -> 2185.81 | H34: =+H30+H29+H27+H26 -> 2421.86 | I34: =+I30+I29+I27+I26 -> 2487.45 | ... K34: =+K30+K29+K27+K26 -> 748.76
A40: Quarters
A41: Report Date | B41: 44651 | C41: 44742 | D41: 44834 | E41: 44926 | F41: 45016 | G41: 45107 | H41: 45199 | I41: 45291 | J41: 45382 | K41: 45473
A42: Sales | B42: 2915.82 | C42: 3124.97 | D42: 3391.92 | E42: 3598.92 | F42: 3200.16 | G42: 3448.91 | H42: 3601.95 | I42: 3659.64 | J42: 3385.61 | K42: 3331.58
A43: Expenses | B43: 2452.75 | C43: 2604.17 | D43: 2849.81 | E43: 2872.28 | F43: 2559.29 | G43: 2806.07 | H43: 2897.78 | I43: 2818.92 | J43: 2629.89 | K43: 2607.15
A44: Other Income | B44: 3.24 | C44: 25.69 | D44: 17.2 | E44: 35.71 | F44: 35.74 | G44: -12.67 | H44: 53.39 | I44: 63.19 | J44: -2311.81 | K44: 56.81
A45: Depreciation | B45: 49.5 | C45: 57.06 | D45: 53.32 | E45: 57.32 | F45: 68.59 | G45: 76.29 | H45: 60.88 | I45: 53.88 | J45: 49.91 | K45: 49.46
A46: Interest | B46: 32.81 | C46: 35.06 | D46: 48.25 | E46: 39.92 | F46: 52.51 | G46: 74 | H46: 77.31 | I46: 66.59 | J46: 78.47 | K46: 87.75
A47: Profit before tax | B47: 384 | C47: 454.37 | D47: 457.74 | E47: 665.11 | F47: 555.51 | G47: 479.88 | H47: 619.37 | I47: 783.44 | J47: -1684.47 | K47: 644.03
A48: Tax | B48: 20.76 | C48: 109.25 | D48: 98.88 | E48: 118.77 | F48: 103.37 | G48: 161.06 | H48: 186.6 | I48: 202.38 | J48: 208.74 | K48: 193.34
A49: Net profit | B49: 363.24 | C49: 345.12 | D49: 358.86 | E49: 546.34 | F49: 452.14 | G49: 318.82 | H49: 432.77 | I49: 581.06 | J49: -1893.21 | K49: 450.69
A50: Operating Profit | B50: 463.07 | C50: 520.8 | D50: 542.11 | E50: 726.64 | F50: 640.87 | G50: 642.84 | H50: 704.17 | I50: 840.72 | J50: 755.72 | K50: 724.43
A51: EBITDA | B51: =B49+B48+B46+B45 -> 466.31 | C51: =C49+C48+C46+C45 -> 546.49 | D51: =D49+D48+D46+D45 -> 559.31 | E51: =E49+E48+E46+E45 -> 762.35 | F51: =F49+F48+F46+F45 -> 676.61 | G51: =G49+G48+G46+G45 -> 630.17 | H51: =H49+H48+H46+H45 -> 757.56 | I51: =I49+I48+I46+I45 -> 903.91 | ... K51: =K49+K48+K46+K45 -> 781.24
A55: BALANCE SHEET
A56: Report Date | B56: 42094 | C56: 42460 | D56: 42825 | E56: 43190 | F56: 43555 | G56: 43921 | H56: 44286 | I56: 44651 | J56: 45016 | K56: 45382
A57: Equity Share Capital | B57: 34.04 | C57: 34.05 | D57: 34.06 | E57: 68.13 | F57: 102.22 | G57: 102.23 | H57: 102.25 | I57: 102.26 | J57: 102.27 | K57: 102.28
A58: Reserves | B58: 4276.65 | C58: 4232.91 | D58: 5267.89 | E58: 6190.18 | F58: 7164.7 | G58: 7796.13 | H58: 9336.65 | I58: 11453.67 | J58: 13691.96 | K58: 12496.29
A59: Borrowings | B59: 2717.15 | C59: 2891.12 | D59: 4000.93 | E59: 3507.57 | F59: 3382.05 | G59: 3574.97 | H59: 1863.97 | I59: 1704.34 | J59: 1129.58 | K59: 3222.2
A60: Other Liabilities | B60: 2097.18 | C60: 2520.66 | D60: 3637.37 | E60: 4097.89 | F60: 3444.58 | G60: 3406.95 | H60: 2940.92 | I60: 2821.85 | J60: 2513.45 | K60: 2571.31
A61: Total | B61: 9125.02 | C61: 9678.74 | D61: 12940.25 | E61: 13863.77 | F61: 14093.55 | G61: 14880.28 | H61: 14243.79 | I61: 16082.12 | J61: 17437.26 | K61: 18392.08
A62: Net Block | B62: 5550.95 | C62: 5931.41 | D62: 8082.89 | E62: 8315 | F62: 8670.26 | G62: 9231.4 | H62: 8904.77 | I62: 9219.3 | J62: 9933.66 | K62: 10440.24
A63: Capital Work in Progress | B63: 224.61 | C63: 43.66 | D63: 97.43 | E63: 83.88 | F63: 52.06 | G63: 57.04 | H63: 57.43 | I63: 116.44 | J63: 45.42 | K63: 83.36
A64: Investments | B64: 185.69 | C64: 189.5 | D64: 933.54 | E64: 997.28 | F64: 515.98 | G64: 671.98 | H64: 679.1 | I64: 1015.43 | J64: 3028.98 | K64: 3503.67
A65: Other Assets | B65: 3163.77 | C65: 3514.17 | D65: 3826.39 | E65: 4467.61 | F65: 4855.25 | G65: 4919.86 | H65: 4602.49 | I65: 5730.95 | J65: 4429.2 | K65: 4364.81
A66: Total | B66: 9125.02 | C66: 9678.74 | D66: 12940.25 | E66: 13863.77 | F66: 14093.55 | G66: 14880.28 | H66: 14243.79 | I66: 16082.12 | J66: 17437.26 | K66: 18392.08
A67: Receivables | B67: 804.58 | C67: 1118.01 | D67: 1028.74 | E67: 1245.5 | F67: 1292.9 | G67: 1157.25 | H67: 1004.5 | I67: 1116.32 | J67: 1245.28 | K67: 1535.37
... A70: No. of Equity Shares | B70: 340446901 | C70: 340533823 | D70: 340600816 | E70: 681329518 | F70: 1022166096 | G70: 1022316352 | H70: 1022486273 | I70: 1022581079 | J70: 1022695318 | K70: 1022820329
A71: New Bonus Shares | E71: 340600816 | F71: 340722032
A72: Face value | B72: 1 | C72: 1 | D72: 1 | E72: 1 | F72: 1 | G72: 1 | H72: 1 | I72: 1 | J72: 1 | K72: 1
H73: =H62-G62+H45 -> -265.75 | I73: =I62-H62+I45 -> 368.41 | J73: =J62-I62+J45 -> 764.27 | K73: =K62-J62+K45 -> 556.04
A80: CASH FLOW:
A81: Report Date | B81: 42094 | C81: 42460 | D81: 42825 | E81: 43190 | F81: 43555 | G81: 43921 | H81: 44286 | I81: 44651 | J81: 45016 | K81: 45382
A82: Cash from Operating Activity | B82: 1026.73 | C82: 847.37 | D82: 1860.22 | E82: 1723.35 | F82: 1728.85 | G82: 1588.11 | H82: 2029.63 | I82: 1450.57 | J82: 2150.65 | K82: 2069.95
A83: Cash from Investing Activity | B83: -1235.86 | C83: -621.59 | D83: -2243.25 | E83: -336.37 | F83: 274.07 | G83: -552.12 | H83: -292.15 | I83: -844.32 | J83: -1754.46 | K83: -3435.01
A84: Cash from Financing Activity | B84: -12.04 | C84: -202.47 | D84: 664.65 | E84: -1384.01 | F84: -2038.73 | G84: -1295.33 | H84: -1816.22 | I84: -379.52 | J84: -794.31 | K84: 1406.34
A85: Net Cash Flow | B85: -221.17 | C85: 23.31 | D85: 281.62 | E85: 2.97 | F85: -35.81 | G85: -259.34 | H85: -78.74 | I85: 226.73 | J85: -398.12 | K85: 41.28
A90: PRICE: | B90: 346.99 | C90: 460.27 | D90: 557.14 | E90: 729.1 | F90: 686 | G90: 520.85 | H90: 729.65 | I90: 747.3 | J90: 968.15 | K90: 1251.8
A92: DERIVED:
A93: Adjusted Equity Shares in Cr | B93: 102.14 | C93: 102.16 | D93: 102.18 | E93: 102.2 | F93: 102.22 | G93: 102.23 | H93: 102.25 | I93: 102.26 | J93: 102.27 | K93: 102.28

Sheet Sheet6
O1: Dabur | Q1: Bajaj Consumer | S1: Emami | U1: Jyothy | W1: Varun | AA1: Colgate
B2: S.No. | C2: Name | D2: CMP Rs. | E2: Mar Cap Rs.Cr. | F2: Debt Rs.Cr. | G2: Debt / Eq | K2: Date | L2: NFY Return | O2: Adj Close | P2: Return | Q2: Adj Close | R2: Return | S2: Adj Close | T2: Return | U2: Adj Close | V2: Return | W2: Adj Close | X2: Return | Y2: N | AA2: Adj Close | AB2: Return
B3: 1 | C3: Godrej Consumer | D3: 1336.15 | E3: 136678 | F3: 3222.2 | G3: 0.26 | K3: 45208 | O3: 533.79 | Q3: 231.94 | S3: 501.56 | U3: 367.68 | W3: 371.17 | Y3: 1 | AA3: 2008.29 | AE3: SUMMARY OUTPUT
B4: 2 | C4: Dabur India | D4: 571.4 | E4: 101269.87 | F4: 1365.09 | G4: 0.14 | K4: 45215 | L4: 0.0052933027 | O4: 519.88 | P4: =O4/O3-1 -> -0.026058937 | Q4: 235.29 | R4: =Q4/Q3-1 -> 0.014443391 | S4: 501.37 | T4: =(S4/S3-1) -> -0.00037881809 | U4: 364.71 | V4: =(U4/U3-1) -> -0.0080776762 | W4: 369.86 | X4: =W4/W3-1 -> -0.0035293801 | Y4: 2 | AA4: 2068.66 | AB4: =AA4/AA3-1 -> 0.0300604
B5: 3 | C5: Emami | D5: 700.85 | E5: 30592.1 | F5: 93.95 | G5: 0.04 | K5: 45222 | L5: -0.00091528003 | M5: beta2 | N5: =((_xlfn.COVARIANCE.S($L$4:$L$56,$P$4:$P$56)/_xlfn.VAR.S($L$4:$L$56))) -> 0.69029221 | O5: 519.63 | P5: =O5/O4-1 -> -0.0004808802 | Q5: 236.67 | R5: =Q5/Q4-1 -> 0.0058651026 | S5: 496.55 | T5: =(S5/S4-1) -> -0.0096136586 | U5: 359.25 | V5: =(U5/U4-1) -> -0.014970799 | W5: 367.96 | X5: =W5/W4-1 -> -0.0051370789 | Y5: 3 | AA5: 2039.01 | AB5: =AA5/AA4-1 -> -0.01433295 | AE5: Regression Statistics
B6: 4 | C6: Jyothy Labs | D6: 512.1 | E6: 18804.75 | F6: 50.56 | G6: 0.03 | K6: 45229 | L6: 0.033886092 | M6: beta3 | N6: =((_xlfn.COVARIANCE.S($L$4:$L$56,R$4:R$56)/_xlfn.VAR.S($L$4:$L$56))) -> 0.41363446 | O6: 530.47 | P6: =O6/O5-1 -> 0.020860997 | Q6: 231.99 | R6: =Q6/Q5-1 -> -0.019774369 | S6: 500.43 | T6: =(S6/S5-1) -> 0.007813916 | U6: 359.54 | V6: =(U6/U5-1) -> 0.0008072373 | W6: 380.1 | X6: =W6/W5-1 -> 0.032992717 | Y6: 4 | AA6: 2062.98 | AB6: =AA6/AA5-1 -> 0.011755705 | AE6: Multiple R | AF6: 0.75703395
B7: 5 | C7: Bajaj Consumer | D7: 228.98 | E7: 3269.69 | F7: 8.75 | G7: 0.01 | K7: 45236 | L7: -0.035662727 | M7: beta4 | N7: =((_xlfn.COVARIANCE.S($L$4:$L$56,T$4:T$56)/_xlfn.VAR.S($L$4:$L$56))) -> 0.58255317 | O7: 528.34 | P7: =O7/O6-1 -> -0.0040153072 | Q7: 222.91 | R7: =Q7/Q6-1 -> -0.039139618 | S7: 504.61 | T7: =(S7/S6-1) -> 0.0083528166 | U7: 411.01 | V7: =(U7/U6-1) -> 0.14315514 | W7: 402.94 | X7: =W7/W6-1 -> 0.06008945 | Y7: 5 | AA7: 2065.33 | AB7: =AA7/AA6-1 -> 0.0011391288 | AE7: R Square | AF7: 0.5731004
K8: 45243 | L8: 0.017861014 | M8: beta5 | N8: =((_xlfn.COVARIANCE.S($L$4:$L$56,V$4:V$56)/_xlfn.VAR.S($L$4:$L$56))) -> 0.47654062 | O8: 538.39 | P8: =O8/O7-1 -> 0.019021842 | Q8: 222.52 | R8: =Q8/Q7-1 -> -0.001749585 | S8: 484.2 | T8: =(S8/S7-1) -> -0.040447078 | U8: 449.03 | V8: =(U8/U7-1) -> 0.092503832 | W8: 416.68 | X8: =W8/W7-1 -> 0.03409937 | Y8: 6 | AA8: 2144.69 | AB8: =AA8/AA7-1 -> 0.038424852 | AE8: Adjusted R Square | AF8: 0.56472982
K9: 45250 | L9: 0.012587611 | O9: 535.06 | P9: =O9/O8-1 -> -0.0061851074 | Q9: 219.91 | R9: =Q9/Q8-1 -> -0.011729283 | S9: 499.33 | T9: =(S9/S8-1) -> 0.031247418 | U9: 436.43 | V9: =(U9/U8-1) -> -0.028060486 | W9: 426.54 | X9: =W9/W8-1 -> 0.023663243 | Y9: 7 | AA9: 2174.05 | AB9: =AA9/AA8-1 -> 0.013689624 | AE9: Standard Error | AF9: 0.020182789
K10: 45257 | L10: 0.015756787 | O10: 538.84 | P10: =O10/O9-1 -> 0.0070646283 | Q10: 218.48 | R10: =Q10/Q9-1 -> -0.0065026602 | S10: 511.33 | T10: =(S10/S9-1) -> 0.024032203 | U10: 440.79 | V10: =(U10/U9-1) -> 0.0099901473 | W10: 434.89 | X10: =W10/W9-1 -> 0.019576124 | Y10: 8 | AA10: 2257.39 | AB10: =AA10/AA9-1 -> 0.038333985 | AE10: Observations | AF10: 53
K11: 45264 | L11: -0.0037572853 | O11: 545.17 | P11: =O11/O10-1 -> 0.011747458 | Q11: 215.77 | R11: =Q11/Q10-1 -> -0.012403881 | S11: 493.63 | T11: =(S11/S10-1) -> -0.03461561 | U11: 450.07 | V11: =(U11/U10-1) -> 0.021053109 | W11: 426.06 | X11: =W11/W10-1 -> -0.020303985 | Y11: 9 | AA11: 2271.81 | AB11: =AA11/AA10-1 -> 0.0063879082
K12: 45271 | L12: 0.020163925 | O12: 537.4 | P12: =O12/O11-1 -> -0.014252435 | Q12: 217.49 | R12: =Q12/Q11-1 -> 0.0079714511 | S12: 494.13 | T12: =(S12/S11-1) -> 0.0010129044 | U12: 458.86 | V12: =(U12/U11-1) -> 0.019530295 | W12: 438.86 | X12: =W12/W11-1 -> 0.030042717 | Y12: 10 | AA12: 2362.82 | AB12: =AA12/AA11-1 -> 0.040060568 | AE12: ANOVA
K13: 45278 | L13: 0.030797892 | O13: 527.04 | P13: =O13/O12-1 -> -0.019278005 | Q13: 211.67 | R13: =Q13/Q12-1 -> -0.026759851 | S13: 490.46 | T13: =(S13/S12-1) -> -0.0074271953 | U13: 475.74 | V13: =(U13/U12-1) -> 0.03678682 | W13: 494.6 | X13: =W13/W12-1 -> 0.12701089 | Y13: 11 | AA13: 2383.57 | AB13: =AA13/AA12-1 -> 0.0087818793 | AF13: df | AG13: SS | AH13: MS | AI13: F | AJ13: Significance F
K14: 45285 | L14: 0.053015541 | O14: 554.82 | P14: =O14/O13-1 -> 0.052709472 | Q14: 216.55 | R14: =Q14/Q13-1 -> 0.023054755 | S14: 558.86 | T14: =(S14/S13-1) -> 0.13946091 | U14: 475.39 | V14: =(U14/U13-1) -> -0.00073569597 | W14: 493.93 | X14: =W14/W13-1 -> -0.00135463 | Y14: 12 | AA14: 2505.44 | AB14: =AA14/AA13-1 -> 0.051129189 | AE14: Regression | AF14: 1 | AG14: 0.027889292 | AH14: 0.027889292 | AI14: 68.466028 | AJ14: 5.423838e-11
K15: 45292 | L15: 0.078371251 | O15: 566.62 | P15: =O15/O14-1 -> 0.021268159 | Q15: 224.34 | R15: =Q15/Q14-1 -> 0.035973216 | S15: 559.9 | T15: =(S15/S14-1) -> 0.0018609312 | U15: 514.15 | V15: =(U15/U14-1) -> 0.081533057 | W15: 510.8 | X15: =W15/W14-1 -> 0.034154637 | Y15: 13 | AA15: 2490.54 | AB15: =AA15/AA14-1 -> -0.0059470592 | AE15: Residual | AF15: 51 | AG15: 0.020774593 | AH15: 0.00040734497
K16: 45299 | L16: -0.052755488 | O16: 547.36 | P16: =O16/O15-1 -> -0.033991035 | Q16: 223.16 | R16: =Q16/Q15-1 -> -0.0052598734 | S16: 520.2 | T16: =(S16/S15-1) -> -0.070905519 | U16: 501.84 | V16: =(U16/U15-1) -> -0.023942429 | W16: 505.17 | X16: =W16/W15-1 -> -0.011021926 | Y16: 14 | AA16: 2427.84 | AB16: =AA16/AA15-1 -> -0.025175263 | AE16: Total | AF16: 52 | AG16: 0.048663885
K17: 45306 | L17: -0.0054083383 | O17: 539.99 | P17: =O17/O16-1 -> -0.01346463 | Q17: 218.77 | R17: =Q17/Q16-1 -> -0.019671984 | S17: 496.06 | T17: =(S17/S16-1) -> -0.046405229 | U17: 526.21 | V17: =(U17/U16-1) -> 0.048561294 | W17: 506.09 | X17: =W17/W16-1 -> 0.0018211691 | Y17: 15 | AA17: 2466.52 | AB17: =AA17/AA16-1 -> 0.015931857
K18: 45313 | L18: 0.0070039595 | O18: 529.33 | P18: =O18/O17-1 -> -0.019741106 | Q18: 213.74 | R18: =Q18/Q17-1 -> -0.022992184 | S18: 488.23 | T18: =(S18/S17-1) -> -0.015784381 | U18: 542.59 | V18: =(U18/U17-1) -> 0.031128257 | W18: 502.11 | X18: =W18/W17-1 -> -0.0078642139 | Y18: 16 | AA18: 2468.65 | AB18: =AA18/AA17-1 -> 0.00086356486 | AF18: Coefficients | AG18: Standard Error | AH18: t Stat | AI18: P-value | AJ18: Lower 95% | AK18: Upper 95% | AL18: Lower 95.0% | AM18: Upper 95.0%
K19: 45320 | L19: 0.068739842 | O19: 542.33 | P19: =O19/O18-1 -> 0.024559349 | Q19: 218.38 | R19: =Q19/Q18-1 -> 0.021708618 | S19: 497.1 | T19: =(S19/S18-1) -> 0.018167667 | U19: 505.96 | V19: =(U19/U18-1) -> -0.067509538 | W19: 513.43 | X19: =W19/W18-1 -> 0.022544861 | Y19: 17 | AA19: 2517.38 | AB19: =AA19/AA18-1 -> 0.019739534 | AE19: Intercept | AF19: -0.0029898854 | AG19: 0.0028273349 | AH19: -1.0574925 | AI19: 0.29527027 | AJ19: -0.0086659972 | AK19: 0.0026862263 | AL19: -0.0086659972 | AM19: 0.0026862263
K20: 45327 | L20: -0.014716342 | O20: 536.9 | P20: =O20/O19-1 -> -0.010012354 | Q20: 209.31 | R20: =Q20/Q19-1 -> -0.041533107 | S20: 480.35 | T20: =(S20/S19-1) -> -0.033695434 | U20: 442.33 | V20: =(U20/U19-1) -> -0.12576093 | W20: 547.08 | X20: =W20/W19-1 -> 0.065539606 | Y20: 18 | AA20: 2509.85 | AB20: =AA20/AA19-1 -> -0.0029912051 | AE20: X Variable 1 | AF20: 0.69029221 | AG20: 0.083424844 | AH20: 8.2744201 | AI20: 5.423838e-11 | AJ20: 0.52280985 | AK20: 0.85777457 | AL20: 0.52280985 | AM20: 0.85777457
K21: 45334 | L21: 0.018628696 | O21: 542.18 | P21: =O21/O20-1 -> 0.0098342336 | Q21: 209.11 | R21: =Q21/Q20-1 -> -0.00095552052 | S21: 456.01 | T21: =(S21/S20-1) -> -0.050671385 | U21: 468.54 | V21: =(U21/U20-1) -> 0.059254403 | W21: 568.26 | X21: =W21/W20-1 -> 0.03871463 | Y21: 19 | AA21: 2554.86 | AB21: =AA21/AA20-1 -> 0.017933343
K22: 45341 | L22: 0.0077306571 | O22: 533.02 | P22: =O22/O21-1 -> -0.016894758 | Q22: 239.3 | R22: =Q22/Q21-1 -> 0.14437377 | S22: 458.35 | T22: =(S22/S21-1) -> 0.0051314664 | U22: 466.26 | V22: =(U22/U21-1) -> -0.00486618 | W22: 604.78 | X22: =W22/W21-1 -> 0.064266357 | Y22: 20 | AA22: 2521.98 | AB22: =AA22/AA21-1 -> -0.01286959
K23: 45348 | L23: 0.013192463 | O23: 538.79 | P23: =O23/O22-1 -> 0.01082511 | Q23: 238.7 | R23: =Q23/Q22-1 -> -0.002507313 | S23: 455 | T23: =(S23/S22-1) -> -0.0073088251 | U23: 449.13 | V23: =(U23/U22-1) -> -0.036739158 | W23: 566.18 | X23: =W23/W22-1 -> -0.063824862 | Y23: 21 | AA23: 2510.35 | AB23: =AA23/AA22-1 -> -0.0046114561
K24: 45355 | L24: -0.026192965 | O24: 532.97 | P24: =O24/O23-1 -> -0.010801982 | Q24: 227.6 | R24: =Q24/Q23-1 -> -0.046501885 | S24: 450.2 | T24: =(S24/S23-1) -> -0.010549451 | U24: 426.35 | V24: =(U24/U23-1) -> -0.050720281 | W24: 568.38 | X24: =W24/W23-1 -> 0.0038856901 | Y24: 22 | AA24: 2553.97 | AB24: =AA24/AA23-1 -> 0.017376063
K25: 45362 | L25: -0.017459199 | O25: 524.3 | P25: =O25/O24-1 -> -0.016267332 | Q25: 213.45 | R25: =Q25/Q24-1 -> -0.062170475 | S25: 423.05 | T25: =(S25/S24-1) -> -0.06030653 | U25: 424.27 | V25: =(U25/U24-1) -> -0.0048786209 | W25: 572.71 | X25: =W25/W24-1 -> 0.0076181428 | Y25: 23 | AA25: 2702.39 | AB25: =AA25/AA24-1 -> 0.058113447
K26: 45369 | L26: 0.0073796123 | O26: 518.58 | P26: =O26/O25-1 -> -0.010909784 | Q26: 219.1 | R26: =Q26/Q25-1 -> 0.026469899 | S26: 424.25 | T26: =(S26/S25-1) -> 0.0028365441 | U26: 421.14 | V26: =(U26/U25-1) -> -0.0073773776 | W26: 560.01 | X26: =W26/W25-1 -> -0.022175272 | Y26: 24 | AA26: 2682.08 | AB26: =AA26/AA25-1 -> -0.0075155696
K27: 45376 | L27: 0.024683387 | O27: 520.92 | P27: =O27/O26-1 -> 0.0045123221 | Q27: 212.05 | R27: =Q27/Q26-1 -> -0.032177088 | S27: 429.35 | T27: =(S27/S26-1) -> 0.012021214 | U27: 436.72 | V27: =(U27/U26-1) -> 0.036994824 | W27: 558.5 | X27: =W27/W26-1 -> -0.0026963804 | Y27: 25 | AA27: 2684.36 | AB27: =AA27/AA26-1 -> 0.0008500865
K28: 45383 | L28: -0.033313946 | O28: 505.73 | P28: =O28/O27-1 -> -0.029159948 | Q28: 230.75 | R28: =Q28/Q27-1 -> 0.088186748 | S28: 446.6 | T28: =(S28/S27-1) -> 0.040177012 | U28: 441.09 | V28: =(U28/U27-1) -> 0.010006411 | W28: 596.49 | X28: =W28/W27-1 -> 0.068021486 | Y28: 26 | AA28: 2703.18 | AB28: =AA28/AA27-1 -> 0.0070109821
K29: 45390 | L29: -0.0085570077 | O29: 498.47 | P29: =O29/O28-1 -> -0.014355486 | Q29: 228.5 | R29: =Q29/Q28-1 -> -0.0097508126 | S29: 454.25 | T29: =(S29/S28-1) -> 0.017129422 | U29: 431.81 | V29: =(U29/U28-1) -> -0.02103879 | W29: 553.87 | X29: =W29/W28-1 -> -0.071451324 | Y29: 27 | AA29: 2636.38 | AB29: =AA29/AA28-1 -> -0.024711636
K30: 45397 | L30: -0.0257493 | O30: 502.05 | P30: =O30/O29-1 -> 0.0071819768 | Q30: 225.65 | R30: =Q30/Q29-1 -> -0.012472648 | S30: 441.95 | T30: =(S30/S29-1) -> -0.0270776 | U30: 407.14 | V30: =(U30/U29-1) -> -0.057131609 | W30: 557.97 | X30: =W30/W29-1 -> 0.0074024591 | Y30: 28 | AA30: 2624.24 | AB30: =AA30/AA29-1 -> -0.004604799
K31: 45404 | L31: 0.028783016 | O31: 506.83 | P31: =O31/O30-1 -> 0.009520964 | Q31: 230.1 | R31: =Q31/Q30-1 -> 0.019720807 | S31: 480.2 | T31: =(S31/S30-1) -> 0.086548252 | U31: 417.37 | V31: =(U31/U30-1) -> 0.025126492 | W31: 583.39 | X31: =W31/W30-1 -> 0.045558005 | Y31: 29 | AA31: 2827.77 | AB31: =AA31/AA30-1 -> 0.077557693
K32: 45411 | L32: 0.040499176 | O32: 529.48 | P32: =O32/O31-1 -> 0.044689541 | Q32: 253.85 | R32: =Q32/Q31-1 -> 0.10321599 | S32: 495.45 | T32: =(S32/S31-1) -> 0.031757601 | U32: 420.1 | V32: =(U32/U31-1) -> 0.0065409589 | W32: 602.17 | X32: =W32/W31-1 -> 0.032191159 | Y32: 30 | AA32: 2772.31 | AB32: =AA32/AA31-1 -> -0.019612628
... K56: 45579 | L56: 0.015543057 | O56: 567.3 | P56: =O56/O55-1 -> -0.0062187965 | Q56: 226.96 | R56: =Q56/Q55-1 -> -0.013174486 | S56: 724.6 | T56: =(S56/S55-1) -> -0.0077370763 | U56: 521.55 | V56: =(U56/U55-1) -> -0.010810811 | W56: 588.75 | X56: =W56/W55-1 -> -0.006077488 | Y56: 54 | AA56: 3522.45 | AB56: =AA56/AA55-1 -> -0.045315951

Sheet Cash Flow Data
C2: 42064 | D2: 42430 | E2: 42795 | F2: 43160 | G2: 43525 | H2: 43891 | I2: 44256 | J2: 44621 | K2: 44986 | L2: 45352
B3: Cash from Operating Activity - | C3: 1027 | D3: 847 | E3: 1860 | F3: 1723 | G3: 1729 | H3: 1588 | I3: 2030 | J3: 1451 | K3: 2151 | L3: 2070
B4: Profit from operations | C4: 1397 | D4: 1669 | E4: 1947 | F4: 2147 | G4: 2181 | H4: 2185 | I4: 2472 | J4: 2434 | K4: 2476 | L4: 2900
B5: Receivables | C5: -81 | D5: -323 | E5: 166 | F5: -245 | G5: -174 | H5: 130 | I5: 81 | J5: -89 | K5: -165 | L5: -479
B6: Inventory | C6: 26 | D6: -235 | E6: 46 | F6: -165 | G6: -20 | H6: -169 | I6: -70 | J6: -384 | K6: 555 | L6: -71
B7: Payables | C7: 0 | D7: 17 | E7: 196 | F7: 613 | G7: 274 | H7: -95 | I7: -473 | J7: 83 | K7: -370 | L7: 91
B8: Loans Advances | C8: 8 | D8: 1 | E8: -3 | F8: 1 | G8: -1 | H8: -3 | I8: 1 | J8: 0 | K8: 0 | L8: 0
B9: Other WC items | C9: -39 | D9: 75 | E9: -65 | F9: -219 | G9: -79 | H9: -116 | I9: 416 | J9: -146 | K9: 74 | L9: 3
B10: Working capital changes | C10: -87 | D10: -465 | E10: 341 | F10: -16 | G10: 1 | H10: -253 | I10: -45 | J10: -536 | K10: 93 | L10: -456
B11: Direct taxes | C11: -257 | D11: -336 | E11: -407 | F11: -393 | G11: -435 | H11: -344 | I11: -397 | J11: -448 | K11: -418 | L11: -374
B12: Cash from Investing Activity - | C12: -1236 | D12: -622 | E12: -2243 | F12: -336 | G12: 274 | H12: -552 | I12: -292 | J12: -844 | K12: -1754 | L12: -3435
B13: Fixed assets purchased | C13: -213 | D13: -208 | E13: -180 | F13: -311 | G13: -208 | H13: -152 | I13: -164 | J13: 0 | K13: 0 | L13: 0
B14: Fixed assets sold | C14: 0 | D14: 0 | E14: 0 | F14: 0 | G14: 0 | H14: 0 | I14: 0 | J14: 3 | K14: 8 | L14: 31
... B33: Net Cash Flow | C33: -221 | D33: 23 | E33: 282 | F33: 3 | G33: -36 | H33: -259 | I33: -79 | J33: 227 | K33: -398 | L33: 41

Sheet Raw FS
C1: 41334 | D1: 41699 | E1: 42064 | F1: 42430 | G1: 42795 | H1: 43160 | I1: 43525 | J1: 43891 | K1: 44256 | L1: 44621 | M1: 44986 | N1: 45352
B2: Equity Capital | C2: 34 | D2: 34 | E2: 34 | F2: 34 | G2: 34 | H2: 68 | I2: 102 | J2: 102 | K2: 102 | L2: 102 | M2: 102 | N2: 102
B3: Reserves | C3: 3279 | D3: 3741 | E3: 4277 | F3: 4233 | G3: 5268 | H3: 6190 | I3: 7165 | J3: 7796 | K3: 9337 | L3: 11454 | M3: 13692 | N3: 12496
B4: Borrowings - | C4: 2456 | D4: 2373 | E4: 2717 | F4: 2891 | G4: 4001 | H4: 3508 | I4: 3382 | J4: 3575 | K4: 1864 | L4: 1704 | M4: 1130 | N4: 3222
B5: Long term Borrowings | C5: 1866 | D5: 1591 | E5: 2023 | F5: 2449 | G5: 3108 | H5: 2380 | I5: 2605 | J5: 2145 | K5: 480 | L5: 381 | M5: 189 | N5: 0
B6: Short term Borrowings | C6: 82 | D6: 111 | E6: 147 | F6: 182 | G6: 233 | H6: 154 | I6: 271 | J6: 519 | K6: 1288 | L6: 1227 | M6: 845 | N6: 3155
B7: Lease Liabilities | C7: 0 | D7: 0 | E7: 0 | F7: 0 | G7: 0 | H7: 0 | I7: 0 | J7: 57 | K7: 96 | L7: 97 | M7: 96 | N7: 68
B8: Other Borrowings | C8: 508 | D8: 671 | E8: 547 | F8: 260 | G8: 660 | H8: 973 | I8: 506 | J8: 855 | K8: 0 | L8: 0 | M8: 0 | N8: 0
B9: Other Liabilities - | C9: 1926 | D9: 2171 | E9: 2097 | F9: 2521 | G9: 3637 | H9: 4098 | I9: 3445 | J9: 3407 | K9: 2941 | L9: 2822 | M9: 2513 | N9: 2571
B10: Non controlling int | C10: 210 | D10: 225 | E10: 162 | F10: 10 | G10: 0 | H10: 0 | I10: 0 | J10: 0 | K10: 0 | L10: 0 | M10: 0 | N10: 0
B11: Trade Payables | C11: 1035 | D11: 1234 | E11: 1088 | F11: 1485 | G11: 1724 | H11: 2353 | I11: 2540 | J11: 2480 | K11: 2012 | L11: 2163 | M11: 1823 | N11: 1675
B12: Advance from Customers | C12: 0 | D12: 0 | E12: 0 | F12: 0 | G12: 0 | H12: 0 | I12: 0 | J12: 25 | K12: 27 | L12: 30 | M12: 38 | N12: 30
B13: Other liability items | C13: 681 | D13: 712 | E13: 847 | F13: 1026 | G13: 1913 | H13: 1745 | I13: 905 | J13: 901 | K13: 901 | L13: 629 | M13: 652 | N13: 865
... B28: Accumulated Depreciation | C28: 570 | D28: 682 | E28: 782 | F28: 93 | G28: 208 | H28: 359 | I28: 457 | J28: 661 | K28: 886 | L28: 1127 | M28: 1315 | N28: 2732
B29: Net Block | C29: =C27-C28 -> 4496 | D29: =D27-D28 -> 5122 | E29: =E27-E28 -> 5551 | F29: =F27-F28 -> 5931 | G29: =G27-G28 -> 8083 | H29: =H27-H28 -> 8315 | I29: =I27-I28 -> 8670 | J29: =J27-J28 -> 9231 | ... N29: =N27-N28 -> 10440
B31: CWIP | C31: 141 | D31: 167 | E31: 225 | F31: 44 | G31: 97 | H31: 84 | I31: 52 | J31: 57 | K31: 57 | L31: 116 | M31: 45 | N31: 83
B32: Investments | C32: 121 | D32: 136 | E32: 186 | F32: 190 | G32: 934 | H32: 997 | I32: 516 | J32: 672 | K32: 679 | L32: 1015 | M32: 3029 | N32: 3504
B34: Other Assets - | C34: 2937 | D34: 2895 | E34: 3164 | F34: 3514 | G34: 3826 | H34: 4468 | I34: 4855 | J34: 4920 | K34: 4602 | L34: 5731 | M34: 4429 | N34: 4365
B35: Inventories | C35: 1047 | D35: 1082 | E35: 1072 | F35: 1307 | G35: 1412 | H35: 1578 | I35: 1559 | J35: 1703 | K35: 1716 | L35: 2130 | M35: 1537 | N35: 1271
B36: Trade receivables | C36: 729 | D36: 732 | E36: 805 | F36: 1118 | G36: 1029 | H36: 1246 | I36: 1293 | J36: 1157 | K36: 1004 | L36: 1116 | M36: 1245 | N36: 1535
B37: Cash Equivalents | C37: 748 | D37: 705 | E37: 894 | F37: 754 | G37: 913 | H37: 960 | I37: 895 | J37: 770 | K37: 672 | L37: 1108 | M37: 391 | N37: 547
B38: Short term loans | C38: 0 | D38: 0 | E38: 0 | F38: 0 | G38: 0 | H38: 0 | I38: 0 | J38: 0 | K38: 0 | L38: 0 | M38: 0 | N38: 0
B39: Other asset items | C39: 414 | D39: 376 | E39: 393 | F39: 335 | G39: 472 | H39: 684 | I39: 1109 | J39: 1289 | K39: 1209 | L39: 1377 | M39: 1256 | N39: 1012
B40: Total Assets | C40: 7695 | D40: 8320 | E40: 9125 | F40: 9679 | G40: 12940 | H40: 13864 | I40: 14094 | J40: 14880 | K40: 14244 | L40: 16082 | M40: 17437 | N40: 18392
C43: 41334 | D43: 41699 | E43: 42064 | F43: 42430 | G43: 42795 | H43: 43160 | I43: 43525 | J43: 43891 | K43: 44256 | L43: 44621 | M43: 44986 | N43: 45352
B44: Cash from Operating Activity - | C44: 820 | D44: 1116 | E44: 1027 | F44: 847 | G44: 1860 | H44: 1723 | I44: 1729 | J44: 1588 | K44: 2030 | L44: 1451 | M44: 2151 | N44: 2070
B45: Profit from operations | C45: 996 | D45: 1168 | E45: 1397 | F45: 1669 | G45: 1947 | H45: 2147 | I45: 2181 | J45: 2185 | K45: 2472 | L45: 2434 | M45: 2476 | N45: 2900
B46: Receivables | C46: -218 | D46: 13 | E46: -81 | F46: -323 | G46: 166 | H46: -245 | I46: -174 | J46: 130 | K46: 81 | L46: -89 | M46: -165 | N46: -479
B47: Inventory | C47: -263 | D47: -35 | E47: 26 | F47: -235 | G47: 46 | H47: -165 | I47: -20 | J47: -169 | K47: -70 | L47: -384 | M47: 555 | N47: -71
B48: Payables | C48: 0 | D48: 0 | E48: 0 | F48: 17 | G48: 196 | H48: 613 | I48: 274 | J48: -95 | K48: -473 | L48: 83 | M48: -370 | N48: 91
B49: Loans Advances | C49: -60 | D49: -15 | E49: 8 | F49: 1 | G49: -3 | H49: 1 | I49: -1 | J49: -3 | K49: 1 | L49: 0 | M49: 0 | N49: 0
B50: Other WC items | C50: 484 | D50: 224 | E50: -39 | F50: 75 | G50: -65 | H50: -219 | I50: -79 | J50: -116 | K50: 416 | L50: -146 | M50: 74 | N50: 3
B51: Working capital changes | C51: -57 | D51: 186 | E51: -87 | F51: -465 | G51: 341 | H51: -16 | I51: 1 | J51: -253 | K51: -45 | L51: -536 | M51: 93 | N51: -456
B52: Direct taxes | C52: -207 | D52: -238 | E52: -257 | F52: -336 | G52: -407 | H52: -393 | I52: -435 | J52: -344 | K52: -397 | L52: -448 | M52: -418 | N52: -374
B53: Other operating items | C53: 0 | D53: 0 | E53: 0 | F53: 0 | G53: -20 | H53: -15 | I53: -18 | J53: 0 | K53: 0 | L53: 0 | M53: 0 | N53: 0
B54: Exceptional CF items | C54: 88 | D54: -1 | E54: -26 | F54: -21 | G54: 0 | H54: 0 | I54: 0 | J54: 0 | K54: 0 | L54: 0 | M54: 0 | N54: 0
B55: Cash from Investing Activity - | C55: -865 | D55: -494 | E55: -1236 | F55: -622 | G55: -2243 | H55: -336 | I55: 274 | J55: -552 | K55: -292 | L55: -844 | M55: -1754 | N55: -3435
... B76: Net Cash Flow | C76: 237 | D76: 1 | E76: -221 | F76: 23 | G76: 282 | H76: 3 | I76: -36 | J76: -259 | K76: -79 | L76: 227 | M76: -398 | N76: 41

Sheet List of Stocks
A2: COMPANY_NAME | B2: BSE | C2: NSE | D2: Industry
A3: 20 MICRONS LTD | B3: 533022 | C3: 20MICRONS | D3: Mining
A4: 21ST CENTURY MANAGEMENT SERVICES LTD | B4: 526921 | C4: 21STCENMGM | D4: Other Financial Services
A5: 3I INFOTECH LTD | B5: 532628 | C5: 3IINFOTECH | D5: IT Consulting & Software
A6: 3M (INDIA) LTD | B6: 523395 | C6: 3M(INDIA) | D6: Diversified
A7: 3M INDIA LTD | B7: 523395 | C7: 3MINDIA | D7: Diversified
A8: 3P LAND HOLDINGS LTD | B8: 516092 | C8: 3PLAND | D8: Paper & Paper Products
A9: 5PAISA CAPITAL LTD | B9: 540776 | C9: 5PAISA | D9: Other Financial Services
A10: 63 MOONS TECHNOLOGIES LTD | B10: 526881 | C10: 63MOONS | D10: IT Consulting & Software
A11: 7NR RETAIL LTD | B11: 540615 | C11: Not Listed | D11: Specialty Retail
A12: 7SEAS ENTERTAINMENT LTD | B12: 540874 | C12: Not Listed | D12: Movies & Entertainment
A13: 8K MILES SOFTWARE SERVICES LTD | B13: 512161 | C13: 8KMILES | D13: Internet Software & Services
A14: A & M FEBCON LTD | B14: 540697 | C14: Not Listed | D14: Industrial Machinery
A15: A AND M JUMBO BAGS LTD | B15: Not Listed | C15: AMJUMBO | D15: SME
A16: A INFRASTRUCTURE LTD | B16: 539620 | C16: Not Listed | D16: Cement & Cement Products
A17: A K SPINTEX LTD | B17: 539300 | C17: Not Listed | D17: Textiles
A18: A K CAPITAL SERVICES LTD | B18: 530499 | C18: Not Listed | D18: Finance (including NBFCs)
A19: A.F. Enterprises Ltd | B19: 538351 | C19: AFEL | D19: Investment Companies
A20: A-1 ACID LTD | B20: 542012 | C20: Not Listed | D20: Comm.Trading & Distribution
A21: A2Z INFRA ENGINEERING LTD | B21: 533292 | C21: A2ZINFRA | D21: Utilities:Non-Elec.
A22: AADHAAR VENTURES (INDIA) LTD | B22: 531611 | C22: Not Listed | D22: Finance (including NBFCs)
A23: AADHAAR VENTURES INDIA LTD | B23: 531611 | C23: Not Listed | D23: Finance (including NBFCs)
A24: AAKASH EXPLORATION SERVICES LTD | B24: Not Listed | C24: AAKASH | D24: SME
A25: AANANDA LAKSHMI SPINNING MILLS LTD | B25: 539096 | C25: Not Listed | D25: Textiles
A26: AANCHAL ISPAT LTD | B26: 538812 | C26: Not Listed | D26: Iron & Steel/Interm.Products
A27: AAR COMMERCIAL COMPANY LTD | B27: 539632 | C27: Not Listed | D27: Distributors
A28: Aar Shyam India Investment Company Ltd | B28: 542377 | C28: AARSHYAM | D28: Finance (including NBFCs)
A29: AAREY DRUGS & PHARMACEUTICALS LTD | B29: 524412 | C29: Not Listed | D29: Pharmaceuticals
A30: AARON INDUSTRIES LTD | B30: Not Listed | C30: AARON | D30: SME
A31: Aartech Solonics Ltd | B31: 542580 | C31: AARTECH | D31: Heavy Electrical Equipment
A32: AARTI DRUGS LTD | B32: 524348 | C32: AARTIDRUGS | D32: Pharmaceuticals
A33: AARTI INDUSTRIES LTD | B33: 524208 | C33: AARTIIND | D33: Commodity Chemicals
A34: AARV INFRATEL LTD | B34: 526488 | C34: Not Listed | D34: Textiles
A35: AARVEE DENIMS & EXPORTS LTD | B35: 514274 | C35: AARVEEDEN | D35: Textiles
A36: AARVI ENCON LTD | B36: Not Listed | C36: AARVI | D36: SME
A37: AASHEE INFOTECH LTD | B37: 519319 | C37: Not Listed | D37: Internet Software & Services
A38: AASWA TRADING & EXPORTS LTD | B38: 512038 | C38: Not Listed | D38: Comm.Trading & Distribution
A39: AAVAS FINANCIERS LTD | B39: 541988 | C39: AAVAS | D39: Housing Finance
A40: AAYUSH FOOD AND HERBS LTD | B40: 539528 | C40: Not Listed | D40: Packaged Foods
A41: ABAN OFFSHORE LTD | B41: 523204 | C41: ABAN | D41: Exploration & Production
A42: ABANS ENTERPRISES LTD | B42: 512165 | C42: Not Listed | D42: Comm.Trading & Distribution
A43: ABB INDIA LTD | B43: 500002 | C43: ABB | D43: Heavy Electrical Equipment
A44: ABBOTT (INDIA) LTD | B44: 500488 | C44: ABBOT(INDIA) | D44: Pharmaceuticals
A45: ABBOTT INDIA LTD | B45: 500488 | C45: ABBOTINDIA | D45: Pharmaceuticals
A46: ABC (INDIA) LTD | B46: 520123 | C46: Not Listed | D46: Surface Transportation
A47: ABC GAS INTERNATIONAL LTD | B47: 513119 | C47: Not Listed | D47: Copper
A48: ABC INDIA LTD | B48: 520123 | C48: Not Listed | D48: Surface Transportation
... A56: ABIRAMI FINANCIAL SERVICES INDIA LTD | B56: 511756 | C56: Not Listed | D56: Finance (including NBFCs)
A57: ABM INTERNATIONAL LTD | B57: Not Listed | C57: ABMINTLTD | D57: Others
A58: ABM KNOWLEDGEWARE LTD | B58: 531161 | C58: Not Listed | D58: IT Software Products
A59: ACC LTD | B59: 500410 | C59: ACC | D59: Cement & Cement Products
A60: ACCEL LTD | B60: 517494 | C60: Not Listed | D60: Storage Media & Peripherals
A61: ACCELYA KALE SOLUTIONS LTD | B61: 532268 | C61: ACCELYA | D61: IT Consulting & Software
A62: ACCORD SYNERGY LTD | B62: Not Listed | C62: ACCORD | D62: SME
A63: ACCURACY SHIPPING LTD | B63: Not Listed | C63: ACCURACY | D63: SME
A64: ACE EDUTREND LTD | B64: 530093 | C64: Not Listed | D64: Education
A65: ACE INTEGRATED SOLUTIONS LTD | B65: Not Listed | C65: ACEINTEG | D65: SME
A66: ACE MEN ENGG WORKS LTD | B66: 539661 | C66: Not Listed | D66: Distributors
A67: ACE SOFTWARE EXPORTS LTD | B67: 531525 | C67: Not Listed | D67: IT Software Products
A68: Achal Investments Ltd | B68: 538570 | C68: ACHAL | D68: Other Financial Services
A69: ACI INFOCOM LTD | B69: 517356 | C69: Not Listed | D69: Storage Media & Peripherals
A70: ACKNIT INDUSTRIES LTD | B70: 530043 | C70: Not Listed | D70: Other Apparels & Accessories
A71: ACME RESOURCES LTD | B71: 539391 | C71: Not Listed | D71: Finance (including NBFCs)
A72: ACROW INDIA LTD. | B72: 513149 | C72: ACROW | D72: Iron &amp; Steel Products
A73: ACRYSIL LTD | B73: 524091 | C73: Not Listed | D73: Plastic Products
A74: ACTION CONSTRUCTION EQUIPMENT LTD | B74: 532762 | C74: ACE | D74: Transport Related Services
A75: ACTION FINANCIAL SERVICES (INDIA) LTD | B75: 511706 | C75: Not Listed | D75: Other Financial Services
A76: ACTION FINANCIAL SERVICES INDIA LTD | B76: 511706 | C76: Not Listed | D76: Other Financial Services
A77: ACTIVE CLOTHING CO LTD | B77: 541144 | C77: Not Listed | D77: Other Apparels & Accessories
... A135: AGRI-TECH INDIA LTD | B135: 537292 | C135: AGRITECH | D135: Other Agricultural Products
A136: AGRO PHOS (INDIA) LTD | B136: Not Listed | C136: AGROPHOS | D136: SME
A137: AGRO PHOS INDIA LTD | B137: Not Listed | C137: AGROPHOS | D137: SME
A138: AGRO TECH FOODS LTD | B138: 500215 | C138: ATFL | D138: Other Agricultural Products
A139: AHIMSA INDUSTRIES LTD | B139: Not Listed | C139: AHIMSA | D139: SME
A140: AHLADA ENGINEERS LTD | B140: Not Listed | C140: AHLADA | D140: SME
A141: AHLUWALIA CONTRACTS (INDIA) LTD | B141: 532811 | C141: AHLUCONT | D141: Realty
A142: AHLUWALIA CONTRACTS INDIA LTD | B142: 532811 | C142: AHLUCONT | D142: Realty
A143: AHMEDABAD STEELCRAFT LTD | B143: 522273 | C143: Not Listed | D143: Iron & Steel/Interm.Products
A144: AI CHAMPDANY INDUSTRIES LTD | B144: 532806 | C144: Not Listed | D144: Jute & Jute Products
A145: AIA ENGINEERING LTD | B145: 532683 | C145: AIAENG | D145: Other Industrial Goods
A146: AIMCO PESTICIDES LTD | B146: 524288 | C146: Not Listed | D146: Agrochemicals
A147: AIRAN LTD | B147: Not Listed | C147: AIRAN | D147: SME
A148: AIRO LAM LTD | B148: Not Listed | C148: AIROLAM | D148: SME
A149: AISHWARYA TELECOM LTD | B149: 532975 | C149: Not Listed | D149: Telecom Equipment
A150: AJANTA PHARMA LTD | B150: 532331 | C150: AJANTPHARM | D150: Pharmaceuticals
A151: AJANTA SOYA LTD | B151: 519216 | C151: Not Listed | D151: Edible Oils
A152: AJCON GLOBAL SERVICES LTD | B152: 511692 | C152: Not Listed | D152: Other Financial Services
A153: AJEL LTD | B153: 530713 | C153: Not Listed | D153: IT Consulting & Software
A154: AJMERA REALTY & INFRA (INDIA) LTD | B154: 513349 | C154: AJMERA | D154: Realty
A155: AJMERA REALTY & INFRA INDIA LTD | B155: 513349 | C155: AJMERA | D155: Realty
A156: AJOONI BIOTECH LTD | B156: Not Listed | C156: AJOONI | D156: SME
A157: AJWA FUN WORLD & RESORT LTD | B157: 526628 | C157: Not Listed | D157: Other Leisure Facilities
A158: AKAR AUTO INDUSTRIES LTD | B158: 530621 | C158: Not Listed | D158: Industrial Machinery
A159: AKASH INFRA PROJECTS LTD | B159: Not Listed | C159: AKASH | D159: SME
A160: AKASHDEEP METAL INDUSTRIES LTD | B160: 538778 | C160: Not Listed | D160: Finance (including NBFCs)
A161: AKG EXIM LTD | B161: Not Listed | C161: AKG | D161: SME
A162: AKI (INDIA) LTD | B162: 542020 | C162: Not Listed | D162: Other Apparels & Accessories
A163: AKI INDIA LTD | B163: 542020 | C163: Not Listed | D163: Other Apparels & Accessories
A164: AKM LACE AND EMBROTEX LTD | B164: 540718 | C164: Not Listed | D164: Textiles
A165: AKME STAR HOUSING FINANCE LTD | B165: 539017 | C165: Not Listed | D165: Housing Finance
...

Sheet Relative Data
B2: S.No. | C2: Name | D2: CMP Rs. | E2: No. Eq. Shares Cr. | F2: Market Cap | G2: Debt Rs.Cr. | H2: Cash End Rs.Cr. | I2: EV | J2: Sales Rs.Cr. | K2: EBITDA | L2: NP 12M Rs.Cr. | M2: EV / EBITDA
B3: 1 | C3: Godrej Consumer | D3: 1181.1 | E3: 102.3 | F3: =D3*E3 -> 120826.53 | G3: 3828.47 | H3: 546.94 | I3: =F3+G3-H3 -> 124108.06 | J3: 14043.16 | K3: =I3/M3 -> 3371.5854 | L3: -370.15 | M3: 36.81
B4: 2 | C4: Dabur India | D4: 521.15 | E4: 177.23 | F4: =D4*E4 -> 92363.414 | G4: 1751.62 | H4: 666.36 | I4: =F4+G4-H4 -> 93448.674 | J4: 12447.4 | K4: =I4/M4 -> 2878.8871 | L4: 1759.53 | M4: 32.46
B5: 3 | C5: Emami | D5: 595.75 | E5: 43.65 | F5: =D5*E5 -> 26004.487 | G5: 74.39 | H5: 201.38 | I5: =F5+G5-H5 -> 25877.497 | J5: 3684.22 | K5: =I5/M5 -> 1045.1332 | L5: 768.99 | M5: 24.76
B6: 4 | C6: Jyothy Labs | D6: 408.1 | E6: 36.72 | F6: =D6*E6 -> 14985.432 | G6: 55.87 | H6: 166.05 | I6: =F6+G6-H6 -> 14875.252 | J6: 2813.06 | K6: =I6/M6 -> 547.48811 | L6: 375.78 | M6: 27.17
B7: 5 | C7: Bajaj Consumer | D7: 195.24 | E7: 14.28 | F7: =D7*E7 -> 2788.0272 | G7: 6.39 | H7: 44.35 | I7: =F7+G7-H7 -> 2750.0672 | J7: 959.03 | K7: =I7/M7 -> 182.00312 | L7: 140.9 | M7: 15.11
B15: 6 | C15: Yash Optics | D15: 86 | E15: 2.48 | F15: =D15*E15 -> 213.28 | G15: 16.41 | H15: 0.85 | I15: =F15+G15-H15 -> 228.84 | J15: 41.93 | K15: =I15/M15 -> 17.603077 | L15: 9.28 | M15: 13
B16: 7 | C16: JHS Sven.Lab. | D16: 20.5 | E16: 8.56 | F16: =D16*E16 -> 175.48 | G16: 4.29 | H16: 10.36 | I16: =F16+G16-H16 -> 169.41 | J16: 80.12 | K16: =I16/M16 -> 6.5739232 | L16: -11.69 | M16: 25.77
B17: 8 | C17: GKB Ophthalmics | D17: 97.1 | E17: 0.5 | F17: =D17*E17 -> 48.55 | G17: 12.35 | H17: 17.84 | I17: =F17+G17-H17 -> 43.06 | J17: 97.76 | K17: =I17/M17 -> 1.8062081 | L17: -3.37 | M17: 23.84
B18: 9 | C18: Paramount Cosmet | D18: 47.8 | E18: 0.49 | F18: =D18*E18 -> 23.422 | G18: 12.13 | H18: 1.48 | I18: =F18+G18-H18 -> 34.072 | J18: 20.23 | K18: =I18/M18 -> 2.1925354 | L18: -0.16 | M18: 15.54
B19: 10 | C19: Novateor Resear. | D19: 42.85 | E19: 0.48 | F19: =D19*E19 -> 20.568 | G19: 0.73 | H19: 0.09 | I19: =F19+G19-H19 -> 21.208 | J19: 1.64 | K19: =I19/M19 -> 0.2182342 | L19: 0.05 | M19: 97.18
B20: 11 | C20: Ador Multi Prod. | D20: 30.57 | E20: 0.47 | F20: =D20*E20 -> 14.3679 | G20: 0 | H20: 0.07 | I20: =F20+G20-H20 -> 14.2979 | J20: 2.87 | K20: =I20/M20 -> -0.66041109 | L20: 1.66 | M20: -21.65
